Workbook
Name CurMonth: 'FACTORY COST'!$G$2
Name CurYear: 'FACTORY COST'!$BW$7
Name ProductionRRT: 'MFG COST SUMMARY'!$J$134
Name ProductionVolume: 'MFG COST SUMMARY'!$F$134
Name PrvMonthProductionRRT: 'FACTORY COST'!$AI$3

Sheet Guideline
A1: Guideline
A3: A. Data
B4: 1. STD:
C5: - Periodic: update new standard cost by Jan & Jul (if any)
C6: - Monthly: update additional product cost
B7: 2. ZVF59 (sheet has name of month: Jan, Feb…):
C8: - Check account 911330: balance is zero
C9: - Check & confirm all documents have been posted into system
C10: - Export data by T-code ZVF59 and copy to sheet of each month
M11: Document type: ZT (default)
M12: WIP Account: 132000 (default)
M13: Posting Date for Transfer, Posting Date: input as month period
M14: Exclusive Document Type: ZT (default)
M15: G/L Account: there was default manufactoring cost accounts (VAS 621 - 627). Add new account if any
M16: Functional Area:
M27: Download file: Location to save exported ZVF59 txt file
B32: 3. Direct material (sheet Tire Weight, DM-Sum)
C33: - Update theoretical DM from file DM calculation
C34: - Update Tyre weight tolerance from TS dept.
B35: 4. Rework tire
C36: - Update rework tire data from below link
C37: Rework tire 2023
B38: 5. Budget
C39: - Update budget (OB/RBAC) production volume and RRT
A41: B. Calculation
B42: 1. FACTORY COST
C43: - Choose month (refer to name CurMonth), year (refer to CurYear)
C44: - Update Production RRT of previous month (refer to name PrvMonthProductionRRT) to check gap vs previous month
C45: - Update budget (OB/RBAC) data in columns AT -> BE
C46: - Ensure total amount transfer in ZVF59 equal total actual amount in Factory cost:
D47: If amounts are different, please check:
D48: + New/change account number
D49: + Check formulas of sheet "Factory cost"
C50: - Check and comment for gap of each item (vs OB/RBAC and vs Previous month)
B51: 2. MFG COST SUMMARY
C52: - Update products produced in month based on FG inventory report
C53: Note: insert new line upper last product line to maintain sum formula
C54: - Check and comment for all gap and different trend
C55: - Update Ticket production volume and RRT (from PP-IE)
B56: 3. COGM upload
C57: - Ensure data correct with sheet "MFG COST SUMMARY"
C58: - Update rework tire from sheet "Rework"
B59: 4. Check with ZVF51
C60: After uploading to ZVF51, check the adjustment of "GOODS RECEIPT (COGM - PREDETERMINED)" equal Actual vs standard in sheet "MFG COST SUMMARY"
B61: 5. Report
C62: This sheet supports management reports as FC Analysis, AIP Report…

Sheet Data

Sheet STD
B1: BTMV 2024 Standard
B2: Update std in Jan & Jul
B3: \\10.118.29.7\BTMV-Data\4-ACCOUNTING\71.Costing\5.Standard & TPL\TPL\2023\Additional\ | P3: 2023 OB
P4: DM | T4: CC | U4: WS | V4: FC | W4: OPEX% | X4: Royalty% | Z4: TPL price
C5: BPC | D5: Description | E5: LI/SP | F5: Section | G5: Rim | H5: Pattern | I5: Brand name | J5: Brand category | K5: MTP group | L5: BTMV code | M5: M3 | N5: Tire weight g/tire | O5: RRW g/tire | Q5: LB | R5: Dep. | S5: Other | X5: BSJ | Y5: BSCAP | Z5: BSJ | AA5: BSCAP
C6: 300105689 | D6: 81W 195/45R17 RE005 | E6: 81W | F6: 195/45 | G6: 17 | H6: RE005 | I6: BRIDGESTONE | J6: BS | K6: PSR2 | M6: 0.056456094 | N6: 8832 | O6: 4115 | P6: 19.434096 | Q6: 5.6798664 | R6: 7.7709226 | S6: 6.9204876 | T6: 20.371277 | U6: 0.54031432 | V6: 40.345687 | W6: 0.047 | X6: 0 | Y6: 0.04 | Z6: 43.71 | AA6: 45.69 | AB6: =V6-P6-Q6-R6-S6-U6 -> 2.4424907e-15 | AC6: =T6-SUM(Q6:S6) -> 0
C7: 300105830 | D7: 96W 225/45R19 RE005 | E7: 96W | F7: 225/45 | G7: 19 | H7: RE005 | I7: BRIDGESTONE | J7: BS | K7: PSR2 | M7: 0.082901065 | N7: 12566 | O7: 5887 | P7: 26.65072 | Q7: 7.0321532 | R7: 9.5062235 | S7: 8.7901863 | T7: 25.328563 | U7: 0.76874884 | V7: 52.748032 | W7: 0.047 | X7: 0 | Y7: 0.04 | Z7: 57.15 | AA7: 59.74 | AB7: =V7-P7-Q7-R7-S7-U7 -> -2.553513e-15 | AC7: =T7-SUM(Q7:S7) -> 0
C8: 300110512 | D8: 93W 215/45R18 PT005A | E8: 93W | F8: 215/45 | G8: 18 | H8: PT005A | I8: BRIDGESTONE | J8: BS | K8: PSR2 | M8: 0.071461105 | N8: 12295 | O8: 5722 | P8: 23.51189 | Q8: 6.5702044 | R8: 8.6541574 | S8: 8.0078482 | T8: 23.23221 | U8: 0.7521699 | V8: 47.49627 | W8: 0.047 | X8: 0 | Y8: 0.04 | Z8: 51.46 | AA8: 53.79 | AB8: =V8-P8-Q8-R8-S8-U8 -> 9.9920072e-16 | AC8: =T8-SUM(Q8:S8) -> 0
C9: 300115807 | D9: 93W 215/45R18 PT005A | E9: 93W | F9: 215/45 | G9: 18 | H9: PT005A | I9: BRIDGESTONE | J9: BS | K9: PSR2 | M9: 0.071461105 | N9: 11009 | O9: 4809 | P9: 23.588244 | Q9: 6.2719431 | R9: 8.6882074 | S9: 7.9301246 | T9: 22.890275 | U9: 0.67349642 | V9: 47.152015 | W9: 0.047 | X9: 0 | Y9: 0.04 | Z9: 51.09 | AA9: 53.4 | AB9: =V9-P9-Q9-R9-S9-U9 -> -3.8857806e-15 | AC9: =T9-SUM(Q9:S9) -> 0
C10: 300119530 | D10: 91V 205/55R16 P-EP15 | E10: 91V | F10: 205/55 | G10: 16 | H10: P-EP15 | I10: BRIDGESTONE | J10: BS | K10: PSR3 | M10: 0.064256968 | N10: 10090 | O10: 4832 | P10: 19.877298 | Q10: 5.9375767 | R10: 7.6737609 | S10: 7.0057664 | T10: 20.617104 | U10: 0.61727485 | V10: 41.111677 | W10: 0.047 | X10: 0 | Y10: 0.04 | Z10: 44.54 | AA10: 46.56 | AB10: =V10-P10-Q10-R10-S10-U10 -> -2.220446e-15 | AC10: =T10-SUM(Q10:S10) -> 0
C11: 300123416 | D11: 96H 215/60R17 EL64Z | E11: 96H | F11: 215/60 | G11: 17 | H11: EL64Z | I11: BRIDGESTONE | J11: BS | K11: PSR2 | M11: 0.080307202 | N11: 12313 | O11: 5583 | P11: 26.280589 | Q11: 6.6133977 | R11: 8.7613298 | S11: 8.1493412 | T11: 23.524069 | U11: 0.75327109 | V11: 50.557929 | W11: 0.047 | X11: 0 | Y11: 0.04 | Z11: 54.78 | AA11: 57.26 | AB11: =V11-P11-Q11-R11-S11-U11 -> 2.6645353e-15 | AC11: =T11-SUM(Q11:S11) -> 0
C12: 300123417 | D12: 95V 215/55R18 DTH1AZ | E12: 95V | F12: 215/55 | G12: 18 | H12: DTH1AZ | I12: BRIDGESTONE | J12: BS | K12: PSR2 | M12: 0.081217853 | N12: 12073 | O12: 5650 | P12: 24.230519 | Q12: 6.7748712 | R12: 9.1917312 | S12: 8.4601627 | T12: 24.426765 | U12: 0.73858863 | V12: 49.395873 | W12: 0.047 | X12: 0 | Y12: 0.04 | Z12: 53.52 | AA12: 55.94 | AB12: =V12-P12-Q12-R12-S12-U12 -> -9.2148511e-15 | AC12: =T12-SUM(Q12:S12) -> 0
C13: 300123424 | D13: 245/45R20 AL011Z | F13: 245/45 | G13: 20 | H13: AL011Z | I13: BRIDGESTONE | J13: BS | K13: PSR2 | M13: 0.10206923 | N13: 15095 | O13: 6959 | P13: 31.903354 | Q13: 7.9098713 | R13: 10.565309 | S13: 9.946525 | T13: 28.421706 | U13: 0.92346521 | V13: 61.248525 | W13: 0.047 | X13: 0 | Y13: 0.04 | Z13: 66.36 | AA13: 69.36 | AB13: =V13-P13-Q13-R13-S13-U13 -> 6.2172489e-15 | AC13: =T13-SUM(Q13:S13) -> 0
C14: 300123425 | D14: 225/55R19 AL011Z | F14: 225/55 | G14: 19 | H14: AL011Z | I14: BRIDGESTONE | J14: BS | K14: PSR2 | M14: 0.094149252 | N14: 12566 | O14: 5887 | P14: 26.648953 | Q14: 7.0321532 | R14: 9.5062235 | S14: 8.7901863 | T14: 25.328563 | U14: 0.76874884 | V14: 52.746265 | W14: 0.047 | X14: 0 | Y14: 0.04 | Z14: 57.15 | AA14: 59.74 | AB14: =V14-P14-Q14-R14-S14-U14 -> -6.1062266e-15 | AC14: =T14-SUM(Q14:S14) -> 0
C15: 300125819 | D15: 99V 225/55R19 AL01 | E15: 99V | F15: 225/55 | G15: 19 | H15: AL01 | I15: BRIDGESTONE | J15: BS | K15: PSR2 | M15: 0.094149252 | N15: 12566 | O15: 5887 | P15: 26.646953 | Q15: 7.0321532 | R15: 9.5062235 | S15: 8.7901863 | T15: 25.328563 | U15: 0.76874884 | V15: 52.744265 | W15: 0.047 | X15: 0 | Y15: 0.04 | Z15: 57.14 | AA15: 59.73 | AB15: =V15-P15-Q15-R15-S15-U15 -> -2.7755576e-15 | AC15: =T15-SUM(Q15:S15) -> 0
C16: 300125820 | D16: 101W 235/55R19 AL01 | E16: 101W | F16: 235/55 | G16: 19 | H16: AL01 | I16: BRIDGESTONE | J16: BS | K16: PSR2 | M16: 0.10131906 | N16: 13665 | O16: 6288 | P16: 29.182018 | Q16: 7.452603 | R16: 10.013683 | S16: 9.367666 | T16: 26.833952 | U16: 0.83598225 | V16: 56.851952 | W16: 0.047 | X16: 0 | Y16: 0.04 | Z16: 61.59 | AA16: 64.38 | AB16: =V16-P16-Q16-R16-S16-U16 -> 1.4432899e-15 | AC16: =T16-SUM(Q16:S16) -> 0
C17: PSR0V01B | D17: 79S 155/80R13 SL10Z | E17: 79S | F17: 155/80 | G17: 13 | H17: SL10Z | I17: SEIBERLING | J17: FS&D | K17: PSR5 | L17: GSGVA | M17: 0.040677807 | N17: 5367 | O17: 2520 | P17: 10.498264 | Q17: 4.1208603 | R17: 5.3369935 | S17: 4.5629747 | T17: 14.020829 | U17: 0.32833639 | V17: 24.847428 | W17: 0.047 | X17: 0.0025 | Y17: 0.0325 | Z17: 26.99 | AA17: 27.9 | AB17: =V17-P17-Q17-R17-S17-U17 -> 3.4972025e-15 | AC17: =T17-SUM(Q17:S17) -> 0
C18: PSR0V01P | D18: 82H 175/65R14 BAR3Z | E18: 82H | F18: 175/65 | G18: 14 | H18: BAR3Z | I18: BOB JANE | J18: Others | K18: PSR5 | L18: R2DVA | M18: 0.046708271 | N18: 6435 | O18: 3133 | P18: 12.268556 | Q18: 4.5634788 | R18: 6.0224413 | S18: 5.2321611 | T18: 15.818081 | U18: 0.39367331 | V18: 28.48031 | W18: 0.047 | X18: 0 | Y18: 0.03 | Z18: 30.86 | AA18: 31.89 | AB18: =V18-P18-Q18-R18-S18-U18 -> 3.4972025e-15 | AC18: =T18-SUM(Q18:S18) -> 0
C19: PSR0V01S | D19: 82H 175/65R14 SPCZ | E19: 82H | F19: 175/65 | G19: 14 | H19: SPCZ | I19: SUPERCAT | J19: Others | K19: PSR5 | L19: P2PVA | M19: 0.046708271 | N19: 7043 | O19: 3404 | P19: 13.651433 | Q19: 4.7381973 | R19: 6.2042895 | S19: 5.4533965 | T19: 16.395883 | U19: 0.43086886 | V19: 30.478185 | W19: 0.047 | X19: 0 | Y19: 0.03 | Z19: 33.02 | AA19: 34.13 | AB19: =V19-P19-Q19-R19-S19-U19 -> -3.663736e-15 | AC19: =T19-SUM(Q19:S19) -> 0
C20: PSR0V02P | D20: 95H 205/65R15 BAR3Z | E20: 95H | F20: 205/65 | G20: 15 | H20: BAR3Z | I20: BOB JANE | J20: Others | K20: PSR4 | L20: QP3VA | M20: 0.067468812 | N20: 8892 | O20: 4138 | P20: 17.492648 | Q20: 5.2585929 | R20: 6.9017625 | S20: 6.2427863 | T20: 18.403142 | U20: 0.54398494 | V20: 36.439775 | W20: 0.047 | X20: 0 | Y20: 0.03 | Z20: 39.48 | AA20: 40.81 | AB20: =V20-P20-Q20-R20-S20-U20 -> 0 | AC20: =T20-SUM(Q20:S20) -> 0
C21: PSR0V03P | D21: 95V 215/60R16 BAR3Z | E21: 95V | F21: 215/60 | G21: 16 | H21: BAR3Z | I21: BOB JANE | J21: Others | K21: PSR3 | L21: BJTVA | M21: 0.074501903 | N21: 10023 | O21: 4806 | P21: 19.512107 | Q21: 5.7764243 | R21: 7.6670462 | S21: 7.0383375 | T21: 20.481808 | U21: 0.613176 | V21: 40.607091 | W21: 0.047 | X21: 0 | Y21: 0.03 | Z21: 43.99 | AA21: 45.47 | AB21: =V21-P21-Q21-R21-S21-U21 -> -4.4408921e-15 | AC21: =T21-SUM(Q21:S21) -> 0
C22: PSR0V03S | D22: 86H 185/65R14 SPCZ | E22: 86H | F22: 185/65 | G22: 14 | H22: SPCZ | I22: SUPERCAT | J22: Others | K22: PSR5 | L22: VVVVA | M22: 0.051603556 | N22: 7502 | O22: 3592 | P22: 14.562613 | Q22: 4.8958896 | R22: 6.4574514 | S22: 5.7103715 | T22: 17.063712 | U22: 0.45894905 | V22: 32.085275 | W22: 0.047 | X22: 0 | Y22: 0.03 | Z22: 34.76 | AA22: 35.93 | AB22: =V22-P22-Q22-R22-S22-U22 -> 7.8270723e-15 | AC22: =T22-SUM(Q22:S22) -> 0
C23: PSR0V04S | D23: 88H 195/60R15 SPCZ | E23: 88H | F23: 195/60 | G23: 15 | H23: SPCZ | I23: SUPERCAT | J23: Others | K23: PSR4 | L23: 3MCVA | M23: 0.057896792 | N23: 8461 | O23: 4040 | P23: 16.360694 | Q23: 5.1693219 | R23: 6.7486861 | S23: 6.0492842 | T23: 17.967292 | U23: 0.51761769 | V23: 34.845604 | W23: 0.047 | X23: 0 | Y23: 0.03 | Z23: 37.75 | AA23: 39.02 | AB23: =V23-P23-Q23-R23-S23-U23 -> 2.9976022e-15 | AC23: =T23-SUM(Q23:S23) -> 0
C24: PSR0V05B | D24: 88S 185/65R15 SL10Z | E24: 88S | F24: 185/65 | G24: 15 | H24: SL10Z | I24: SEIBERLING | J24: FS&D | K24: PSR4 | L24: EHSVA | M24: 0.056094935 | N24: 7509 | O24: 3497 | P24: 14.796449 | Q24: 4.9094159 | R24: 6.2805441 | S24: 5.5627509 | T24: 16.752711 | U24: 0.45937729 | V24: 32.008537 | W24: 0.047 | X24: 0.0025 | Y24: 0.0325 | Z24: 34.77 | AA24: 35.94 | AB24: =V24-P24-Q24-R24-S24-U24 -> -7.6605389e-15 | AC24: =T24-SUM(Q24:S24) -> 0
C25: PSR0V05P | D25: 88H 185/65R15 BAR3Z | E25: 88H | F25: 185/65 | G25: 15 | H25: BAR3Z | I25: BOB JANE | J25: Others | K25: PSR4 | L25: JZTVA | M25: 0.056094935 | N25: 7506 | O25: 3648 | P25: 14.326674 | Q25: 4.8805642 | R25: 6.4500862 | S25: 5.697528 | T25: 17.028178 | U25: 0.45919376 | V25: 31.814046 | W25: 0.047 | X25: 0 | Y25: 0.03 | Z25: 34.47 | AA25: 35.63 | AB25: =V25-P25-Q25-R25-S25-U25 -> -5.7176486e-15 | AC25: =T25-SUM(Q25:S25) -> 0
C26: PSR0V05S | D26: 91H 195/65R15 SPCZ | E26: 91H | F26: 195/65 | G26: 15 | H26: SPCZ | I26: SUPERCAT | J26: Others | K26: PSR4 | L26: YYYVA | M26: 0.061626503 | N26: 8584 | O26: 4086 | P26: 16.617401 | Q26: 5.1823032 | R26: 6.8236052 | S26: 6.1345046 | T26: 18.140413 | U26: 0.52514245 | V26: 35.282957 | W26: 0.047 | X26: 0 | Y26: 0.03 | Z26: 38.23 | AA26: 39.51 | AB26: =V26-P26-Q26-R26-S26-U26 -> -9.9920072e-16 | AC26: =T26-SUM(Q26:S26) -> 0
C27: PSR0V06P | D27: 84H 185/60R15 BAR3Z | E27: 84H | F27: 185/60 | G27: 15 | H27: BAR3Z | I27: BOB JANE | J27: Others | K27: PSR4 | L27: WBPVA | M27: 0.052805117 | N27: 7386 | O27: 3583 | P27: 14.069269 | Q27: 4.8358962 | R27: 6.5506707 | S27: 5.7690098 | T27: 17.155577 | U27: 0.45185253 | V27: 31.676699 | W27: 0.047 | X27: 0 | Y27: 0.03 | Z27: 34.32 | AA27: 35.47 | AB27: =V27-P27-Q27-R27-S27-U27 -> -7.7715612e-16 | AC27: =T27-SUM(Q27:S27) -> 0
C28: PSR0V07S | D28: 95V 215/60R16 SPCZ | E28: 95V | F28: 215/60 | G28: 16 | H28: SPCZ | I28: SUPERCAT | J28: Others | K28: PSR3 | L28: F91VA | M28: 0.074501903 | N28: 10732 | O28: 5097 | P28: 21.181023 | Q28: 5.9755221 | R28: 7.7986882 | S28: 7.2104738 | T28: 20.984684 | U28: 0.65655042 | V28: 42.822257 | W28: 0.047 | X28: 0 | Y28: 0.03 | Z28: 46.39 | AA28: 47.95 | AB28: =V28-P28-Q28-R28-S28-U28 -> -2.220446e-15 | AC28: =T28-SUM(Q28:S28) -> 0
... C41: PSR0V13D | D41: 102V 225/65R17 DTH1AZ | E41: 102V | F41: 225/65 | G41: 17 | H41: DTH1AZ | I41: DAYTON | J41: FS&D | K41: PSR2 | L41: AMMZA | M41: 0.092659328 | N41: 12352 | O41: 5741 | P41: 24.465164 | Q41: 6.7996527 | R41: 8.7557017 | S41: 8.1510522 | T41: 23.706407 | U41: 0.75565699 | V41: 48.927227 | W41: 0.047 | X41: 0.0025 | Y41: 0.0325 | Z41: 53.15 | AA41: 54.94 | AB41: =V41-P41-Q41-R41-S41-U41 -> 0 | AC41: =T41-SUM(Q41:S41) -> 0
C42: PSR0V143 | D42: 175/50R15 150KZ | F42: 175/50 | G42: 15 | H42: 150KZ | I42: BRIDGESTONE | J42: BS | K42: PSR4 | L42: KCEVA | M42: 0.042467558 | N42: 6951 | O42: 3383 | P42: 13.622983 | Q42: 4.7963971 | R42: 6.7727014 | S42: 5.9258298 | T42: 17.494928 | U42: 0.42524059 | V42: 31.543152 | W42: 0.047 | X42: 0 | Y42: 0.04 | Z42: 34.17 | AA42: 35.72 | AB42: =V42-P42-Q42-R42-S42-U42 -> -2.553513e-15 | AC42: =T42-SUM(Q42:S42) -> 0
C43: PSR0V145 | D43: 98V 225/60R16 EP3AZ | E43: 98V | F43: 225/60 | G43: 16 | H43: EP3AZ | I43: BRIDGESTONE | J43: BS | K43: PSR3 | L43: KPXVA | M43: 0.080808933 | N43: 9731 | O43: 4767 | P43: 20.175765 | Q43: 5.7498507 | R43: 7.7718118 | S43: 7.1095965 | T43: 20.631259 | U43: 0.59531235 | V43: 41.402336 | W43: 0.047 | X43: 0 | Y43: 0.04 | Z43: 44.86 | AA43: 46.89 | AB43: =V43-P43-Q43-R43-S43-U43 -> 0 | AC43: =T43-SUM(Q43:S43) -> 0
C44: PSR0V14D | D44: 108V 235/65R17 DTH1AZ | E44: 108V | F44: 235/65 | G44: 17 | H44: DTH1AZ | I44: DAYTON | J44: FS&D | K44: PSR2 | L44: LCDZA | M44: 0.10028269 | N44: 13460 | O44: 6300 | P44: 26.97937 | Q44: 7.1210799 | R44: 9.3587767 | S44: 8.7692267 | T44: 25.249083 | U44: 0.82344098 | V44: 53.051894 | W44: 0.047 | X44: 0.0025 | Y44: 0.0325 | Z44: 57.63 | AA44: 59.58 | AB44: =V44-P44-Q44-R44-S44-U44 -> -1.8873791e-15 | AC44: =T44-SUM(Q44:S44) -> 0
C45: PSR0V150 | D45: 185/70R13 150EZ | F45: 185/70 | G45: 13 | H45: 150EZ | I45: BRIDGESTONE | J45: BS | K45: PSR5 | L45: ADXVA | M45: 0.069302044 | N45: 6682 | O45: 3258 | P45: 13.251737 | Q45: 4.576501 | R45: 6.2553497 | S45: 5.5474272 | T45: 16.379278 | U45: 0.408784 | V45: 30.039799 | W45: 0.047 | X45: 0 | Y45: 0.04 | Z45: 32.55 | AA45: 34.02 | AB45: =V45-P45-Q45-R45-S45-U45 -> -1.9984014e-15 | AC45: =T45-SUM(Q45:S45) -> 0
C46: PSR0V151 | D46: 079S 165/65R14 150EZ | E46: 079S | F46: 165/65 | G46: 14 | H46: 150EZ | I46: BRIDGESTONE | J46: BS | K46: PSR5 | L46: RBMVA | M46: 0.04209744 | N46: 6154 | O46: 2989 | P46: 12.159812 | Q46: 4.5374844 | R46: 6.404158 | S46: 5.5691661 | T46: 16.510808 | U46: 0.3764826 | V46: 29.047103 | W46: 0.047 | X46: 0 | Y46: 0.04 | Z46: 31.47 | AA46: 32.9 | AB46: =V46-P46-Q46-R46-S46-U46 -> 6.1617378e-15 | AC46: =T46-SUM(Q46:S46) -> 0
C47: PSR0V152 | D47: 079S 165/70R13 150EZ | E47: 079S | F47: 165/70 | G47: 13 | H47: 150EZ | I47: BRIDGESTONE | J47: BS | K47: PSR5 | L47: ECCVA | M47: 0.040793308 | N47: 5603 | O47: 2729 | P47: 11.137326 | Q47: 4.2505776 | R47: 5.7836344 | S47: 5.0055806 | T47: 15.039793 | U47: 0.34277413 | V47: 26.519892 | W47: 0.047 | X47: 0 | Y47: 0.04 | Z47: 28.73 | AA47: 30.03 | AB47: =V47-P47-Q47-R47-S47-U47 -> 1.2212453e-15 | AC47: =T47-SUM(Q47:S47) -> 0
C48: PSR0V15D | D48: 96H 215/60R17 DTH1AZ | E48: 96H | F48: 215/60 | G48: 17 | H48: DTH1AZ | I48: DAYTON | J48: FS&D | K48: PSR2 | L48: 7DTMA | M48: 0.080307202 | N48: 10819 | O48: 5070 | P48: 20.493922 | Q48: 6.1399529 | R48: 7.9502052 | S48: 7.2712386 | T48: 21.361397 | U48: 0.66187281 | V48: 42.517192 | W48: 0.047 | X48: 0.0025 | Y48: 0.0325 | Z48: 46.19 | AA48: 47.75 | AB48: =V48-P48-Q48-R48-S48-U48 -> 4.4408921e-15 | AC48: =T48-SUM(Q48:S48) -> 0
C49: PSR0V164 | D49: 235/40R18 EL64AZ | F49: 235/40 | G49: 18 | H49: EL64AZ | I49: BRIDGESTONE | J49: BS | K49: PSR2 | L49: SCLZA | M49: 0.076793814 | N49: 11557 | O49: 5130 | P49: 24.574951 | Q49: 6.4162461 | R49: 8.7451835 | S49: 8.0443157 | T49: 23.205745 | U49: 0.70702136 | V49: 48.487717 | W49: 0.047 | X49: 0 | Y49: 0.04 | Z49: 52.53 | AA49: 54.91 | AB49: =V49-P49-Q49-R49-S49-U49 -> 0 | AC49: =T49-SUM(Q49:S49) -> 0
C50: PSR0V165 | D50: 84H 185/60R15 EL64Z | E50: 84H | F50: 185/60 | G50: 15 | H50: EL64Z | I50: BRIDGESTONE | J50: BS | K50: PSR4 | L50: ZJFVA | M50: 0.052805117 | N50: 8512 | O50: 4025 | P50: 17.616776 | Q50: 5.1736425 | R50: 6.8716595 | S50: 6.2188652 | T50: 18.264167 | U50: 0.52073772 | V50: 36.401681 | W50: 0.047 | X50: 0 | Y50: 0.04 | Z50: 39.44 | AA50: 41.23 | AB50: =V50-P50-Q50-R50-S50-U50 -> 3.1086245e-15 | AC50: =T50-SUM(Q50:S50) -> 0
C51: PSR0V166 | D51: 88H 185/65R15 EL64Z | E51: 88H | F51: 185/65 | G51: 15 | H51: EL64Z | I51: BRIDGESTONE | J51: BS | K51: PSR4 | L51: QWAVA | M51: 0.056094935 | N51: 8809 | O51: 4150 | P51: 18.355228 | Q51: 5.2501029 | R51: 6.908503 | S51: 6.2863018 | T51: 18.444908 | U51: 0.53890725 | V51: 37.339043 | W51: 0.047 | X51: 0 | Y51: 0.04 | Z51: 40.45 | AA51: 42.29 | AB51: =V51-P51-Q51-R51-S51-U51 -> -5.4400928e-15 | AC51: =T51-SUM(Q51:S51) -> 0
C52: PSR0V168 | D52: 91W 215/45R17 EL64AZ | E52: 91W | F52: 215/45 | G52: 17 | H52: EL64AZ | I52: BRIDGESTONE | J52: BS | K52: PSR2 | L52: JXKVA | M52: 0.06599104 | N52: 10209 | O52: 4579 | P52: 21.758714 | Q52: 6.0049302 | R52: 8.0622986 | S52: 7.3105992 | T52: 21.377828 | U52: 0.6245549 | V52: 43.761097 | W52: 0.047 | X52: 0 | Y52: 0.04 | Z52: 47.41 | AA52: 49.56 | AB52: =V52-P52-Q52-R52-S52-U52 -> 0 | AC52: =T52-SUM(Q52:S52) -> 0
C53: PSR0V169 | D53: 92W 225/40R18 EL64AZ | E53: 92W | F53: 225/40 | G53: 18 | H53: EL64AZ | I53: BRIDGESTONE | J53: BS | K53: PSR2 | L53: GJDZA | M53: 0.071713961 | N53: 10753 | O53: 4754 | P53: 22.91097 | Q53: 6.1456099 | R53: 8.137226 | S53: 7.4196465 | T53: 21.702482 | U53: 0.65783513 | V53: 45.271288 | W53: 0.047 | X53: 0 | Y53: 0.04 | Z53: 49.05 | AA53: 51.27 | AB53: =V53-P53-Q53-R53-S53-U53 -> -1.7763568e-15 | AC53: =T53-SUM(Q53:S53) -> 0
C54: PSR0V16D | D54: 99V 225/60R17 DTH1AZ | E54: 99V | F54: 225/60 | G54: 17 | H54: DTH1AZ | I54: DAYTON | J54: FS&D | K54: PSR2 | L54: 7HGMA | M54: 0.086991917 | N54: 11726 | O54: 5447 | P54: 22.467472 | Q54: 6.4062897 | R54: 8.3891973 | S54: 7.7496011 | T54: 22.545088 | U54: 0.71736025 | V54: 45.72992 | W54: 0.047 | X54: 0.0025 | Y54: 0.0325 | Z54: 49.68 | AA54: 51.35 | AB54: =V54-P54-Q54-R54-S54-U54 -> 3.2196468e-15 | AC54: =T54-SUM(Q54:S54) -> 0
C55: PSR0V170 | D55: 84H 175/65R15 EL64Z | E55: 84H | F55: 175/65 | G55: 15 | H55: EL64Z | I55: BRIDGESTONE | J55: BS | K55: PSR4 | L55: FMNVA | M55: 0.05086615 | N55: 8534 | O55: 4019 | P55: 17.752627 | Q55: 5.1833075 | R55: 6.8439491 | S55: 6.1970177 | T55: 18.224274 | U55: 0.52208361 | V55: 36.498985 | W55: 0.047 | X55: 0 | Y55: 0.04 | Z55: 39.54 | AA55: 41.34 | AB55: =V55-P55-Q55-R55-S55-U55 -> -4.3298698e-15 | AC55: =T55-SUM(Q55:S55) -> 0
C56: PSR0V173 | D56: 91V 205/55R16 EL64Z | E56: 91V | F56: 205/55 | G56: 16 | H56: EL64Z | I56: BRIDGESTONE | J56: BS | K56: PSR3 | L56: LZRVA | M56: 0.064256968 | N56: 10704 | O56: 4947 | P56: 22.133738 | Q56: 5.9440554 | R56: 7.9330295 | S56: 7.3337291 | T56: 21.210814 | U56: 0.65483747 | V56: 43.999389 | W56: 0.047 | X56: 0 | Y56: 0.04 | Z56: 47.67 | AA56: 49.83 | AB56: =V56-P56-Q56-R56-S56-U56 -> -3.1086245e-15 | AC56: =T56-SUM(Q56:S56) -> 0
C57: PSR0V174 | D57: 91V 195/65R15 EL64Z | E57: 91V | F57: 195/65 | G57: 15 | H57: EL64Z | I57: BRIDGESTONE | J57: BS | K57: PSR4 | L57: NJSVA | M57: 0.061626503 | N57: 9987 | O57: 4703 | P57: 20.78642 | Q57: 5.5721133 | R57: 7.4010908 | S57: 6.845943 | T57: 19.819147 | U57: 0.61097363 | V57: 41.21654 | W57: 0.047 | X57: 0 | Y57: 0.04 | Z57: 44.65 | AA57: 46.68 | AB57: =V57-P57-Q57-R57-S57-U57 -> -4.1078252e-15 | AC57: =T57-SUM(Q57:S57) -> 0
C58: PSR0V177 | D58: 75V 165/50R16 EA04FZ | E58: 75V | F58: 165/50 | G58: 16 | H58: EA04FZ | I58: BRIDGESTONE | J58: BS | K58: PSR3 | L58: XDFVA | M58: 0.042289648 | N58: 6679 | O58: 3147 | P58: 14.187245 | Q58: 4.8139453 | R58: 6.4985031 | S58: 5.6335478 | T58: 16.945996 | U58: 0.40860047 | V58: 31.541842 | W58: 0.047 | X58: 0 | Y58: 0.04 | Z58: 34.17 | AA58: 35.72 | AB58: =V58-P58-Q58-R58-S58-U58 -> 0 | AC58: =T58-SUM(Q58:S58) -> 0
C59: PSR0V178 | D59: 73V 165/50R15 EA04FZ | E59: 73V | F59: 165/50 | G59: 15 | H59: EA04FZ | I59: BRIDGESTONE | J59: BS | K59: PSR4 | L59: KVQVA | M59: 0.038613475 | N59: 6277 | O59: 2987 | P59: 13.427511 | Q59: 4.5510926 | R59: 6.0281231 | S59: 5.2023195 | T59: 15.781535 | U59: 0.38400736 | V59: 29.593053 | W59: 0.047 | X59: 0 | Y59: 0.04 | Z59: 32.06 | AA59: 33.51 | AB59: =V59-P59-Q59-R59-S59-U59 -> -1.6098234e-15 | AC59: =T59-SUM(Q59:S59) -> 0
C60: PSR0V179 | D60: 75V 165/55R15 EA04FZ | E60: 75V | F60: 165/55 | G60: 15 | H60: EA04FZ | I60: BRIDGESTONE | J60: BS | K60: PSR4 | L60: DPJVA | M60: 0.04098252 | N60: 6546 | O60: 3106 | P60: 13.987882 | Q60: 4.6453175 | R60: 6.2608135 | S60: 5.4376291 | T60: 16.34376 | U60: 0.40046394 | V60: 30.732106 | W60: 0.047 | X60: 0 | Y60: 0.04 | Z60: 33.3 | AA60: 34.8 | AB60: =V60-P60-Q60-R60-S60-U60 -> 2.3869795e-15 | AC60: =T60-SUM(Q60:S60) -> 0
C61: PSR0V17D | D61: 102V 235/60R17 DTH1AZ | E61: 102V | F61: 235/60 | G61: 17 | H61: DTH1AZ | I61: DAYTON | J61: FS&D | K61: PSR2 | L61: PKMZA | M61: 0.093991938 | N61: 12536 | O61: 5806 | P61: 24.900372 | Q61: 6.8460886 | R61: 8.8552834 | S61: 8.2599784 | T61: 23.96135 | U61: 0.76691354 | V61: 49.628636 | W61: 0.047 | X61: 0.0025 | Y61: 0.0325 | Z61: 53.91 | AA61: 55.73 | AB61: =V61-P61-Q61-R61-S61-U61 -> 7.6605389e-15 | AC61: =T61-SUM(Q61:S61) -> 0
... C68: PSR0V194 | D68: 84H 185/60R15 EP15LZ | E68: 84H | F68: 185/60 | G68: 15 | H68: EP15LZ | I68: BRIDGESTONE | J68: BS | K68: PSR4 | L68: VRQVA | M68: 0.052805117 | N68: 8089 | O68: 3943 | P68: 17.311334 | Q68: 5.099281 | R68: 6.9911902 | S68: 6.269343 | T68: 18.359814 | U68: 0.49485989 | V68: 36.166008 | W68: 0.047 | X68: 0 | Y68: 0.04 | Z68: 39.18 | AA68: 40.96 | AB68: =V68-P68-Q68-R68-S68-U68 -> 4.6074256e-15 | AC68: =T68-SUM(Q68:S68) -> 0
C69: PSR0V195 | D69: 205/55R16 T05BZ | F69: 205/55 | G69: 16 | H69: T05BZ | I69: BRIDGESTONE | J69: BS | K69: PSR3 | L69: FTWVA | M69: 0.059195014 | N69: 9426 | O69: 4452 | P69: 18.822576 | Q69: 5.6325893 | R69: 7.7511123 | S69: 7.0514386 | T69: 20.43514 | U69: 0.5766534 | V69: 39.834369 | W69: 0.047 | X69: 0 | Y69: 0.04 | Z69: 43.16 | AA69: 45.11 | AB69: =V69-P69-Q69-R69-S69-U69 -> -2.9976022e-15 | AC69: =T69-SUM(Q69:S69) -> 0
C70: PSR0V197 | D70: 185/60R15 EP30Z | F70: 185/60 | G70: 15 | H70: EP30Z | I70: BRIDGESTONE | J70: BS | K70: PSR4 | L70: NGRVA | M70: 0.057347401 | N70: 7126 | O70: 3521 | P70: 14.71211 | Q70: 4.83305 | R70: 6.3748972 | S70: 5.6062334 | T70: 16.814181 | U70: 0.43594654 | V70: 31.962237 | W70: 0.047 | X70: 0 | Y70: 0.04 | Z70: 34.63 | AA70: 36.2 | AB70: =V70-P70-Q70-R70-S70-U70 -> 7.4384943e-15 | AC70: =T70-SUM(Q70:S70) -> 0
C71: PSR0V198 | D71: 085V 195/55R15 EP30Z | E71: 085V | F71: 195/55 | G71: 15 | H71: EP30Z | I71: BRIDGESTONE | J71: BS | K71: PSR4 | L71: FZWVA | M71: 0.054283495 | N71: 7563 | O71: 3660 | P71: 15.591755 | Q71: 4.9933189 | R71: 6.8770891 | S71: 6.111095 | T71: 17.981503 | U71: 0.46268084 | V71: 34.035939 | W71: 0.047 | X71: 0 | Y71: 0.04 | Z71: 36.88 | AA71: 38.55 | AB71: =V71-P71-Q71-R71-S71-U71 -> 7.2164497e-16 | AC71: =T71-SUM(Q71:S71) -> 0
C72: PSR0V199 | D72: 092V 205/60R16 EP30Z | E72: 092V | F72: 205/60 | G72: 16 | H72: EP30Z | I72: BRIDGESTONE | J72: BS | K72: PSR3 | L72: RNFVA | M72: 0.068493825 | N72: 9133 | O72: 4502 | P72: 18.768443 | Q72: 5.5588162 | R72: 7.7195233 | S72: 6.9911183 | T72: 20.269458 | U72: 0.55872857 | V72: 39.59663 | W72: 0.047 | X72: 0 | Y72: 0.04 | Z72: 42.9 | AA72: 44.84 | AB72: =V72-P72-Q72-R72-S72-U72 -> 2.7755576e-15 | AC72: =T72-SUM(Q72:S72) -> 0
C73: PSR0V19D | D73: 100V 225/60R18 DTH1AZ | E73: 100V | F73: 225/60 | G73: 18 | H73: DTH1AZ | I73: DAYTON | J73: FS&D | K73: PSR2 | L73: TXLZA | M73: 0.093402804 | N73: 12114 | O73: 5634 | P73: 23.41276 | Q73: 6.5755719 | R73: 8.6148745 | S73: 7.9598696 | T73: 23.150316 | U73: 0.74109689 | V73: 47.304173 | W73: 0.047 | X73: 0.0025 | Y73: 0.0325 | Z73: 51.39 | AA73: 53.12 | AB73: =V73-P73-Q73-R73-S73-U73 -> -1.2212453e-15 | AC73: =T73-SUM(Q73:S73) -> 0
C74: PSR0V202 | D74: 195/60R15 EP30Z | F74: 195/60 | G74: 15 | H74: EP30Z | I74: BRIDGESTONE | J74: BS | K74: PSR4 | L74: JSQVA | M74: 0.062777919 | N74: 7646 | O74: 3732 | P74: 15.91935 | Q74: 5.0027064 | R74: 6.6680504 | S74: 5.9443697 | T74: 17.615126 | U74: 0.46775853 | V74: 34.002235 | W74: 0.047 | X74: 0 | Y74: 0.04 | Z74: 36.84 | AA74: 38.51 | AB74: =V74-P74-Q74-R74-S74-U74 -> -4.8294702e-15 | AC74: =T74-SUM(Q74:S74) -> 0
C75: PSR0V203 | D75: 215/60R16 EP30Z | F75: 215/60 | G75: 16 | H75: EP30Z | I75: BRIDGESTONE | J75: BS | K75: PSR3 | L75: KDSVA | M75: 0.068914377 | N75: 9384 | O75: 4553 | P75: 19.272693 | Q75: 5.6498231 | R75: 7.7511008 | S75: 7.0437251 | T75: 20.444649 | U75: 0.57408397 | V75: 40.291426 | W75: 0.047 | X75: 0 | Y75: 0.04 | Z75: 43.65 | AA75: 45.63 | AB75: =V75-P75-Q75-R75-S75-U75 -> -2.1094237e-15 | AC75: =T75-SUM(Q75:S75) -> 0
C76: PSR0V208 | D76: 105W 255/45R20 AL011Z | E76: 105W | F76: 255/45 | G76: 20 | H76: AL011Z | I76: BRIDGESTONE | J76: BS | K76: PSR2 | L76: XSYKA | M76: 0.10887643 | N76: 15344 | O76: 7010 | P76: 33.022246 | Q76: 7.9785569 | R76: 10.731601 | S76: 10.07486 | T76: 28.785018 | U76: 0.93869825 | V76: 62.745962 | W76: 0.047 | X76: 0 | Y76: 0.04 | Z76: 67.98 | AA76: 71.06 | AB76: =V76-P76-Q76-R76-S76-U76 -> 1.8873791e-15 | AC76: =T76-SUM(Q76:S76) -> 0
C77: PSR0V20D | D77: 107V 235/60R18 DTH1AZ | E77: 107V | F77: 235/60 | G77: 18 | H77: DTH1AZ | I77: DAYTON | J77: FS&D | K77: PSR2 | L77: DHHZA | M77: 0.10080021 | N77: 13974 | O77: 6524 | P77: 28.062443 | Q77: 7.2826713 | R77: 9.6482786 | S77: 9.0757022 | T77: 26.006652 | U77: 0.85488591 | V77: 54.923981 | W77: 0.047 | X77: 0.0025 | Y77: 0.0325 | Z77: 59.67 | AA77: 61.68 | AB77: =V77-P77-Q77-R77-S77-U77 -> 8.437695e-15 | AC77: =T77-SUM(Q77:S77) -> 0
C78: PSR0V210 | D78: 102V 245/50R20 AL011Z | E78: 102V | F78: 245/50 | G78: 20 | H78: AL011Z | I78: BRIDGESTONE | J78: BS | K78: PSR2 | L78: CQKKA | M78: 0.10905001 | N78: 15095 | O78: 6959 | P78: 31.999124 | Q78: 7.9098713 | R78: 10.565309 | S78: 9.946525 | T78: 28.421706 | U78: 0.92346521 | V78: 61.344295 | W78: 0.047 | X78: 0 | Y78: 0.04 | Z78: 66.46 | AA78: 69.47 | AB78: =V78-P78-Q78-R78-S78-U78 -> 0 | AC78: =T78-SUM(Q78:S78) -> 0
C79: PSR0V211 | D79: 082H 185/60R14 150EZ | E79: 082H | F79: 185/60 | G79: 14 | H79: 150EZ | I79: BRIDGESTONE | J79: BS | K79: PSR5 | L79: RCAVA | M79: 0.04845022 | N79: 6847 | O79: 3350 | P79: 13.548987 | Q79: 4.7056711 | R79: 6.5763848 | S79: 5.8025507 | T79: 17.084607 | U79: 0.41887819 | V79: 31.052472 | W79: 0.047 | X79: 0 | Y79: 0.04 | Z79: 33.64 | AA79: 35.17 | AB79: =V79-P79-Q79-R79-S79-U79 -> 5.2735594e-15 | AC79: =T79-SUM(Q79:S79) -> 0
C80: PSR0V213 | D80: 99V 225/55R19 AL011Z | E80: 99V | F80: 225/55 | G80: 19 | H80: AL011Z | I80: BRIDGESTONE | J80: BS | K80: PSR2 | L80: ZV2KA | M80: 0.094149252 | N80: 12566 | O80: 5887 | P80: 26.716678 | Q80: 7.0321532 | R80: 9.5062235 | S80: 8.7901863 | T80: 25.328563 | U80: 0.76874884 | V80: 52.81399 | W80: 0.047 | X80: 0 | Y80: 0.04 | Z80: 57.22 | AA80: 59.81 | AB80: =V80-P80-Q80-R80-S80-U80 -> 8.8817842e-16 | AC80: =T80-SUM(Q80:S80) -> 0
C81: PSR0V214 | D81: 235/55R19 AL011Z | F81: 235/55 | G81: 19 | H81: AL011Z | I81: BRIDGESTONE | J81: BS | K81: PSR2 | L81: ZW3KA | M81: 0.10131906 | N81: 13665 | O81: 6288 | P81: 29.280825 | Q81: 7.4266003 | R81: 9.9815272 | S81: 9.349944 | T81: 26.758071 | U81: 0.83598225 | V81: 56.874879 | W81: 0.047 | X81: 0 | Y81: 0.04 | Z81: 61.62 | AA81: 64.41 | AB81: =V81-P81-Q81-R81-S81-U81 -> 5.1070259e-15 | AC81: =T81-SUM(Q81:S81) -> 0
C82: PSR0V215 | D82: 103V 245/55R19 AL011Z | E82: 103V | F82: 245/55 | G82: 19 | H82: AL011Z | I82: BRIDGESTONE | J82: BS | K82: PSR2 | L82: ZX4KA | M82: 0.10878948 | N82: 15115 | O82: 6976 | P82: 32.238329 | Q82: 7.7534851 | R82: 10.428462 | S82: 9.8808873 | T82: 28.062835 | U82: 0.92468874 | V82: 61.225853 | W82: 0.047 | X82: 0 | Y82: 0.04 | Z82: 66.33 | AA82: 69.34 | AB82: =V82-P82-Q82-R82-S82-U82 -> 4.6629367e-15 | AC82: =T82-SUM(Q82:S82) -> 0
C83: PSR0V21D | D83: 105H 245/60R18 DTH1AZ | E83: 105H | F83: 245/60 | G83: 18 | H83: DTH1AZ | I83: DAYTON | J83: FS&D | K83: PSR2 | L83: NQTZA | M83: 0.10852927 | N83: 14240 | O83: 6625 | P83: 28.697038 | Q83: 7.3559608 | R83: 9.8111281 | S83: 9.2523748 | T83: 26.419464 | U83: 0.87115896 | V83: 55.98766 | W83: 0.047 | X83: 0.0025 | Y83: 0.0325 | Z83: 60.82 | AA83: 62.87 | AB83: =V83-P83-Q83-R83-S83-U83 -> -3.1086245e-15 | AC83: =T83-SUM(Q83:S83) -> 0
C84: PSR0V221 | D84: 098V 215/55R17 EL64Z | E84: 098V | F84: 215/55 | G84: 17 | H84: EL64Z | I84: BRIDGESTONE | J84: BS | K84: PSR2 | L84: XLHZA | M84: 0.075379116 | N84: 12313 | O84: 5583 | P84: 26.182613 | Q84: 6.6133977 | R84: 8.7613298 | S84: 8.1493412 | T84: 23.524069 | U84: 0.75327109 | V84: 50.459953 | W84: 0.047 | X84: 0 | Y84: 0.04 | Z84: 54.67 | AA84: 57.15 | AB84: =V84-P84-Q84-R84-S84-U84 -> 8.8817842e-16 | AC84: =T84-SUM(Q84:S84) -> 0
C85: PSR0V223 | D85: 155/65R13 NEWNZ | F85: 155/65 | G85: 13 | H85: NEWNZ | I85: BRIDGESTONE | J85: BS | K85: PSR5 | L85: BF3VA | M85: 0.034398117 | N85: 4611 | O85: 2306 | P85: 9.5021673 | Q85: 3.9329628 | R85: 5.4067328 | S85: 4.5434061 | T85: 13.883102 | U85: 0.28208666 | V85: 23.667356 | W85: 0.047 | X85: 0 | Y85: 0.04 | Z85: 25.64 | AA85: 26.8 | AB85: =V85-P85-Q85-R85-S85-U85 -> -2.1649349e-15 | AC85: =T85-SUM(Q85:S85) -> 0
C86: PSR0V224 | D86: 110H 265/60R18 684A6Z | E86: 110H | F86: 265/60 | G86: 18 | H86: 684A6Z | I86: BRIDGESTONE | J86: BS | K86: PSR2 | L86: FX8KA | M86: 0.12500951 | N86: 16267 | O86: 7735 | P86: 33.645728 | Q86: 8.1299161 | R86: 11.022849 | S86: 10.49218 | T86: 29.644945 | U86: 0.99516452 | V86: 64.285837 | W86: 0.047 | X86: 0 | Y86: 0.04 | Z86: 69.65 | AA86: 72.8 | AB86: =V86-P86-Q86-R86-S86-U86 -> 4.773959e-15 | AC86: =T86-SUM(Q86:S86) -> 0
C87: PSR0V225 | D87: 112S 265/65R17 693BHZ | E87: 112S | F87: 265/65 | G87: 17 | H87: 693BHZ | I87: BRIDGESTONE | J87: BS | K87: PSR2 | L87: F17KA | M87: 0.12536454 | N87: 16080 | O87: 7728 | P87: 33.036091 | Q87: 7.9159019 | R87: 10.674858 | S87: 10.219717 | T87: 28.810476 | U87: 0.98372445 | V87: 62.830291 | W87: 0.047 | X87: 0 | Y87: 0.04 | Z87: 68.07 | AA87: 71.16 | AB87: =V87-P87-Q87-R87-S87-U87 -> -2.3314684e-15 | AC87: =T87-SUM(Q87:S87) -> 0
C88: PSR0V227 | D88: 205/55R16 EP30Z | F88: 205/55 | G88: 16 | H88: EP30Z | I88: BRIDGESTONE | J88: BS | K88: PSR3 | L88: XPDVA | M88: 0.059195014 | N88: 9010 | O88: 4260 | P88: 18.548262 | Q88: 5.535734 | R88: 7.5611702 | S88: 6.8406343 | T88: 19.937539 | U88: 0.55120381 | V88: 39.037004 | W88: 0.047 | X88: 0 | Y88: 0.04 | Z88: 42.29 | AA88: 44.21 | AB88: =V88-P88-Q88-R88-S88-U88 -> -2.7755576e-15 | AC88: =T88-SUM(Q88:S88) -> 0
C89: PSR0V229 | D89: 155/65R14 NEWNZ | F89: 155/65 | G89: 14 | H89: NEWNZ | I89: BRIDGESTONE | J89: BS | K89: PSR5 | L89: DFYVA | M89: 0.037763103 | N89: 4918 | O89: 2412 | P89: 10.115692 | Q89: 4.1229682 | R89: 5.5529013 | S89: 4.6692522 | T89: 14.345122 | U89: 0.30086796 | V89: 24.761681 | W89: 0.047 | X89: 0 | Y89: 0.04 | Z89: 26.83 | AA89: 28.04 | AB89: =V89-P89-Q89-R89-S89-U89 -> 5.4400928e-15 | AC89: =T89-SUM(Q89:S89) -> 0
C90: PSR0V22D | D90: 98V 225/55R18 DTH1AZ | E90: 98V | F90: 225/55 | G90: 18 | H90: DTH1AZ | I90: DAYTON | J90: FS&D | K90: PSR2 | L90: TGAZA | M90: 0.087712344 | N90: 12295 | O90: 5722 | P90: 23.624728 | Q90: 6.5702044 | R90: 8.6541574 | S90: 8.0078482 | T90: 23.23221 | U90: 0.7521699 | V90: 47.609108 | W90: 0.047 | X90: 0.0025 | Y90: 0.0325 | Z90: 51.72 | AA90: 53.46 | AB90: =V90-P90-Q90-R90-S90-U90 -> 4.5519144e-15 | AC90: =T90-SUM(Q90:S90) -> 0
C91: PSR0V230 | D91: 185/65R15 NEWNZ | F91: 185/65 | G91: 15 | H91: NEWNZ | I91: BRIDGESTONE | J91: BS | K91: PSR4 | L91: BG5VA | M91: 0.056094935 | N91: 6918 | O91: 3406 | P91: 14.361262 | Q91: 4.7959271 | R91: 6.6120745 | S91: 5.7970302 | T91: 17.205032 | U91: 0.42322175 | V91: 31.989516 | W91: 0.047 | X91: 0 | Y91: 0.04 | Z91: 34.66 | AA91: 36.23 | AB91: =V91-P91-Q91-R91-S91-U91 -> 1.831868e-15 | AC91: =T91-SUM(Q91:S91) -> 0
C92: PSR0V231 | D92: 185/70R14 NEWNZ | F92: 185/70 | G92: 14 | H92: NEWNZ | I92: BRIDGESTONE | J92: BS | K92: PSR5 | L92: HXHVA | M92: 0.054856298 | N92: 6676 | O92: 3298 | P92: 13.791087 | Q92: 4.6540915 | R92: 6.2812916 | S92: 5.4925766 | T92: 16.42796 | U92: 0.40841694 | V92: 30.627464 | W92: 0.047 | X92: 0 | Y92: 0.04 | Z92: 33.18 | AA92: 34.69 | AB92: =V92-P92-Q92-R92-S92-U92 -> -7.6605389e-15 | AC92: =T92-SUM(Q92:S92) -> 0
C93: PSR0V232 | D93: 175/65R15 NEWNZ | F93: 175/65 | G93: 15 | H93: NEWNZ | I93: BRIDGESTONE | J93: BS | K93: PSR4 | L93: YC4VA | M93: 0.05086615 | N93: 6279 | O93: 3084 | P93: 13.063298 | Q93: 4.6268439 | R93: 6.4082646 | S93: 5.5490243 | T93: 16.584133 | U93: 0.38412971 | V93: 30.03156 | W93: 0.047 | X93: 0 | Y93: 0.04 | Z93: 32.54 | AA93: 34.01 | AB93: =V93-P93-Q93-R93-S93-U93 -> 3.1641356e-15 | AC93: =T93-SUM(Q93:S93) -> 0
C94: PSR0V233 | D94: 195/65R15 NEWNZ | F94: 195/65 | G94: 15 | H94: NEWNZ | I94: BRIDGESTONE | J94: BS | K94: PSR4 | L94: BYJVA | M94: 0.061626503 | N94: 7269 | O94: 3592 | P94: 15.079966 | Q94: 4.9066162 | R94: 6.599908 | S94: 5.8201475 | T94: 17.326672 | U94: 0.44469484 | V94: 32.851333 | W94: 0.047 | X94: 0 | Y94: 0.04 | Z94: 35.59 | AA94: 37.2 | AB94: =V94-P94-Q94-R94-S94-U94 -> 4.4964032e-15 | AC94: =T94-SUM(Q94:S94) -> 0
C95: PSR0V234 | D95: 075H 155/65R14 NH2CZ | E95: 075H | F95: 155/65 | G95: 14 | H95: NH2CZ | I95: BRIDGESTONE | J95: BS | K95: PSR5 | L95: K47VA | M95: 0.037763103 | N95: 5068 | O95: 2352 | P95: 10.952638 | Q95: 4.1733851 | R95: 5.6377287 | S95: 4.7553298 | T95: 14.566444 | U95: 0.3100445 | V95: 25.829126 | W95: 0.047 | X95: 0 | Y95: 0.04 | Z95: 27.98 | AA95: 29.25 | AB95: =V95-P95-Q95-R95-S95-U95 -> 1.831868e-15 | AC95: =T95-SUM(Q95:S95) -> 0
C96: PSR0V235 | D96: 075H 165/60R14 NH2CZ | E96: 075H | F96: 165/60 | G96: 14 | H96: NH2CZ | I96: BRIDGESTONE | J96: BS | K96: PSR5 | L96: 35NVA | M96: 0.03969591 | N96: 5667 | O96: 2589 | P96: 12.327111 | Q96: 4.3158722 | R96: 5.9105057 | S96: 5.0672255 | T96: 15.293603 | U96: 0.34668945 | V96: 27.967404 | W96: 0.047 | X96: 0 | Y96: 0.04 | Z96: 30.3 | AA96: 31.67 | AB96: =V96-P96-Q96-R96-S96-U96 -> -1.831868e-15 | AC96: =T96-SUM(Q96:S96) -> 0
C97: PSR0V236 | D97: 082S 175/65R14 NH2CZ | E97: 082S | F97: 175/65 | G97: 14 | H97: NH2CZ | I97: BRIDGESTONE | J97: BS | K97: PSR5 | L97: 36TVA | M97: 0.046708271 | N97: 6092 | O97: 2844 | P97: 13.278956 | Q97: 4.4524528 | R97: 6.0327716 | S97: 5.228293 | T97: 15.713517 | U97: 0.37268963 | V97: 29.365163 | W97: 0.047 | X97: 0 | Y97: 0.04 | Z97: 31.81 | AA97: 33.26 | AB97: =V97-P97-Q97-R97-S97-U97 -> -1.9984014e-15 | AC97: =T97-SUM(Q97:S97) -> 0
C98: PSR0V237 | D98: 084S 175/70R14 NH2CZ | E98: 084S | F98: 175/70 | G98: 14 | H98: NH2CZ | I98: BRIDGESTONE | J98: BS | K98: PSR5 | L98: 37AVA | M98: 0.049553959 | N98: 6224 | O98: 2921 | P98: 13.481814 | Q98: 4.4792979 | R98: 5.90573 | S98: 5.1237004 | T98: 15.508728 | U98: 0.38076498 | V98: 29.371307 | W98: 0.047 | X98: 0 | Y98: 0.04 | Z98: 31.82 | AA98: 33.26 | AB98: =V98-P98-Q98-R98-S98-U98 -> 4.3853809e-15 | AC98: =T98-SUM(Q98:S98) -> 0
C99: PSR0V238 | D99: 088S 185/65R15 NH2CZ | E99: 088S | F99: 185/65 | G99: 15 | H99: NH2CZ | I99: BRIDGESTONE | J99: BS | K99: PSR4 | L99: 4QAVA | M99: 0.056094935 | N99: 7037 | O99: 3267 | P99: 15.346225 | Q99: 4.8186413 | R99: 6.5771027 | S99: 5.7743326 | T99: 17.170077 | U99: 0.4305018 | V99: 32.946803 | W99: 0.047 | X99: 0 | Y99: 0.04 | Z99: 35.7 | AA99: 37.31 | AB99: =V99-P99-Q99-R99-S99-U99 -> 0 | AC99: =T99-SUM(Q99:S99) -> 0
C100: PSR0V239 | D100: 088S 185/70R14 NH2SZ | E100: 088S | F100: 185/70 | G100: 14 | H100: NH2SZ | I100: BRIDGESTONE | J100: BS | K100: PSR5 | L100: 2CVVA | M100: 0.054856298 | N100: 6621 | O100: 3087 | P100: 14.370424 | Q100: 4.6200952 | R100: 6.0996011 | S100: 5.3297158 | T100: 16.049412 | U100: 0.40505221 | V100: 30.824888 | W100: 0.047 | X100: 0 | Y100: 0.04 | Z100: 33.4 | AA100: 34.91 | AB100: =V100-P100-Q100-R100-S100-U100 -> 0 | AC100: =T100-SUM(Q100:S100) -> 0
C101: PSR0V23D | D101: 104V 235/55R18 DTH1AZ | E101: 104V | F101: 235/55 | G101: 18 | H101: DTH1AZ | I101: DAYTON | J101: FS&D | K101: PSR2 | L101: SMLZA | M101: 0.094492982 | N101: 13335 | O101: 6192 | P101: 26.833872 | Q101: 7.1388517 | R101: 9.3431515 | S101: 8.7381651 | T101: 25.220168 | U101: 0.81579387 | V101: 52.869834 | W101: 0.047 | X101: 0.0025 | Y101: 0.0325 | Z101: 57.44 | AA101: 59.37 | AB101: =V101-P101-Q101-R101-S101-U101 -> 0 | AC101: =T101-SUM(Q101:S101) -> 0
C102: PSR0V240 | D102: 084H 185/60R15 NH2CZ | E102: 084H | F102: 185/60 | G102: 15 | H102: NH2CZ | I102: BRIDGESTONE | J102: BS | K102: PSR4 | L102: KYVVA | M102: 0.052805117 | N102: 6845 | O102: 3213 | P102: 14.870518 | Q102: 4.7373878 | R102: 6.3927382 | S102: 5.5903874 | T102: 16.720513 | U102: 0.41875583 | V102: 32.009787 | W102: 0.047 | X102: 0 | Y102: 0.04 | Z102: 34.68 | AA102: 36.25 | AB102: =V102-P102-Q102-R102-S102-U102 -> -1.3322676e-15 | AC102: =T102-SUM(Q102:S102) -> 0
C103: PSR0V243 | D103: 235/55R19 AL011Z | F103: 235/55 | G103: 19 | H103: AL011Z | I103: BRIDGESTONE | J103: BS | K103: PSR2 | L103: NX4KA | M103: 0.075442942 | N103: 13665 | O103: 6288 | P103: 29.283732 | Q103: 7.452603 | R103: 10.013683 | S103: 9.367666 | T103: 26.833952 | U103: 0.83598225 | V103: 56.953666 | W103: 0.047 | X103: 0 | Y103: 0.04 | Z103: 61.7 | AA103: 64.5 | AB103: =V103-P103-Q103-R103-S103-U103 -> 5.1070259e-15 | AC103: =T103-SUM(Q103:S103) -> 0
C104: PSR0V247 | D104: 089H 195/60R16 EP15HZ | E104: 089H | F104: 195/60 | G104: 16 | H104: EP15HZ | I104: BRIDGESTONE | J104: BS | K104: PSR3 | L104: BXWVA | M104: 0.062777919 | N104: 8239 | O104: 3804 | P104: 17.222837 | Q104: 5.2843044 | R104: 7.1606241 | S104: 6.392257 | T104: 18.837185 | U104: 0.50403642 | V104: 36.564059 | W104: 0.047 | X104: 0 | Y104: 0.04 | Z104: 39.61 | AA104: 41.41 | AB104: =V104-P104-Q104-R104-S104-U104 -> 1.8873791e-15 | AC104: =T104-SUM(Q104:S104) -> 0
C105: PSR0V248 | D105: 089V 205/50R17 T05ABZ | E105: 089V | F105: 205/50 | G105: 17 | H105: T05ABZ | I105: BRIDGESTONE | J105: BS | K105: PSR2 | L105: FNTZA | M105: 0.065257379 | N105: 8832 | O105: 4115 | P105: 19.433157 | Q105: 5.6798664 | R105: 7.7709226 | S105: 6.9204876 | T105: 20.371277 | U105: 0.54031432 | V105: 40.344748 | W105: 0.047 | X105: 0 | Y105: 0.04 | Z105: 43.71 | AA105: 45.69 | AB105: =V105-P105-Q105-R105-S105-U105 -> 6.8833828e-15 | AC105: =T105-SUM(Q105:S105) -> 0
C106: PSR0V249 | D106: 099V 225/60R17 AL01AZ | E106: 099V | F106: 225/60 | G106: 17 | H106: AL01AZ | I106: BRIDGESTONE | J106: BS | K106: PSR2 | L106: 7VFMA | M106: 0.086991917 | N106: 10480 | O106: 4967 | P106: 21.65775 | Q106: 6.2441286 | R106: 8.4265279 | S106: 7.6559858 | T106: 22.326642 | U106: 0.64113384 | V106: 44.625526 | W106: 0.047 | X106: 0 | Y106: 0.04 | Z106: 48.35 | AA106: 50.54 | AB106: =V106-P106-Q106-R106-S106-U106 -> -1.2212453e-15 | AC106: =T106-SUM(Q106:S106) -> 0
C107: PSR0V250 | D107: 103W 235/60R18 AL01Z | E107: 103W | F107: 235/60 | G107: 18 | H107: AL01Z | I107: BRIDGESTONE | J107: BS | K107: PSR2 | L107: 8TSZA | M107: 0.10080021 | N107: 13428 | O107: 6281 | P107: 29.169051 | Q107: 7.3431174 | R107: 9.7851453 | S107: 9.1535692 | T107: 26.281832 | U107: 0.82148332 | V107: 56.272366 | W107: 0.047 | X107: 0 | Y107: 0.04 | Z107: 60.97 | AA107: 63.73 | AB107: =V107-P107-Q107-R107-S107-U107 -> -8.8817842e-16 | AC107: =T107-SUM(Q107:S107) -> 0
C108: PSR0V254 | D108: 95V 215/60R16 EL64Z | E108: 95V | F108: 215/60 | G108: 16 | H108: EL64Z | I108: BRIDGESTONE | J108: BS | K108: PSR3 | L108: 3VVVA | M108: 0.074501903 | N108: 11812 | O108: 5604 | P108: 24.209032 | Q108: 6.2029912 | R108: 8.2043851 | S108: 7.7132932 | T108: 22.120669 | U108: 0.72262146 | V108: 47.052323 | W108: 0.047 | X108: 0 | Y108: 0.04 | Z108: 50.98 | AA108: 53.29 | AB108: =V108-P108-Q108-R108-S108-U108 -> 2.7755576e-15 | AC108: =T108-SUM(Q108:S108) -> 0
C109: PSR0V257 | D109: 99W 235/45R19 AL01AZ | E109: 99W | F109: 235/45 | G109: 19 | H109: AL01AZ | I109: BRIDGESTONE | J109: BS | K109: PSR2 | L109: E33KA | M109: 0.088875408 | N109: 11956 | O109: 5404 | P109: 25.188941 | Q109: 6.7317795 | R109: 9.136016 | S109: 8.3679816 | T109: 24.235777 | U109: 0.73143094 | V109: 50.156149 | W109: 0.047 | X109: 0 | Y109: 0.04 | Z109: 54.34 | AA109: 56.8 | AB109: =V109-P109-Q109-R109-S109-U109 -> -2.8865799e-15 | AC109: =T109-SUM(Q109:S109) -> 0
C110: PSR0V258 | D110: 95V 225/45R18 EL64AZ | E110: 95V | F110: 225/45 | G110: 18 | H110: EL64AZ | I110: BRIDGESTONE | J110: BS | K110: PSR2 | L110: QZZZA | M110: 0.076867922 | N110: 12295 | O110: 5722 | P110: 25.146585 | Q110: 6.5702044 | R110: 8.6541574 | S110: 8.0078482 | T110: 23.23221 | U110: 0.7521699 | V110: 49.130965 | W110: 0.047 | X110: 0 | Y110: 0.04 | Z110: 53.23 | AA110: 55.64 | AB110: =V110-P110-Q110-R110-S110-U110 -> -2.553513e-15 | AC110: =T110-SUM(Q110:S110) -> 0
C111: PSR0V259 | D111: 94W 205/55R16 T06BZ | E111: 94W | F111: 205/55 | G111: 16 | H111: T06BZ | I111: BRIDGESTONE | J111: BS | K111: PSR3 | M111: 0.064256968 | N111: 10704 | O111: 4947 | P111: 22.226454 | Q111: 5.9440554 | R111: 7.9330295 | S111: 7.3337291 | T111: 21.210814 | U111: 0.65483747 | V111: 44.092105 | W111: 0.047 | X111: 0 | Y111: 0.04 | Z111: 47.77 | AA111: 49.93 | AB111: =V111-P111-Q111-R111-S111-U111 -> -4.8849813e-15 | AC111: =T111-SUM(Q111:S111) -> 0
C112: PSR0V25S | D112: 84H 175/70R14 SPCZ | E112: 84H | F112: 175/70 | G112: 14 | H112: SPCZ | I112: SUPERCAT | J112: Others | K112: PSR5 | L112: KSAVA | M112: 0.049553959 | N112: 6933 | O112: 3318 | P112: 13.418705 | Q112: 4.668005 | R112: 6.1090145 | S112: 5.3666589 | T112: 16.143678 | U112: 0.4241394 | V112: 29.986523 | W112: 0.047 | X112: 0 | Y112: 0.03 | Z112: 32.49 | AA112: 33.58 | AB112: =V112-P112-Q112-R112-S112-U112 -> 1.1657342e-15 | AC112: =T112-SUM(Q112:S112) -> 0
C113: PSR0V261 | D113: 205/60R16 T06BZ | F113: 205/60 | G113: 16 | H113: T06BZ | I113: BRIDGESTONE | J113: BS | K113: PSR3 | L113: 0 | M113: 0.068493825 | N113: 10273 | O113: 4726 | P113: 21.397948 | Q113: 5.7696424 | R113: 7.4590425 | S113: 6.8900301 | T113: 20.118715 | U113: 0.62847023 | V113: 42.145133 | W113: 0.047 | X113: 0 | Y113: 0.04 | Z113: 45.66 | AA113: 47.73 | AB113: =V113-P113-Q113-R113-S113-U113 -> 3.1086245e-15 | AC113: =T113-SUM(Q113:S113) -> 0
C114: PSR0V27B | D114: 101V 225/55R17 SL20AZ | E114: 101V | F114: 225/55 | G114: 17 | H114: SL20AZ | I114: SEIBERLING | J114: FS&D | K114: PSR2 | L114: AF2MA | M114: 0.08150334 | N114: 11913 | O114: 5579 | P114: 24.212634 | Q114: 6.4770704 | R114: 8.5546816 | S114: 7.9139817 | T114: 22.945734 | U114: 0.72880033 | V114: 47.887168 | W114: 0.047 | X114: 0.0025 | Y114: 0.0325 | Z114: 52.02 | AA114: 53.78 | AB114: =V114-P114-Q114-R114-S114-U114 -> -2.9976022e-15 | AC114: =T114-SUM(Q114:S114) -> 0
C115: PSR0V28B | D115: 225/40R18 SL20GZ | F115: 225/40 | G115: 18 | H115: SL20GZ | I115: SEIBERLING | J115: FS&D | K115: PSR2 | L115: XCQZA | M115: 0.033268379 | N115: 9924 | O115: 4458 | P115: 20.445517 | Q115: 5.9946584 | R115: 8.0937045 | S115: 7.2823911 | T115: 21.370754 | U115: 0.60711949 | V115: 42.42339 | W115: 0.047 | X115: 0.0025 | Y115: 0.0325 | Z115: 46.09 | AA115: 47.64 | AB115: =V115-P115-Q115-R115-S115-U115 -> -5.4400928e-15 | AC115: =T115-SUM(Q115:S115) -> 0
C116: PSR0V29B | D116: 089W 215/45R18 SL20GZ | E116: 089W | F116: 215/45 | G116: 18 | H116: SL20GZ | I116: SEIBERLING | J116: FS&D | K116: PSR2 | L116: JWTZA | M116: 0.071461105 | N116: 10258 | O116: 4573 | P116: 20.890803 | Q116: 6.0792949 | R116: 8.0328978 | S116: 7.2704651 | T116: 21.382658 | U116: 0.62755257 | V116: 42.901013 | W116: 0.047 | X116: 0.0025 | Y116: 0.0325 | Z116: 46.61 | AA116: 48.18 | AB116: =V116-P116-Q116-R116-S116-U116 -> 1.9984014e-15 | AC116: =T116-SUM(Q116:S116) -> 0
C117: PSR0V29D | D117: 99V 215/55R18 DTH1AZ | E117: 99V | F117: 215/55 | G117: 18 | H117: DTH1AZ | I117: DAYTON | J117: FS&D | K117: PSR2 | L117: LFCZA | M117: 0.081217853 | N117: 12073 | O117: 5650 | P117: 24.35322 | Q117: 6.7748712 | R117: 9.1917312 | S117: 8.4601627 | T117: 24.426765 | U117: 0.73858863 | V117: 49.518574 | W117: 0.047 | X117: 0.0025 | Y117: 0.0325 | Z117: 53.8 | AA117: 55.61 | AB117: =V117-P117-Q117-R117-S117-U117 -> -5.6621374e-15 | AC117: =T117-SUM(Q117:S117) -> 0
C118: PSR0V30B | D118: 94S 205/65R15 SL10Z | E118: 94S | F118: 205/65 | G118: 15 | H118: SL10Z | I118: SEIBERLING | J118: FS&D | K118: PSR4 | L118: WNPVA | M118: 0.067468812 | N118: 8700 | O118: 4008 | P118: 17.150823 | Q118: 5.2262869 | R118: 6.8480146 | S118: 6.1879688 | T118: 18.26227 | U118: 0.53223897 | V118: 35.945332 | W118: 0.047 | X118: 0.0025 | Y118: 0.0325 | Z118: 39.05 | AA118: 40.37 | AB118: =V118-P118-Q118-R118-S118-U118 -> -2.1094237e-15 | AC118: =T118-SUM(Q118:S118) -> 0
...

Sheet Jan
A1: Kết xuất ZVF59 từ SAP, copy thay dữ liệu từ A2 -> BO210
A2: Creation Flag(1) | B2: Unit No. of slip(80) | C2: Posting Date(10) | D2: Document Date(10) | E2: Document Type(5) | F2: Reference(16) | G2: Doc. Header text(25) | H2: Currency(5) | I2: Exchange Rate(11) | J2: Translation Date(10) | K2: Posting Key(2) | L2: Account Code(17) | M2: G/L Account(10) | N2: Amount in Doc. Currency(14) | O2: Amount in Local Currency(14) | P2: Tax Base Amount in Document Currency(14) | Q2: Calculate tax(1) | R2: Tax Code(2) | S2: Payment Block(1) | T2: Payment Method(1) | U2: Business Place(4) | V2: Assignment(18) | W2: Text(50) | X2: Number of Invoice(10) | Y2: Fiscal Year of Relevant Invoice(4) | Z2: Line Item of Relevant Invoice(3) | AA2: Reference specification 1(12) | AB2: Reference specification 2(12) | AC2: Reference specification 3(20) | AD2: Material(18) | AE2: Cost center(10) | AF2: Internal Order(12) | AG2: Sales Order(10) | AH2: Sales Order Item(6) | AI2: Delivery Schedule for SO(4) | AJ2: Personnel number(8) | AK2: Plant(4) | AL2: Business Area(4) | AM2: Quantity(14) | AN2: Unit of Measure(3) | AO2: Profit Center(10) | AP2: Partner(10) | AQ2: Functional Area(4) | AR2: Purchase order(10) | AS2: Purchase order Item(5) | AT2: Baseline Date(10) | AU2: Value date(10) | AV2: Payment terms(4) | AW2: Cash Discount Days 1(3) | AX2: Cash Discount Percentage 1(6) | AY2: Cash Discount Days 2(3) | AZ2: Cash Discount Percentage 2(6) | BA2: Net Payment Terms Period(3) | BB2: Own Bank(5) | BC2: Bank Business Partners(4) | BD2: Instruction Key 1(2) | BE2: Instruction Key 2(2) | BF2: Instruction Key 3(2) | BG2: Instruction Key 4(2) | BH2: Payment Reference(30) | BI2: Payment currency amount(14) | BJ2: WHT Code(2) | BK2: WHT Base Amount(16) | BL2: WHT Amount(16) | BM2: SCB Indicator(3) | BN2: Supplying Country(3)
A3: 0 | B3: 1 | C3: 31.01.2024 | D3: 31.01.2024 | E3: ZT | G3: Transfer to WIP Jan-2024 | H3: USD | K3: 40 | L3: 132000 | N3: 6314761.3 | V3: Transfer to WIP | W3: Transfer to WIP 132000 | AL3: A01
A4: 0 | B4: 1 | K4: 50 | L4: 651110 | N4: 1830.46 | V4: Transfer to WIP | W4: Transfer to WIP 651110 62730401831U | AE4: 831U | AF4: 62730401831U | AL4: A01 | AO4: 99999
A5: 0 | B5: 1 | K5: 50 | L5: 651110 | N5: 3237.13 | V5: Transfer to WIP | W5: Transfer to WIP 651110 62730401832B | AE5: 832B | AF5: 62730401832B | AL5: A01 | AO5: 99999
A6: 0 | B6: 1 | K6: 50 | L6: 651110 | N6: 13819.41 | V6: Transfer to WIP | W6: Transfer to WIP 651110 62730401832C | AE6: 832C | AF6: 62730401832C | AL6: A01 | AO6: 99999
A7: 0 | B7: 1 | K7: 50 | L7: 651110 | N7: 37860.46 | V7: Transfer to WIP | W7: Transfer to WIP 651110 62730401832E | AE7: 832E | AF7: 62730401832E | AL7: A01 | AO7: 99999
A8: 0 | B8: 1 | K8: 50 | L8: 651110 | N8: 3461.26 | V8: Transfer to WIP | W8: Transfer to WIP 651110 62730401832F | AE8: 832F | AF8: 62730401832F | AL8: A01 | AO8: 99999
A9: 0 | B9: 1 | K9: 50 | L9: 651110 | N9: 10204.42 | V9: Transfer to WIP | W9: Transfer to WIP 651110 62730401832H | AE9: 832H | AF9: 62730401832H | AL9: A01 | AO9: 99999
A10: 0 | B10: 1 | K10: 50 | L10: 651110 | N10: 726.47 | V10: Transfer to WIP | W10: Transfer to WIP 651110 62730403832H | AE10: 832H | AF10: 62730403832H | AL10: A01 | AO10: 99999
A11: 0 | B11: 1 | K11: 50 | L11: 651110 | N11: 63161.51 | V11: Transfer to WIP | W11: Transfer to WIP 651110 62730401832J | AE11: 832J | AF11: 62730401832J | AL11: A01 | AO11: 99999
A12: 0 | B12: 1 | K12: 50 | L12: 651110 | N12: 4513.09 | V12: Transfer to WIP | W12: Transfer to WIP 651110 62730401832L | AE12: 832L | AF12: 62730401832L | AL12: A01 | AO12: 99999
A13: 0 | B13: 1 | K13: 50 | L13: 651110 | N13: 443.86 | V13: Transfer to WIP | W13: Transfer to WIP 651110 62730401851C | AE13: 851C | AF13: 62730401851C | AL13: A01 | AO13: 99999
A14: 0 | B14: 1 | K14: 50 | L14: 651110 | N14: 449.62 | V14: Transfer to WIP | W14: Transfer to WIP 651110 62730401851H | AE14: 851H | AF14: 62730401851H | AL14: A01 | AO14: 99999
A15: 0 | B15: 1 | K15: 50 | L15: 651110 | N15: 485.25 | V15: Transfer to WIP | W15: Transfer to WIP 651110 62730401851L | AE15: 851L | AF15: 62730401851L | AL15: A01 | AO15: 99999
A16: 0 | B16: 1 | K16: 50 | L16: 652210 | N16: 627.99 | V16: Transfer to WIP | W16: Transfer to WIP 652210 627706013221 | AE16: 3221 | AF16: 627706013221 | AL16: A01 | AO16: 99999
A17: 0 | B17: 1 | K17: 50 | L17: 652210 | N17: 1541.99 | V17: Transfer to WIP | W17: Transfer to WIP 652210 627706043221 | AE17: 3221 | AF17: 627706043221 | AL17: A01 | AO17: 99999
A18: 0 | B18: 1 | K18: 50 | L18: 652210 | N18: 650.92 | V18: Transfer to WIP | W18: Transfer to WIP 652210 627706013312 | AE18: 3312 | AF18: 627706013312 | AL18: A01 | AO18: 99999
A19: 0 | B19: 1 | K19: 50 | L19: 652210 | N19: 48046.86 | V19: Transfer to WIP | W19: Transfer to WIP 652210 627706018111 | AE19: 8111 | AF19: 627706018111 | AL19: A01 | AO19: 99999
A20: 0 | B20: 1 | K20: 50 | L20: 652210 | N20: 13092.77 | V20: Transfer to WIP | W20: Transfer to WIP 652210 627706018312 | AE20: 8312 | AF20: 627706018312 | AL20: A01 | AO20: 99999
A21: 0 | B21: 1 | K21: 50 | L21: 652210 | N21: 11452.61 | V21: Transfer to WIP | W21: Transfer to WIP 652210 62770605832E | AE21: 832E | AF21: 62770605832E | AL21: A01 | AO21: 99999
A22: 0 | B22: 1 | K22: 50 | L22: 652210 | N22: 16489.65 | V22: Transfer to WIP | W22: Transfer to WIP 652210 62770605832F | AE22: 832F | AF22: 62770605832F | AL22: A01 | AO22: 99999
A23: 0 | B23: 1 | K23: 50 | L23: 652210 | N23: 95.21 | V23: Transfer to WIP | W23: Transfer to WIP 652210 62770601832L | AE23: 832L | AF23: 62770601832L | AL23: A01 | AO23: 99999
A24: 0 | B24: 1 | K24: 50 | L24: 652210 | N24: 331.25 | V24: Transfer to WIP | W24: Transfer to WIP 652210 62770601851H | AE24: 851H | AF24: 62770601851H | AL24: A01 | AO24: 99999
A25: 0 | B25: 1 | K25: 50 | L25: 652210 | N25: 111.79 | V25: Transfer to WIP | W25: Transfer to WIP 652210 62770601851I | AE25: 851I | AF25: 62770601851I | AL25: A01 | AO25: 99999
A26: 0 | B26: 1 | K26: 50 | L26: 652210 | N26: 98.64 | V26: Transfer to WIP | W26: Transfer to WIP 652210 62770601851L | AE26: 851L | AF26: 62770601851L | AL26: A01 | AO26: 99999
A27: 0 | B27: 1 | K27: 50 | L27: 652210 | N27: 924.72 | V27: Transfer to WIP | W27: Transfer to WIP 652210 62770601852I | AE27: 852I | AF27: 62770601852I | AL27: A01 | AO27: 99999
A28: 0 | B28: 1 | K28: 50 | L28: 654010 | N28: 646233.09 | V28: Transfer to WIP | W28: Transfer to WIP 654010 627400011611 | AE28: 1611 | AF28: 627400011611 | AL28: A01 | AO28: 99999
A29: 0 | B29: 1 | K29: 50 | L29: 654010 | N29: 311905.35 | V29: Transfer to WIP | W29: Transfer to WIP 654010 627400021611 | AE29: 1611 | AF29: 627400021611 | AL29: A01 | AO29: 99999
A30: 0 | B30: 1 | K30: 50 | L30: 651110 | N30: 299.6 | V30: Transfer to WIP | W30: Transfer to WIP 651110 62730401321P | AE30: 321P | AF30: 62730401321P | AL30: A01 | AO30: 99999
A31: 0 | B31: 1 | K31: 50 | L31: 644100 | N31: 35.65 | V31: Transfer to WIP | W31: Transfer to WIP 644100 62720805851L | AE31: 851L | AF31: 62720805851L | AL31: A01 | AO31: 99999
A32: 0 | B32: 1 | K32: 50 | L32: 644100 | N32: 556.71 | V32: Transfer to WIP | W32: Transfer to WIP 644100 62720801852I | AE32: 852I | AF32: 62720801852I | AL32: A01 | AO32: 99999
A33: 0 | B33: 1 | K33: 50 | L33: 644100 | N33: 491.6 | V33: Transfer to WIP | W33: Transfer to WIP 644100 62720801852J | AE33: 852J | AF33: 62720801852J | AL33: A01 | AO33: 99999
A34: 0 | B34: 1 | K34: 50 | L34: 644100 | N34: 331.83 | V34: Transfer to WIP | W34: Transfer to WIP 644100 62720803852J | AE34: 852J | AF34: 62720803852J | AL34: A01 | AO34: 99999
A35: 0 | B35: 1 | K35: 50 | L35: 644100 | N35: 594.21 | V35: Transfer to WIP | W35: Transfer to WIP 644100 62720805852J | AE35: 852J | AF35: 62720805852J | AL35: A01 | AO35: 99999
A36: 0 | B36: 1 | K36: 50 | L36: 644100 | N36: 368.6 | V36: Transfer to WIP | W36: Transfer to WIP 644100 62720899852J | AE36: 852J | AF36: 62720899852J | AL36: A01 | AO36: 99999
A37: 0 | B37: 1 | K37: 50 | L37: 644500 | N37: 1121.94 | V37: Transfer to WIP | W37: Transfer to WIP 644500 627301021213 | AE37: 1213 | AF37: 627301021213 | AL37: A01 | AO37: 99999
A38: 0 | B38: 1 | K38: 50 | L38: 644500 | N38: 648 | V38: Transfer to WIP | W38: Transfer to WIP 644500 627301991213 | AE38: 1213 | AF38: 627301991213 | AL38: A01 | AO38: 99999
A39: 0 | B39: 1 | K39: 50 | L39: 644500 | N39: 11634.17 | V39: Transfer to WIP | W39: Transfer to WIP 644500 627301011511 | AE39: 1511 | AF39: 627301011511 | AL39: A01 | AO39: 99999
A40: 0 | B40: 1 | K40: 50 | L40: 644500 | N40: 495.94 | V40: Transfer to WIP | W40: Transfer to WIP 644500 627301013212 | AE40: 3212 | AF40: 627301013212 | AL40: A01 | AO40: 99999
A41: 0 | B41: 1 | K41: 50 | L41: 644500 | N41: 698.46 | V41: Transfer to WIP | W41: Transfer to WIP 644500 627301018312 | AE41: 8312 | AF41: 627301018312 | AL41: A01 | AO41: 99999
A42: 0 | B42: 1 | K42: 50 | L42: 644500 | N42: 827.32 | V42: Transfer to WIP | W42: Transfer to WIP 644500 627301018514 | AE42: 8514 | AF42: 627301018514 | AL42: A01 | AO42: 99999
A43: 0 | B43: 1 | K43: 50 | L43: 644500 | N43: 76.45 | V43: Transfer to WIP | W43: Transfer to WIP 644500 627301028514 | AE43: 8514 | AF43: 627301028514 | AL43: A01 | AO43: 99999
A44: 0 | B44: 1 | K44: 50 | L44: 644500 | N44: 8.6 | V44: Transfer to WIP | W44: Transfer to WIP 644500 62730101321M | AE44: 321M | AF44: 62730101321M | AL44: A01 | AO44: 99999
A45: 0 | B45: 1 | K45: 50 | L45: 644500 | N45: 22.7 | V45: Transfer to WIP | W45: Transfer to WIP 644500 62730101321P | AE45: 321P | AF45: 62730101321P | AL45: A01 | AO45: 99999
A46: 0 | B46: 1 | K46: 50 | L46: 644500 | N46: 77.84 | V46: Transfer to WIP | W46: Transfer to WIP 644500 62730103331M | AE46: 331M | AF46: 62730103331M | AL46: A01 | AO46: 99999
A47: 0 | B47: 1 | K47: 50 | L47: 644500 | N47: 390.6 | V47: Transfer to WIP | W47: Transfer to WIP 644500 62730101851C | AE47: 851C | AF47: 62730101851C | AL47: A01 | AO47: 99999
A48: 0 | B48: 1 | K48: 50 | L48: 644500 | N48: 712.99 | V48: Transfer to WIP | W48: Transfer to WIP 644500 62730101851I | AE48: 851I | AF48: 62730101851I | AL48: A01 | AO48: 99999
A49: 0 | B49: 1 | K49: 50 | L49: 644500 | N49: 328.79 | V49: Transfer to WIP | W49: Transfer to WIP 644500 62730101851L | AE49: 851L | AF49: 62730101851L | AL49: A01 | AO49: 99999
A50: 0 | B50: 1 | K50: 50 | L50: 644500 | N50: 68.26 | V50: Transfer to WIP | W50: Transfer to WIP 644500 62730101852I | AE50: 852I | AF50: 62730101852I | AL50: A01 | AO50: 99999
A51: 0 | B51: 1 | K51: 50 | L51: 644500 | N51: 761.95 | V51: Transfer to WIP | W51: Transfer to WIP 644500 62730101852J | AE51: 852J | AF51: 62730101852J | AL51: A01 | AO51: 99999
A52: 0 | B52: 1 | K52: 50 | L52: 651110 | N52: 4710.44 | V52: Transfer to WIP | W52: Transfer to WIP 651110 627304013221 | AE52: 3221 | AF52: 627304013221 | AL52: A01 | AO52: 99999
A53: 0 | B53: 1 | K53: 50 | L53: 651110 | N53: 21257.59 | V53: Transfer to WIP | W53: Transfer to WIP 651110 627304018111 | AE53: 8111 | AF53: 627304018111 | AL53: A01 | AO53: 99999
A54: 0 | B54: 1 | K54: 50 | L54: 651110 | N54: 3908.35 | V54: Transfer to WIP | W54: Transfer to WIP 651110 627304018312 | AE54: 8312 | AF54: 627304018312 | AL54: A01 | AO54: 99999
A55: 0 | B55: 1 | K55: 50 | L55: 651110 | N55: 382.22 | V55: Transfer to WIP | W55: Transfer to WIP 651110 627304048312 | AE55: 8312 | AF55: 627304048312 | AL55: A01 | AO55: 99999
A56: 0 | B56: 1 | K56: 50 | L56: 651110 | N56: 887.56 | V56: Transfer to WIP | W56: Transfer to WIP 651110 627304018514 | AE56: 8514 | AF56: 627304018514 | AL56: A01 | AO56: 99999
A57: 0 | B57: 1 | K57: 50 | L57: 665010 | N57: 2824.8 | V57: Transfer to WIP | W57: Transfer to WIP 665010 62771302321P | AE57: 321P | AF57: 62771302321P | AL57: A01 | AO57: 99999
A58: 0 | B58: 1 | K58: 50 | L58: 667001 | N58: 307.1 | V58: Transfer to WIP | W58: Transfer to WIP 667001 627714011213 | AE58: 1213 | AF58: 627714011213 | AL58: A01 | AO58: 99999
A59: 0 | B59: 1 | K59: 50 | L59: 667001 | N59: 1016.19 | V59: Transfer to WIP | W59: Transfer to WIP 667001 627714021213 | AE59: 1213 | AF59: 627714021213 | AL59: A01 | AO59: 99999
A60: 0 | B60: 1 | K60: 50 | L60: 667001 | N60: 4.24 | V60: Transfer to WIP | W60: Transfer to WIP 667001 627714031213 | AE60: 1213 | AF60: 627714031213 | AL60: A01 | AO60: 99999
A61: 0 | B61: 1 | K61: 50 | L61: 667111 | N61: 827.17 | V61: Transfer to WIP | W61: Transfer to WIP 667111 627303011213 | AE61: 1213 | AF61: 627303011213 | AL61: A01 | AO61: 99999
A62: 0 | B62: 1 | K62: 50 | L62: 667111 | N62: 722.89 | V62: Transfer to WIP | W62: Transfer to WIP 667111 627303021213 | AE62: 1213 | AF62: 627303021213 | AL62: A01 | AO62: 99999
A63: 0 | B63: 1 | K63: 50 | L63: 667111 | N63: 13.22 | V63: Transfer to WIP | W63: Transfer to WIP 667111 627303018111 | AE63: 8111 | AF63: 627303018111 | AL63: A01 | AO63: 99999
A64: 0 | B64: 1 | K64: 50 | L64: 667111 | N64: 13.22 | V64: Transfer to WIP | W64: Transfer to WIP 667111 627303018411 | AE64: 8411 | AF64: 627303018411 | AL64: A01 | AO64: 99999
A65: 0 | B65: 1 | K65: 50 | L65: 667111 | N65: 13.22 | V65: Transfer to WIP | W65: Transfer to WIP 667111 627303018514 | AE65: 8514 | AF65: 627303018514 | AL65: A01 | AO65: 99999
A66: 0 | B66: 1 | K66: 50 | L66: 667111 | N66: 9.83 | V66: Transfer to WIP | W66: Transfer to WIP 667111 62730301321M | AE66: 321M | AF66: 62730301321M | AL66: A01 | AO66: 99999
A67: 0 | B67: 1 | K67: 50 | L67: 667111 | N67: 41.12 | V67: Transfer to WIP | W67: Transfer to WIP 667111 62730301851I | AE67: 851I | AF67: 62730301851I | AL67: A01 | AO67: 99999
A68: 0 | B68: 1 | K68: 50 | L68: 667821 | N68: 1522.02 | V68: Transfer to WIP | W68: Transfer to WIP 667821 627810011213 | AE68: 1213 | AF68: 627810011213 | AL68: A01 | AO68: 99999
A69: 0 | B69: 1 | K69: 50 | L69: 667821 | N69: 2042.31 | V69: Transfer to WIP | W69: Transfer to WIP 667821 627810021213 | AE69: 1213 | AF69: 627810021213 | AL69: A01 | AO69: 99999
A70: 0 | B70: 1 | K70: 50 | L70: 667821 | N70: 260.95 | V70: Transfer to WIP | W70: Transfer to WIP 667821 62781001331M | AE70: 331M | AF70: 62781001331M | AL70: A01 | AO70: 99999
A71: 0 | B71: 1 | K71: 50 | L71: 667821 | N71: 228.33 | V71: Transfer to WIP | W71: Transfer to WIP 667821 62781001851H | AE71: 851H | AF71: 62781001851H | AL71: A01 | AO71: 99999
A72: 0 | B72: 1 | K72: 50 | L72: 667821 | N72: 151.48 | V72: Transfer to WIP | W72: Transfer to WIP 667821 62781001851I | AE72: 851I | AF72: 62781001851I | AL72: A01 | AO72: 99999
A73: 0 | B73: 1 | K73: 50 | L73: 667821 | N73: 293.58 | V73: Transfer to WIP | W73: Transfer to WIP 667821 62781001852J | AE73: 852J | AF73: 62781001852J | AL73: A01 | AO73: 99999
A74: 0 | B74: 1 | K74: 50 | L74: 667831 | N74: 175.33 | V74: Transfer to WIP | W74: Transfer to WIP 667831 627811021213 | AE74: 1213 | AF74: 627811021213 | AL74: A01 | AO74: 99999
A75: 0 | B75: 1 | K75: 50 | L75: 668000 | N75: 5059.28 | V75: Transfer to WIP | W75: Transfer to WIP 668000 627722011511 | AE75: 1511 | AF75: 627722011511 | AL75: A01 | AO75: 99999
A76: 0 | B76: 1 | K76: 50 | L76: 668000 | N76: 40125.06 | V76: Transfer to WIP | W76: Transfer to WIP 668000 627722021511 | AE76: 1511 | AF76: 627722021511 | AL76: A01 | AO76: 99999
A77: 0 | B77: 1 | K77: 50 | L77: 671000 | N77: 27315.6 | V77: Transfer to WIP | W77: Transfer to WIP 671000 627705013311 | AE77: 3311 | AF77: 627705013311 | AL77: A01 | AO77: 99999
A78: 0 | B78: 1 | K78: 50 | L78: 671000 | N78: 550.54 | V78: Transfer to WIP | W78: Transfer to WIP 671000 627705993311 | AE78: 3311 | AF78: 627705993311 | AL78: A01 | AO78: 99999
A79: 0 | B79: 1 | K79: 50 | L79: 673001 | N79: 31603.72 | V79: Transfer to WIP | W79: Transfer to WIP 673001 627701211611 | AE79: 1611 | AF79: 627701211611 | AL79: A01 | AO79: 99999
A80: 0 | B80: 1 | K80: 50 | L80: 673002 | N80: 818.67 | V80: Transfer to WIP | W80: Transfer to WIP 673002 627703028311 | AE80: 8311 | AF80: 627703028311 | AL80: A01 | AO80: 99999
A81: 0 | B81: 1 | K81: 50 | L81: 688805 | N81: 200.64 | V81: Transfer to WIP | W81: Transfer to WIP 688805 627899993221 | AE81: 3221 | AF81: 627899993221 | AL81: A01 | AO81: 99999
A82: 0 | B82: 1 | K82: 50 | L82: 691200 | N82: 99114.03 | V82: Transfer to WIP | W82: Transfer to WIP 691200 621002008511 | AE82: 8511 | AF82: 621002008511 | AL82: A01 | AO82: 99999
A83: 0 | B83: 1 | K83: 50 | L83: 665010 | N83: 196.8 | V83: Transfer to WIP | W83: Transfer to WIP 665010 62771301321M | AE83: 321M | AF83: 62771301321M | AL83: A01 | AO83: 99999
A84: 0 | B84: 1 | K84: 50 | L84: 654010 | N84: 35992 | V84: Transfer to WIP | W84: Transfer to WIP 654010 627400031611 | AE84: 1611 | AF84: 627400031611 | AL84: A01 | AO84: 99999
A85: 0 | B85: 1 | K85: 50 | L85: 654010 | N85: 34700 | V85: Transfer to WIP | W85: Transfer to WIP 654010 627400041611 | AE85: 1611 | AF85: 627400041611 | AL85: A01 | AO85: 99999
A86: 0 | B86: 1 | K86: 50 | L86: 654010 | N86: 255434.42 | V86: Transfer to WIP | W86: Transfer to WIP 654010 627400051611 | AE86: 1611 | AF86: 627400051611 | AL86: A01 | AO86: 99999
A87: 0 | B87: 1 | K87: 50 | L87: 654010 | N87: 19087 | V87: Transfer to WIP | W87: Transfer to WIP 654010 627400061611 | AE87: 1611 | AF87: 627400061611 | AL87: A01 | AO87: 99999
A88: 0 | B88: 1 | K88: 50 | L88: 654010 | N88: 87989 | V88: Transfer to WIP | W88: Transfer to WIP 654010 627400071611 | AE88: 1611 | AF88: 627400071611 | AL88: A01 | AO88: 99999
A89: 0 | B89: 1 | K89: 50 | L89: 661001 | N89: 237.76 | V89: Transfer to WIP | W89: Transfer to WIP 661001 627805113211 | AE89: 3211 | AF89: 627805113211 | AL89: A01 | AO89: 99999
A90: 0 | B90: 1 | K90: 50 | L90: 661001 | N90: 287.72 | V90: Transfer to WIP | W90: Transfer to WIP 661001 627805113221 | AE90: 3221 | AF90: 627805113221 | AL90: A01 | AO90: 99999
A91: 0 | B91: 1 | K91: 50 | L91: 661001 | N91: 1031.79 | V91: Transfer to WIP | W91: Transfer to WIP 661001 627805128111 | AE91: 8111 | AF91: 627805128111 | AL91: A01 | AO91: 99999
A92: 0 | B92: 1 | K92: 50 | L92: 661001 | N92: 8.2 | V92: Transfer to WIP | W92: Transfer to WIP 661001 627805118311 | AE92: 8311 | AF92: 627805118311 | AL92: A01 | AO92: 99999
A93: 0 | B93: 1 | K93: 50 | L93: 661001 | N93: 91.18 | V93: Transfer to WIP | W93: Transfer to WIP 661001 627805118411 | AE93: 8411 | AF93: 627805118411 | AL93: A01 | AO93: 99999
A94: 0 | B94: 1 | K94: 50 | L94: 661001 | N94: 2617.38 | V94: Transfer to WIP | W94: Transfer to WIP 661001 627805128411 | AE94: 8411 | AF94: 627805128411 | AL94: A01 | AO94: 99999
A95: 0 | B95: 1 | K95: 50 | L95: 661001 | N95: 3030.42 | V95: Transfer to WIP | W95: Transfer to WIP 661001 627805128511 | AE95: 8511 | AF95: 627805128511 | AL95: A01 | AO95: 99999
... A105: 0 | B105: 1 | K105: 50 | L105: 665000 | N105: 41749.76 | V105: Transfer to WIP | W105: Transfer to WIP 665000 627201028411 | AE105: 8411 | AF105: 627201028411 | AL105: A01 | AO105: 99999
A106: 0 | B106: 1 | K106: 50 | L106: 665000 | N106: 1450.49 | V106: Transfer to WIP | W106: Transfer to WIP 665000 62720101321M | AE106: 321M | AF106: 62720101321M | AL106: A01 | AO106: 99999
A107: 0 | B107: 1 | K107: 50 | L107: 665000 | N107: 6404.73 | V107: Transfer to WIP | W107: Transfer to WIP 665000 62720102321P | AE107: 321P | AF107: 62720102321P | AL107: A01 | AO107: 99999
A108: 0 | B108: 1 | K108: 50 | L108: 665010 | N108: 74.17 | V108: Transfer to WIP | W108: Transfer to WIP 665010 627713023211 | AE108: 3211 | AF108: 627713023211 | AL108: A01 | AO108: 99999
A109: 0 | B109: 1 | K109: 50 | L109: 665010 | N109: 617.39 | V109: Transfer to WIP | W109: Transfer to WIP 665010 627713018411 | AE109: 8411 | AF109: 627713018411 | AL109: A01 | AO109: 99999
...

Sheet Feb
A1: Kết xuất ZVF59 từ SAP, copy thay dữ liệu từ A2 -> BO210 | G1: (Kết chuyển chi phí)

Sheet Mar
A1: Kết xuất ZVF59 từ SAP, copy thay dữ liệu từ A2 -> BO210 | G1: (K/C chi phí)

Sheet Apr
A1: Kết xuất ZVF59 từ SAP, copy thay dữ liệu từ A2

Sheet May
A1: Kết xuất ZVF59 từ SAP, copy thay dữ liệu từ A2 -> BO210

Sheet Jun
A1: Kết xuất ZVF59 từ SAP, copy thay dữ liệu từ A2 -> cột BN

Sheet Jul
A1: Kết xuất ZVF59 từ SAP, copy thay dữ liệu từ A2 -> cột BN

Sheet Aug
A1: Kết xuất ZVF59 từ SAP, copy thay dữ liệu từ A2 -> cột BN

Sheet Sep
A1: Kết xuất ZVF59 từ SAP, copy thay dữ liệu từ A2 -> cột BN

Sheet Oct
A1: Kết xuất ZVF59 từ SAP, copy thay dữ liệu từ A2 -> cột BN

Sheet Nov
A1: Kết xuất ZVF59 từ SAP, copy thay dữ liệu từ A2 -> cột BN

Sheet Dec
A1: Kết xuất ZVF59 từ SAP, copy thay dữ liệu từ A2 -> cột BN

Sheet Tire Weight
A1: Monthly update
B3: Source: | C3: ..\..\..\..\1-ALL\11. 8411\04. TS-Share\08. TS-ACC\RRW update.xlsx | I3: \\10.118.29.7\BTMV-Data\4-ACCOUNTING\71.Costing\1. Costing calculation\2023\Tire weight report\
B4: Please confirm with Nam-san before input data | I4: Tire Weight Tolerance provided by TS
A5: BPC & BTMV Code | B5: BPC | C5: BTMV Code | D5: Tire weight | E5: RRT | I5: BPC | J5: ACTUAL Weight | K5: Plant Process Weight | L5: %
A7: =B7&"-"&C7 -> PSR0V039-BLFVA | B7: PSR0V039 | C7: BLFVA | D7: 6.895 | E7: 3.438 | I7: PSR0V229 | J7: 4.9413261 | K7: 4.929 | L7: =J7/K7 -> 1.0025007
A8: =B8&"-"&C8 -> PSR0VB0F-D3MVA | B8: PSR0VB0F | C8: D3MVA | D8: 8.778 | E8: 4.099 | I8: PSR0V234 | J8: 5.0941341 | K8: 5.082 | L8: =J8/K8 -> 1.0023877
A9: =B9&"-"&C9 -> PSR0V035-DEFVA | B9: PSR0V035 | C9: DEFVA | D9: 5.538 | E9: 2.726 | I9: PSR0VF6F | J9: 12.209864 | K9: 12.219 | L9: =J9/K9 -> 0.99925234
A10: =B10&"-"&C10 -> PSR0V122-YBGVA | B10: PSR0V122 | C10: YBGVA | D10: 9.02 | E10: 4.267 | I10: PSR0VE9F | J10: 7.2400054 | K10: 7.252 | L10: =J10/K10 -> 0.99834602
A11: =B11&"-"&C11 -> PSR0V11F-EAEVA | B11: PSR0V11F | C11: EAEVA | D11: 6.126 | E11: 3.066 | I11: PSR0VH3F | J11: 8.5335681 | K11: 8.592 | L11: =J11/K11 -> 0.99319927
A12: =B12&"-"&C12 -> PSR0V124-KLTZA | B12: PSR0V124 | C12: KLTZA | D12: 10.268 | E12: 4.481 | I12: PSR0V240 | J12: 6.8673224 | K12: 6.845 | L12: =J12/K12 -> 1.0032611
A13: =B13&"-"&C13 -> PSR0V73F-WMTZA | B13: PSR0V73F | C13: WMTZA | D13: 10.268 | E13: 4.481 | I13: PSR0V05B | J13: 7.5226188 | K13: 7.515 | L13: =J13/K13 -> 1.0010138
A14: =B14&"-"&C14 -> PSR0V18F-GBAVA | B14: PSR0V18F | C14: GBAVA | D14: 7.48 | E14: 3.794 | I14: PSR0V81F | J14: 8.3890386 | K14: 8.39 | L14: =J14/K14 -> 0.99988542
A15: =B15&"-"&C15 -> PSR0V19F-SHTVA | B15: PSR0V19F | C15: SHTVA | D15: 7.48 | E15: 3.794 | I15: PSR0VJ7F | J15: 7.4972794 | K15: 7.608 | L15: =J15/K15 -> 0.98544683
A16: =B16&"-"&C16 -> PSR0VB3F-TENVA | B16: PSR0VB3F | C16: TENVA | D16: 8.318 | E16: 3.951 | I16: PSR0VH9F | J16: 10.112926 | K16: 10.017 | L16: =J16/K16 -> 1.0095763
A17: =B17&"-"&C17 -> PSR0V16D-HGKZA | B17: PSR0V16D | C17: HGKZA | D17: 11.726 | E17: 5.447 | I17: PSR0VH8F | J17: 10.685916 | K17: 10.723 | L17: =J17/K17 -> 0.99654166
A18: =B18&"-"&C18 -> PSR0V109-HPBVA | B18: PSR0V109 | C18: HPBVA | D18: 8.323 | E18: 4.112 | I18: PSR0VJ8F | J18: 7.1398197 | K18: 7.096 | L18: =J18/K18 -> 1.0061753
... A57: =B57&"-"&C57 -> PSR0V02P-QP3VA | B57: PSR0V02P | C57: QP3VA | D57: 8.892 | E57: 4.138 | I57: PSR0V149 | J57: 9.1933144 | K57: 9.116 | L57: =J57/K57 -> 1.0084812
A58: =B58&"-"&C58 -> PSR0VB2F-YK2VA | B58: PSR0VB2F | C58: YK2VA | D58: 7.976 | E58: #N/A | I58: PSR0V50D | J58: 9.235988 | K58: 9.227 | L58: =J58/K58 -> 1.0009741
A59: =B59&"-"&C59 -> PSR0V113-S3NVA | B59: PSR0V113 | C59: S3NVA | D59: 7.397 | E59: 3.623 | I59: PSR0V52D | J59: 9.7224699 | K59: 9.777 | L59: =J59/K59 -> 0.99442261
A60: =B60&"-"&C60 -> PSR0V78F-DKHZA | B60: PSR0V78F | C60: DKHZA | D60: 10.919 | E60: 4.741 | I60: PSR0VF2F | J60: 7.4069531 | K60: 7.506 | L60: =J60/K60 -> 0.98680431
A61: =B61&"-"&C61 -> PSR0V123-PLLZA | B61: PSR0V123 | C61: PLLZA | D61: 10.474 | E61: 5.039 | I61: PSR0V23D | J61: 13.258639 | K61: 13.335 | L61: =J61/K61 -> 0.99427367
A62: =B62&"-"&C62 -> PSR0V74F-JRVZA | B62: PSR0V74F | C62: JRVZA | D62: 12.278 | E62: 5.425 | I62: PSR0V225 | J62: 16.47381 | K62: 16.08 | L62: =J62/K62 -> 1.0244906
A63: =B63&"-"&C63 -> PSR0V92F-GMDVA | B63: PSR0V92F | C63: GMDVA | D63: 9.071 | E63: 4.305 | I63: PSR0V168 | J63: 10.174858 | K63: 10.209 | L63: =J63/K63 -> 0.9966557
A64: =B64&"-"&C64 -> PSR0V87F-EMYVA | B64: PSR0V87F | C64: EMYVA | D64: 8.969 | E64: 4.225 | I64: PSR0V51D | J64: 9.895533 | K64: 9.963 | L64: =J64/K64 -> 0.99322824
A65: =B65&"-"&C65 -> PSR0V85F-TCTVA | B65: PSR0V85F | C65: TCTVA | D65: 11.629 | E65: 5.484 | I65: PSR0V169 | J65: 10.752599 | K65: 10.753 | L65: =J65/K65 -> 0.99996268
A66: =B66&"-"&C66 -> PSR0V80F-VHXVA | B66: PSR0V80F | C66: VHXVA | D66: 10.017 | E66: 4.79 | I66: PSR0VG2F | J66: 12.457596 | K66: 12.435 | L66: =J66/K66 -> 1.0018171
A67: =B67&"-"&C67 -> PSR0V84F-ENGVA | B67: PSR0V84F | C67: ENGVA | D67: 10.09 | E67: 4.832 | I67: PSR0V16D | J67: 11.498491 | K67: 11.471 | L67: =J67/K67 -> 1.0023965
A68: =B68&"-"&C68 -> PSR0VA0F-PCXVA | B68: PSR0VA0F | C68: PCXVA | D68: 8.923 | E68: 4.084 | I68: PSR0V187 | J68: 11.478711 | K68: 11.405 | L68: =J68/K68 -> 1.0064631
A69: =B69&"-"&C69 -> PSR0V83F-VSTVA | B69: PSR0V83F | C69: VSTVA | D69: 7.546 | E69: 3.642 | I69: PSR0V165 | J69: 8.5164055 | K69: 8.512 | L69: =J69/K69 -> 1.0005176
A70: =B70&"-"&C70 -> PSR0V93F-EGGVA | B70: PSR0V93F | C70: EGGVA | D70: 8.732 | E70: 4.048 | I70: PSR0V164 | J70: 11.610099 | K70: 11.557 | L70: =J70/K70 -> 1.0045945
... A88: =B88&"-"&C88 -> PSR0V155-TWWZA | B88: PSR0V155 | C88: TWWZA | D88: 12.435 | E88: 5.539 | I88: PSR0VG6F | J88: 10.918174 | K88: 10.816 | L88: =J88/K88 -> 1.0094466
A89: =B89&"-"&C89 -> PSR0V88F-TDHVA | B89: PSR0V88F | C89: TDHVA | D89: 10.723 | E89: 5.057 | L89: =J89/K89 -> #DIV/0!
A90: =B90&"-"&C90 -> PSR0V81F-WETVA | B90: PSR0V81F | C90: WETVA | D90: 8.39 | E90: 4.052 | I90: PSR0V229 | J90: 4.9614622 | K90: 4.929 | L90: =J90/K90 -> 1.006586
A91: =B91&"-"&C91 -> PSR0V043-WLLVA | B91: PSR0V043 | C91: WLLVA | D91: 8.426 | E91: 4.219 | I91: PSR0V234 | J91: 5.1168214 | K91: 5.074 | L91: =J91/K91 -> 1.0084394
A92: =B92&"-"&C92 -> PSR0V91F-REXVA | B92: PSR0V91F | C92: REXVA | D92: 8.624 | E92: 4.033 | I92: PSR0VE9F | J92: 7.263781 | K92: 7.252 | L92: =J92/K92 -> 1.0016245
A93: =B93&"-"&C93 -> PSR0V005-DLVVA | B93: PSR0V005 | C93: DLVVA | D93: 7.732 | E93: 3.875 | I93: PSR0V86F | J93: 8.8744542 | K93: 8.864 | L93: =J93/K93 -> 1.0011794
A94: =B94&"-"&C94 -> PSR0V114-S4NVA | B94: PSR0V114 | C94: S4NVA | D94: 8.338 | E94: 4.03 | I94: PSR0VF2F | J94: 7.4734964 | K94: 7.506 | L94: =J94/K94 -> 0.99566965
A95: =B95&"-"&C95 -> PSR0V135-XBBVA | B95: PSR0V135 | C95: XBBVA | D95: 10.683 | E95: 5.061 | I95: PSR0V92F | J95: 9.1703563 | K95: 9.071 | L95: =J95/K95 -> 1.0109532
A96: =B96&"-"&C96 -> PSR0V77F-SYTZA | B96: PSR0V77F | C96: SYTZA | D96: 11.92 | E96: 5.244 | I96: PSR0V194 | J96: 8.1236966 | K96: 8.089 | L96: =J96/K96 -> 1.0042894
A97: =B97&"-"&C97 -> PSR0V65F-VKEVA | B97: PSR0V65F | C97: VKEVA | D97: 10.326 | E97: 4.669 | I97: PSR0V87F | J97: 9.0148658 | K97: 8.969 | L97: =J97/K97 -> 1.0051138
A98: =B98&"-"&C98 -> PSR0VA6F-VFFVA | B98: PSR0VA6F | C98: VFFVA | D98: 8.104 | E98: 3.85 | I98: PSR0VF6F | J98: 12.236056 | K98: 12.219 | L98: =J98/K98 -> 1.0013958
A99: =B99&"-"&C99 -> PSR0VA5F-VECVA | B99: PSR0VA5F | C99: VECVA | D99: 8.104 | E99: 3.85 | I99: PSR0VJ7F | J99: 7.5165883 | K99: 7.608 | L99: =J99/K99 -> 0.98798479
A100: =B100&"-"&C100 -> PSR0VA7F-VMUVA | B100: PSR0VA7F | C100: VMUVA | D100: 8.104 | E100: 3.85 | I100: PSR0V240 | J100: 6.9301814 | K100: 6.845 | L100: =J100/K100 -> 1.0124443
A101: =B101&"-"&C101 -> PSR0V118-S8NVA | B101: PSR0V118 | C101: S8NVA | D101: 9.161 | E101: 4.462 | I101: PSR0V173 | J101: 10.753428 | K101: 10.704 | L101: =J101/K101 -> 1.0046177
... A157: =B157&"-"&C157 -> PSR0V06P-WBPVA | B157: PSR0V06P | C157: WBPVA | D157: 7.386 | E157: 3.583 | I157: PSR0V256 | J157: 12.313 | K157: 12.349197 | L157: =J157/K157 -> 0.99706884
A158: =B158&"-"&C158 -> PSR0V169-GJDZA | B158: PSR0V169 | C158: GJDZA | D158: 10.753 | E158: 4.754 | L158: =J158/K158 -> #DIV/0!
A159: =B159&"-"&C159 -> PSR0V168-JXKVA | B159: PSR0V168 | C159: JXKVA | D159: 10.209 | E159: 4.579 | L159: =J159/K159 -> #DIV/0!
A160: =B160&"-"&C160 -> PSR0V21S-BZKZA | B160: PSR0V21S | C160: BZKZA | D160: 11.161 | E160: 5.028
A161: =B161&"-"&C161 -> PSR0V22S-CZVZA | B161: PSR0V22S | C161: CZVZA | D161: 12.08 | E161: 5.507 | L161: =J161/K161 -> #DIV/0!
A162: =B162&"-"&C162 -> PSR0V158-WCKVA | B162: PSR0V158 | C162: WCKVA | D162: 8.504 | E162: 4.076 | L162: =J162/K162 -> #DIV/0!
A163: =B163&"-"&C163 -> PSR0V151-RBMVA | B163: PSR0V151 | C163: RBMVA | D163: 6.154 | E163: 2.989 | L163: =J163/K163 -> #DIV/0!
A164: =B164&"-"&C164 -> PSR0V184-JCGZA | B164: PSR0V184 | C164: JCGZA | D164: 11.806 | E164: 5.259 | L164: =J164/K164 -> #DIV/0!
A165: =B165&"-"&C165 -> PSR0V183-LGYZA | B165: PSR0V183 | C165: LGYZA | D165: 12.553 | E165: 5.626 | L165: =J165/K165 -> #DIV/0!
A166: =B166&"-"&C166 -> PSR0V170-FMNVA | B166: PSR0V170 | C166: FMNVA | D166: 8.534 | E166: 4.019 | L166: =J166/K166 -> #DIV/0!
A167: =B167&"-"&C167 -> PSR0V179-DPJVA | B167: PSR0V179 | C167: DPJVA | D167: 6.546 | E167: 3.106 | L167: =J167/K167 -> #DIV/0!
A168: =B168&"-"&C168 -> PSR0V178-KVQVA | B168: PSR0V178 | C168: KVQVA | D168: 6.277 | E168: 2.987 | L168: =J168/K168 -> #DIV/0!
A169: =B169&"-"&C169 -> PSR0V177-XDFVA | B169: PSR0V177 | C169: XDFVA | D169: 6.679 | E169: 3.147 | L169: =J169/K169 -> #DIV/0!
A170: =B170&"-"&C170 -> PSR0V180-JYDVA | B170: PSR0V180 | C170: JYDVA | D170: 6.661 | E170: 3.138 | L170: =J170/K170 -> #DIV/0!
A171: =B171&"-"&C171 -> PSR0V185-EWPVA | B171: PSR0V185 | C171: EWPVA | D171: 8.16 | E171: 3.898 | L171: =J171/K171 -> #DIV/0!
A172: =B172&"-"&C172 -> PSR0V43D-VYFZA | B172: PSR0V43D | C172: VYFZA | D172: 13.511 | E172: 6.297 | L172: =J172/K172 -> #DIV/0!
... A301: =B301&"-"&C301 -> PSR0V256-3LHZA | B301: PSR0V256 | C301: 3LHZA | D301: 12.313 | E301: 5.583 | L301: =J301/K301 -> #DIV/0!
A302: =B302&"-"&C302 -> - | L302: =J302/K302 -> #DIV/0!
A303: =B303&"-"&C303 -> - | L303: =J303/K303 -> #DIV/0!
A304: =B304&"-"&C304 -> - | L304: =J304/K304 -> #DIV/0!
A305: =B305&"-"&C305 -> - | L305: =J305/K305 -> #DIV/0!
A306: =B306&"-"&C306 -> - | L306: =J306/K306 -> #DIV/0!
A307: =B307&"-"&C307 -> - | L307: =J307/K307 -> #DIV/0!
A308: =B308&"-"&C308 -> - | L308: =J308/K308 -> #DIV/0!
A309: =B309&"-"&C309 -> - | L309: =J309/K309 -> #DIV/0!
A310: =B310&"-"&C310 -> - | L310: =J310/K310 -> #DIV/0!
A311: =B311&"-"&C311 -> - | L311: =J311/K311 -> #DIV/0!
A312: =B312&"-"&C312 -> - | L312: =J312/K312 -> #DIV/0!
A313: =B313&"-"&C313 -> - | L313: =J313/K313 -> #DIV/0!
A314: =B314&"-"&C314 -> - | L314: =J314/K314 -> #DIV/0!
A315: =B315&"-"&C315 -> -
A316: =B316&"-"&C316 -> - | L316: =J316/K316 -> #DIV/0!
A317: =B317&"-"&C317 -> - | L317: =J317/K317 -> #DIV/0!
A318: =B318&"-"&C318 -> - | L318: =J318/K318 -> #DIV/0!
A319: =B319&"-"&C319 -> - | L319: =J319/K319 -> #DIV/0!
A320: =B320&"-"&C320 -> - | L320: =J320/K320 -> #DIV/0!
A321: =B321&"-"&C321 -> - | L321: =J321/K321 -> #DIV/0!
A322: =B322&"-"&C322 -> - | L322: =J322/K322 -> #DIV/0!
A323: =B323&"-"&C323 -> - | L323: =J323/K323 -> #DIV/0!
A324: =B324&"-"&C324 -> - | L324: =J324/K324 -> #DIV/0!
A325: =B325&"-"&C325 -> - | L325: =J325/K325 -> #DIV/0!
A326: =B326&"-"&C326 -> - | L326: =J326/K326 -> #DIV/0!
A327: =B327&"-"&C327 -> - | L327: =J327/K327 -> #DIV/0!
... A389: =B389&"-"&C389 -> - | L389: =J389/K389 -> #DIV/0!
A390: =B390&"-"&C390 -> -
A391: =B391&"-"&C391 -> - | L391: =J391/K391 -> #DIV/0!
A392: =B392&"-"&C392 -> - | L392: =J392/K392 -> #DIV/0!
A393: =B393&"-"&C393 -> - | L393: =J393/K393 -> #DIV/0!
A394: =B394&"-"&C394 -> - | L394: =J394/K394 -> #DIV/0!
A395: =B395&"-"&C395 -> - | L395: =J395/K395 -> #DIV/0!
A396: =B396&"-"&C396 -> - | L396: =J396/K396 -> #DIV/0!
A397: =B397&"-"&C397 -> - | L397: =J397/K397 -> #DIV/0!
A398: =B398&"-"&C398 -> - | L398: =J398/K398 -> #DIV/0!
A399: =B399&"-"&C399 -> - | L399: =J399/K399 -> #DIV/0!
A400: =B400&"-"&C400 -> - | L400: =J400/K400 -> #DIV/0!
A401: =B401&"-"&C401 -> - | L401: =J401/K401 -> #DIV/0!
...

Sheet DM-Sum
B1: DM COST CALCULATION
B2: Month: | C2: ='FACTORY COST'!G2 -> Jan
E4: Predetermined | G4: Theoretical | I4: Theor. Vs Pre. | K4: Actual | N4: Act vs Theor.
B5: BPC | C5: Pro. Code | D5: Quantities | E5: Cost/Tire | F5: DMC | G5: Cost/Tire | H5: DMC | I5: Gap | J5: % | K5: Tire Wt. % (Act vs. Process) | L5: Unit price | M5: DMC | N5: Gap
B6: PSR0V01B | C6: =VLOOKUP(B6,'MFG COST SUMMARY'!C:E,3,0) -> GSGVA | D6: 433 | E6: 12.295984 | F6: =E6*D6 -> 5324.161 | G6: 9.7010121 | H6: =+D6*G6 -> 4200.5382 | I6: =H6-F6 -> -1123.6227 | J6: =+H6/F6 -> 0.78895778 | K6: =IFERROR(VLOOKUP($B6,'Tire Weight'!$I:$L,4,0),1) -> 1.0007393 | L6: =G6*K6 -> 9.7081839 | M6: =+H6*K6 -> 4203.6436 | N6: =M6-H6 -> 3.1053944
B7: PSR0V01S | C7: =VLOOKUP(B7,'MFG COST SUMMARY'!C:E,3,0) -> P2PVA | D7: 564 | E7: 15.901027 | F7: =E7*D7 -> 8968.1794 | G7: 12.686868 | H7: =+D7*G7 -> 7155.3938 | I7: =H7-F7 -> -1812.7856 | J7: =+H7/F7 -> 0.79786471 | K7: =IFERROR(VLOOKUP($B7,'Tire Weight'!$I:$L,4,0),1) -> 0.99890657 | L7: =G7*K7 -> 12.672996 | M7: =+H7*K7 -> 7147.5699 | N7: =M7-H7 -> -7.8238909
B8: PSR0V03P | C8: =VLOOKUP(B8,'MFG COST SUMMARY'!C:E,3,0) -> BJTVA | D8: 2 | E8: 23.539557 | F8: =E8*D8 -> 47.079114 | G8: 18.906536 | H8: =+D8*G8 -> 37.813073 | I8: =H8-F8 -> -9.2660419 | J8: =+H8/F8 -> 0.80318147 | K8: =IFERROR(VLOOKUP($B8,'Tire Weight'!$I:$L,4,0),1) -> 0.98959061 | L8: =G8*K8 -> 18.709731 | M8: =+H8*K8 -> 37.419461 | N8: =M8-H8 -> -0.39361108
B9: PSR0V03S | C9: =VLOOKUP(B9,'MFG COST SUMMARY'!C:E,3,0) -> VVVVA | D9: 328 | E9: 16.942699 | F9: =E9*D9 -> 5557.2053 | G9: 13.531537 | H9: =+D9*G9 -> 4438.3441 | I9: =H9-F9 -> -1118.8612 | J9: =+H9/F9 -> 0.79866477 | K9: =IFERROR(VLOOKUP($B9,'Tire Weight'!$I:$L,4,0),1) -> 1.0050561 | L9: =G9*K9 -> 13.599954 | M9: =+H9*K9 -> 4460.7848 | N9: =M9-H9 -> 22.440677
B10: PSR0V04P | C10: =VLOOKUP(B10,'MFG COST SUMMARY'!C:E,3,0) -> TZNVA | D10: 1 | E10: 21.690231 | F10: =E10*D10 -> 21.690231 | G10: 17.394403 | H10: =+D10*G10 -> 17.394403 | I10: =H10-F10 -> -4.2958271 | J10: =+H10/F10 -> 0.80194645 | K10: =IFERROR(VLOOKUP($B10,'Tire Weight'!$I:$L,4,0),1) -> 1.0016103 | L10: =G10*K10 -> 17.422414 | M10: =+H10*K10 -> 17.422414 | N10: =M10-H10 -> 0.028010817
B11: PSR0V04S | C11: =VLOOKUP(B11,'MFG COST SUMMARY'!C:E,3,0) -> 3MCVA | D11: 423 | E11: 19.017484 | F11: =E11*D11 -> 8044.3958 | G11: 15.220953 | H11: =+D11*G11 -> 6438.463 | I11: =H11-F11 -> -1605.9328 | J11: =+H11/F11 -> 0.80036627 | K11: =IFERROR(VLOOKUP($B11,'Tire Weight'!$I:$L,4,0),1) -> 1.0052785 | L11: =G11*K11 -> 15.301296 | M11: =+H11*K11 -> 6472.4483 | N11: =M11-H11 -> 33.985324
B12: PSR0V05B | C12: =VLOOKUP(B12,'MFG COST SUMMARY'!C:E,3,0) -> EHSVA | D12: 4421 | E12: 17.370006 | F12: =E12*D12 -> 76792.797 | G12: 13.706193 | H12: =+D12*G12 -> 60595.081 | I12: =H12-F12 -> -16197.716 | J12: =+H12/F12 -> 0.78907246 | K12: =IFERROR(VLOOKUP($B12,'Tire Weight'!$I:$L,4,0),1) -> 1.0010138 | L12: =G12*K12 -> 13.720089 | M12: =+H12*K12 -> 60656.513 | N12: =M12-H12 -> 61.432318
B13: PSR0V05P | C13: =VLOOKUP(B13,'MFG COST SUMMARY'!C:E,3,0) -> JZTVA | D13: 103 | E13: 17.219285 | F13: =E13*D13 -> 1773.5864 | G13: 13.794321 | H13: =+D13*G13 -> 1420.8151 | I13: =H13-F13 -> -352.77127 | J13: =+H13/F13 -> 0.80109722 | K13: =IFERROR(VLOOKUP($B13,'Tire Weight'!$I:$L,4,0),1) -> 0.99869812 | L13: =G13*K13 -> 13.776363 | M13: =+H13*K13 -> 1418.9654 | N13: =M13-H13 -> -1.8497343
B14: PSR0V05S | C14: =VLOOKUP(B14,'MFG COST SUMMARY'!C:E,3,0) -> YYYVA | D14: 913 | E14: 19.332254 | F14: =E14*D14 -> 17650.348 | G14: 15.467715 | H14: =+D14*G14 -> 14122.023 | I14: =H14-F14 -> -3528.3246 | J14: =+H14/F14 -> 0.80009887 | K14: =IFERROR(VLOOKUP($B14,'Tire Weight'!$I:$L,4,0),1) -> 0.9875932 | L14: =G14*K14 -> 15.27581 | M14: =+H14*K14 -> 13946.814 | N14: =M14-H14 -> -175.20917
B15: PSR0V07S | C15: =VLOOKUP(B15,'MFG COST SUMMARY'!C:E,3,0) -> F91VA | D15: 1081 | E15: 24.713618 | F15: =E15*D15 -> 26715.421 | G15: 19.750078 | H15: =+D15*G15 -> 21349.834 | I15: =H15-F15 -> -5365.5869 | J15: =+H15/F15 -> 0.79915769 | K15: =IFERROR(VLOOKUP($B15,'Tire Weight'!$I:$L,4,0),1) -> 1.0053372 | L15: =G15*K15 -> 19.855487 | M15: =+H15*K15 -> 21463.782 | N15: =M15-H15 -> 113.94776
B16: PSR0V11D | C16: =VLOOKUP(B16,'MFG COST SUMMARY'!C:E,3,0) -> VGBVA | D16: 1 | E16: 26.027867 | F16: =E16*D16 -> 26.027867 | G16: 20.514743 | H16: =+D16*G16 -> 20.514743 | I16: =H16-F16 -> -5.5131244 | J16: =+H16/F16 -> 0.78818378 | K16: =IFERROR(VLOOKUP($B16,'Tire Weight'!$I:$L,4,0),1) -> 0.98932835 | L16: =G16*K16 -> 20.295817 | M16: =+H16*K16 -> 20.295817 | N16: =M16-H16 -> -0.21892611
B17: PSR0V11S | C17: =VLOOKUP(B17,'MFG COST SUMMARY'!C:E,3,0) -> YSLVA | D17: 465 | E17: 19.014857 | F17: =E17*D17 -> 8841.9087 | G17: 15.174665 | H17: =+D17*G17 -> 7056.2193 | I17: =H17-F17 -> -1785.6894 | J17: =+H17/F17 -> 0.79804255 | K17: =IFERROR(VLOOKUP($B17,'Tire Weight'!$I:$L,4,0),1) -> 0.99162369 | L17: =G17*K17 -> 15.047558 | M17: =+H17*K17 -> 6997.1142 | N17: =M17-H17 -> -59.105048
... B116: PSR0VH9F | C116: =VLOOKUP(B116,'MFG COST SUMMARY'!C:E,3,0) -> 4HXVA | D116: 3142 | E116: 22.808889 | F116: =E116*D116 -> 71665.528 | G116: 18.199961 | H116: =+D116*G116 -> 57184.277 | I116: =H116-F116 -> -14481.252 | J116: =+H116/F116 -> 0.79793282 | K116: =IFERROR(VLOOKUP($B116,'Tire Weight'!$I:$L,4,0),1) -> 1.0095763 | L116: =G116*K116 -> 18.374249 | M116: =+H116*K116 -> 57731.889 | N116: =M116-H116 -> 547.61266
B117: Total | D117: =SUM(D6:D116) -> 201209 | E117: x | F117: =SUM(F6:F116) -> 3399527.9 | G117: x | H117: =SUM(H6:H116) -> 2728414.3 | I117: =SUM(I6:I116) -> -671113.6 | J117: =+H117/F117 -> 0.80258624 | K117: x | L117: x | M117: =SUM(M6:M116) -> 2731957.5 | N117: =SUM(N6:N116) -> 3543.1565
H118: =H117/F117 -> 0.80258624 | M118: =M117/H117 -> 1.0012986
B119: Check with file DM calculation | D119: 201209 | F119: 3399527.9 | H119: 2728414.3 | M119: =M117/1000 -> 2731.9575
D120: =D117-D119 -> 0 | F120: =F117-F119 -> 0 | H120: =H117-H119 -> 0
B121: Check with sheet MFG Cost Summary | D121: ='MFG COST SUMMARY'!F130 -> 201209
D122: =D117-D121 -> 0

Sheet Rework
A1: Rework tire control
D4: Jan | L4: Feb | T4: Mar | AB4: Apr | AJ4: May | AR4: Jun | AZ4: Jul | BH4: Aug | BP4: Sep | BX4: Oct | CF4: Nov | CN4: Dec
A5: BPC | B5: Open | D5: WH-> Process | F5: Process-> WH | H5: Scrap | J5: Close | L5: WH-> Process | N5: Process-> WH | P5: Scrap | R5: Close | T5: WH-> Process | V5: Process-> WH | X5: Scrap | Z5: Close | AB5: WH-> Process | AD5: Process-> WH | AF5: Scrap | AH5: Close | AJ5: WH-> Process | AL5: Process-> WH | AN5: Scrap | AP5: Close | AR5: WH-> Process | AT5: Process-> WH | AV5: Scrap | AX5: Close | AZ5: WH-> Process | BB5: Process-> WH | BD5: Scrap | BF5: Close | BH5: WH-> Process | BJ5: Process-> WH | BL5: Scrap | BN5: Close | BP5: WH-> Process | BR5: Process-> WH | BT5: Scrap | BV5: Close | BX5: WH-> Process | BZ5: Process-> WH | CB5: Scrap | CD5: Close | CF5: WH-> Process | CH5: Process-> WH | CJ5: Scrap | CL5: Close | CN5: WH-> Process | CP5: Process-> WH | CR5: Scrap | CT5: Close
B6: Q'ty | C6: Am't | D6: Q'ty | E6: Am't | F6: Q'ty | G6: Am't | H6: Q'ty | I6: Am't | J6: Q'ty | K6: Am't | L6: Q'ty | M6: Am't | N6: Q'ty | O6: Am't | P6: Q'ty | Q6: Am't | R6: Q'ty | S6: Am't | T6: Q'ty | U6: Am't | V6: Q'ty | W6: Am't | X6: Q'ty | Y6: Am't | Z6: Q'ty | AA6: Am't | AB6: Q'ty | AC6: Am't | AD6: Q'ty | AE6: Am't | AF6: Q'ty | AG6: Am't | AH6: Q'ty | AI6: Am't | AJ6: Q'ty | AK6: Am't | AL6: Q'ty | AM6: Am't | AN6: Q'ty | AO6: Am't | AP6: Q'ty | AQ6: Am't | AR6: Q'ty | AS6: Am't | AT6: Q'ty | AU6: Am't | AV6: Q'ty | AW6: Am't | AX6: Q'ty | AY6: Am't | AZ6: Q'ty | BA6: Am't | BB6: Q'ty | BC6: Am't | BD6: Q'ty | BE6: Am't | BF6: Q'ty | BG6: Am't | BH6: Q'ty | BI6: Am't | BJ6: Q'ty | BK6: Am't | BL6: Q'ty | BM6: Am't | BN6: Q'ty | BO6: Am't | BP6: Q'ty | BQ6: Am't | BR6: Q'ty | BS6: Am't | BT6: Q'ty | BU6: Am't | BV6: Q'ty | BW6: Am't | BX6: Q'ty | BY6: Am't | BZ6: Q'ty | CA6: Am't | CB6: Q'ty | CC6: Am't | CD6: Q'ty | CE6: Am't | CF6: Q'ty | CG6: Am't | CH6: Q'ty | CI6: Am't | CJ6: Q'ty | CK6: Am't | CL6: Q'ty | CM6: Am't | CN6: Q'ty | CO6: Am't | CP6: Q'ty | CQ6: Am't | CR6: Q'ty | CS6: Am't | CT6: Q'ty | CU6: Am't
A7: PSR0V124 | B7: 13 | C7: 709.93591 | J7: 13 | K7: 709.93591
A8: PSR0V124 | B8: 4 | C8: 175.88 | J8: 4 | K8: 175.88
A9: PSR0V124 | B9: 29 | C9: 1158.3469 | J9: 29 | K9: 1158.3469
A10: PSR0V226 | B10: 4 | C10: 164.585 | J10: 4 | K10: 164.585
A11: PSR0V13D | B11: 1 | C11: 48.987917 | J11: 1 | K11: 48.987917
A12: PSR0V239 | B12: 1 | C12: 31.54 | J12: 1 | K12: 31.54
A13: PSR0V239 | B13: 4 | C13: 126.08 | F13: 4 | G13: 126.08 | J13: 0 | K13: 0
A14: PSR0V178 | B14: 3 | C14: 85.285 | F14: 3 | G14: 85.285 | J14: 0 | K14: 0
A15: PSR0V185 | B15: 5 | C15: 173.45 | F15: 3 | G15: 104.07 | H15: 1 | I15: 34.69 | J15: 1 | K15: 34.69
A16: PSR0V001 | B16: 1 | C16: 20.45 | H16: 1 | I16: 20.45 | J16: 0 | K16: 0
A17: PSR0V012 | B17: 1 | C17: 27.86 | H17: 1 | I17: 27.86 | J17: 0 | K17: 0
A18: PSR0V013 | B18: 1 | C18: 33.4 | H18: 1 | I18: 33.4 | J18: 0 | K18: 0
A19: PSR0V014 | B19: 1 | C19: 38.03 | H19: 1 | I19: 38.03 | J19: 0 | K19: 0
A20: PSR0V004 | B20: 1 | C20: 31.93 | H20: 1 | I20: 31.93 | J20: 0 | K20: 0
A21: PSR0V043 | B21: 1 | C21: 36.61 | H21: 1 | I21: 36.61 | J21: 0 | K21: 0
A22: PSR0V002 | B22: 1 | C22: 23.95 | H22: 1 | I22: 23.95 | J22: 0 | K22: 0
A23: PSR0V231 | B23: 1 | C23: 29.85 | H23: 1 | I23: 29.85 | J23: 0 | K23: 0
A24: PSR0V18D | B24: 1 | C24: 43.43 | J24: 1 | K24: 43.43
A25: PSR0V04P | B25: 1 | C25: 36.04 | J25: 1 | K25: 36.04
A26: PSR0V236 | B26: 1 | C26: 27.49 | F26: 1 | G26: 27.49 | J26: 0 | K26: 0
A27: PSR0V221 | B27: 0 | C27: 0 | D27: 7 | E27: 321.93 | J27: 7 | K27: 321.93
A28: PSR0V29D | B28: 0 | C28: 0 | D28: 1 | E28: 45.46 | J28: 1 | K28: 45.46
A29: PSR0V210 | B29: 0 | C29: 0 | D29: 4 | E29: 210 | H29: 4 | I29: 210 | J29: 0 | K29: 0
J43: =B43+D43-F43-H43 -> 0 | K43: =C43+E43-G43-I43 -> 0 | R43: =J43+L43-N43-P43 -> 0 | S43: =K43+M43-O43-Q43 -> 0 | Z43: =R43+T43-V43-X43 -> 0 | AA43: =S43+U43-W43-Y43 -> 0 | AH43: =Z43+AB43-AD43-AF43 -> 0 | AI43: =AA43+AC43-AE43-AG43 -> 0 | AP43: =AH43+AJ43-AL43-AN43 -> 0 | AQ43: =AI43+AK43-AM43-AO43 -> 0 | AX43: =AP43+AR43-AT43-AV43 -> 0 | AY43: =AQ43+AS43-AU43-AW43 -> 0 | BF43: =AX43+AZ43-BB43-BD43 -> 0 | BG43: =AY43+BA43-BC43-BE43 -> 0 | BN43: =BF43+BH43-BJ43-BL43 -> 0 | BO43: =BG43+BI43-BK43-BM43 -> 0 | BV43: =BN43+BP43-BR43-BT43 -> 0 | BW43: =BO43+BQ43-BS43-BU43 -> 0 | CD43: =BV43+BX43-BZ43-CB43 -> 0 | CE43: =BW43+BY43-CA43-CC43 -> 0 | CL43: =CD43+CF43-CH43-CJ43 -> 0 | CM43: =CE43+CG43-CI43-CK43 -> 0 | CT43: =CL43+CN43-CP43-CR43 -> 0 | CU43: =CM43+CO43-CQ43-CS43 -> 0
A44: Total | B44: =SUBTOTAL(9,B7:B43) -> 75 | C44: =SUBTOTAL(9,C7:C43) -> 3023.1307 | D44: =SUBTOTAL(9,D7:D43) -> 12 | E44: =SUBTOTAL(9,E7:E43) -> 577.39 | F44: =SUBTOTAL(9,F7:F43) -> 11 | G44: =SUBTOTAL(9,G7:G43) -> 342.925 | H44: =SUBTOTAL(9,H7:H43) -> 13 | I44: =SUBTOTAL(9,I7:I43) -> 486.77 | ... CU44: =SUBTOTAL(9,CU7:CU43) -> 0
CH45: =CF44-CH44 -> 0 | CI45: =CG44-CI44 -> 0

Sheet Cured tire BSTVN
A2: Cured tire_Sep.22
A3: Data source: | B3: ..\..\5.Standard & TPL\Seme-products price\2022\Aug 2022\26EZA.xlsx
C5: Number | D5: Brand name | E5: MTP group | F5: BTMV code | G5: M3 | H5: Tire weight | I5: RRW | J5: Cost (USD)/unit | P5: Total cost (USD)
C6: (PCs) | I6: (g) | J6: DM cost | K6: Conversion cost | N6: WS | O6: Factory cost | P6: DM cost | Q6: Conversion cost | T6: WS | U6: Factory cost
K7: Labor | L7: Dep. | M7: Other | Q7: Labor | R7: Dep. | S7: Other
A8: PSR0V244 | B8: 103W 235/60R18 AL01Z | C8: 4 | D8: BRIDGESTONE | E8: PSR2 | F8: 26EZA | H8: 13456 | I8: 6296.1484 | J8: 30.481687 | K8: 5.6200704 | L8: 11.803505 | M8: 7.26149 | N8: 0.8405578 | O8: =SUM(J8:N8) -> 56.00731 | P8: =J8*$C8+0.01 -> 121.93675 | Q8: =K8*$C8 -> 22.480282 | R8: =L8*$C8 -> 47.21402 | S8: =M8*$C8 -> 29.04596 | T8: =N8*$C8 -> 3.3622312 | U8: =+ROUND(SUM(P8:T8),2) -> 224.04

Sheet Budget
A1: 24OB | B1: Production Volume (Pcs) | C1: Production Rubber Tonnage | E1: RBAC2 | F1: Production Volume (Pcs) | G1: Production Rubber Tonnage | I1: RBAC3 | J1: Production Volume (Pcs) | K1: Production Rubber Tonnage | M1: RBAC4 | N1: Production Volume (Pcs) | O1: Production Rubber Tonnage
A2: Jan | B2: 206640 | C2: 795.42376 | E2: Jan | I2: Jan | M2: Jan
A3: Feb | B3: 146880 | C3: 574.30178 | E3: Feb | I3: Feb | M3: Feb
A4: Mar | B4: 223200 | C4: 775.89055 | E4: Mar | I4: Mar | M4: Mar
A5: Apr | B5: 190800 | C5: 775.16231 | E5: Apr | I5: Apr | M5: Apr
A6: May | B6: 198720 | C6: 758.40554 | E6: May | I6: May | M6: May
A7: Jun | B7: 216000 | C7: 855.31156 | E7: Jun | I7: Jun | M7: Jun
A8: Jul | B8: 241800 | C8: 955.5536 | E8: Jul | I8: Jul | M8: Jul
A9: Aug | B9: 240240 | C9: 931.35916 | E9: Aug | I9: Aug | M9: Aug
A10: Sep | B10: 191880 | C10: 753.77863 | E10: Sep | I10: Sep | M10: Sep
A11: Oct | B11: 241800 | C11: 984.66693 | E11: Oct | I11: Oct | M11: Oct
A12: Nov | B12: 234000 | C12: 916.19473 | E12: Nov | I12: Nov | M12: Nov
A13: Dec | B13: 231660 | C13: 902.54425 | E13: Dec | I13: Dec | M13: Dec

Sheet Result

Sheet FACTORY COST
F1: FACTORY COST DATA
F2: Month: | G2: Jan | U2: =MATCH($G$2,$I$5:$T$5,0) -> 1 | AI2: =+AH3/AI3 -> 0.89342208 | AJ2: =AH3/AJ3 -> 0.86500477
F3: YTD: | G3: Jan_Jan-24 | I3: =+I9/(I9+I8) -> 0.032177732 | J3: =+J9/(J9+J8) -> #DIV/0! | K3: =+K9/(K9+K8) -> #DIV/0! | L3: =+L9/(L9+L8) -> #DIV/0! | M3: =+M9/(M9+M8) -> #DIV/0! | N3: =+N9/(N9+N8) -> #DIV/0! | O3: =+O9/(O9+O8) -> #DIV/0! | P3: =+P9/(P9+P8) -> #DIV/0! | ... T3: =+T9/(T9+T8) -> #DIV/0! | AF3: → ▲ | AH3: ='MFG COST SUMMARY'!J134 -> 688.04535 | AI3: 770.12351 | AJ3: {=INDEX($AT$3:$BE$3,ROW()-2,MATCH($G$2,$AT$5:$BE$5,0))} -> 795.42376 | AT3: =INDEX(Budget!$C$2:$C$13,MATCH(AT$5,Budget!$M$2:$M$13,0)) -> 795.42376 | AU3: =INDEX(Budget!$C$2:$C$13,MATCH(AU$5,Budget!$M$2:$M$13,0)) -> 574.30178 | AV3: =INDEX(Budget!$C$2:$C$13,MATCH(AV$5,Budget!$M$2:$M$13,0)) -> 775.89055 | AW3: =INDEX(Budget!$C$2:$C$13,MATCH(AW$5,Budget!$M$2:$M$13,0)) -> 775.16231 | AX3: =INDEX(Budget!$C$2:$C$13,MATCH(AX$5,Budget!$M$2:$M$13,0)) -> 758.40554 | AY3: =INDEX(Budget!$C$2:$C$13,MATCH(AY$5,Budget!$M$2:$M$13,0)) -> 855.31156 | AZ3: =INDEX(Budget!$C$2:$C$13,MATCH(AZ$5,Budget!$M$2:$M$13,0)) -> 955.5536 | BA3: =INDEX(Budget!$C$2:$C$13,MATCH(BA$5,Budget!$M$2:$M$13,0)) -> 931.35916 | ... BE3: =INDEX(Budget!$C$2:$C$13,MATCH(BE$5,Budget!$M$2:$M$13,0)) -> 902.54425
I4: =CurYear & "_ACT" -> 2024_ACT | Z4: vs. previous month | AD4: ="vs. "&$AT$4 -> vs. 24OB | AH4: Gentan-i | AL4: YTD | AR4: ="Remaining "&$AT$4 -> Remaining 24OB | AT4: 24OB | BG4: =$AT$4&"_Accumulated" -> 24OB_Accumulated
A5: MD code | B5: TD code1 | C5: Mfg_Code | D5: Allot key | E5: SAP code | F5: Acc. No | G5: Description | H5: 2023 Dec | I5: Jan | J5: Feb | K5: Mar | L5: Apr | M5: May | N5: Jun | O5: Jul | P5: Aug | Q5: Sep | R5: Oct | S5: Nov | T5: Dec | U5: ="Total cost " &G2&" "& CurYear -> Total cost Jan 2024 | V5: Opn WIP & SOJ | W5: Cls WIP & SOJ | X5: After Adjustment | Z5: % | AA5: Gap | AB5: Reason | AD5: % | AE5: Gap | AF5: Reason | AH5: =G2 -> Jan | AI5: Previous month | AJ5: =$AT$4 -> 24OB | AL5: =G3 -> Jan_Jan-24 | AN5: ="Vs "&$AT$4 -> Vs 24OB | AP5: Reason | AT5: Jan | AU5: Feb | AV5: Mar | AW5: Apr | AX5: May | AY5: Jun | AZ5: Jul | BA5: Aug | BB5: Sep | BC5: Oct | BD5: Nov | BE5: Dec | BG5: Jan_Feb-24 | BH5: Jan_Mar-24 | BI5: Jan_Apr-24 | BJ5: Jan_May-24 | BK5: Jan_Jun-24 | BL5: Jan_Jul-24 | BM5: Jan_Aug-24 | BN5: Jan_Sep-24 | BO5: Jan_Oct-24 | BP5: Jan_Nov-24 | BQ5: Jan_Dec-24
F7: 154 | H7: =+SUBTOTAL(9,H8:H83) -> 6559483 | I7: =+SUBTOTAL(9,I8:I83) -> 6314761.3 | J7: =+SUBTOTAL(9,J8:J83) -> 0 | K7: =+SUBTOTAL(9,K8:K83) -> 0 | L7: =+SUBTOTAL(9,L8:L83) -> 0 | M7: =+SUBTOTAL(9,M8:M83) -> 0 | N7: =+SUBTOTAL(9,N8:N83) -> 0 | O7: =+SUBTOTAL(9,O8:O83) -> 0 | ... T7: =+SUBTOTAL(9,T8:T83) -> 0 | U7: =SUBTOTAL(9,U8:U83) -> 6314761.3 | V7: =+SUBTOTAL(9,V8:V83) -> 0 | W7: =+SUBTOTAL(9,W8:W83) -> 0 | X7: =+SUBTOTAL(9,X8:X83) -> 6314761.3 | Z7: {=IFERROR(U7/OFFSET($H7:$U7,,MATCH($G$2,$H$5:$U$5,0)-2,,1),"-")} -> 0.96269192 | AA7: =SUBTOTAL(9,AA8:AA83) -> -244721.72 | AD7: {=IFERROR(U7/OFFSET($AT7,,MATCH($G$2,$AT$5:$BE$5,0)-1,,),"-")} -> 0.89681435 | AE7: =SUBTOTAL(9,AE8:AE83) -> -726563.67 | AL7: ="Act "&LEFT(AL5,7) -> Act Jan_Jan | AM7: =$AT$4&" "&LEFT(AL5,7) -> 24OB Jan_Jan | AN7: Var | AO7: % | AR7: =+SUBTOTAL(9,AR8:AR83) -> 84683860 | AT7: =+SUBTOTAL(9,AT8:AT83) -> 7041324.9 | AU7: =+SUBTOTAL(9,AU8:AU83) -> 5877425.3 | AV7: =+SUBTOTAL(9,AV8:AV83) -> 7213914.5 | AW7: =+SUBTOTAL(9,AW8:AW83) -> 7420362.1 | AX7: =+SUBTOTAL(9,AX8:AX83) -> 7288949.7 | AY7: =+SUBTOTAL(9,AY8:AY83) -> 7857651.5 | AZ7: =+SUBTOTAL(9,AZ8:AZ83) -> 8202511.5 | BA7: =+SUBTOTAL(9,BA8:BA83) -> 8137536.8 | ... BE7: =+SUBTOTAL(9,BE8:BE83) -> 8473594.7 | BG7: =+SUBTOTAL(9,BG8:BG83) -> 12918750 | BH7: =+SUBTOTAL(9,BH8:BH83) -> 20132665 | BI7: =+SUBTOTAL(9,BI8:BI83) -> 27553027 | BJ7: =+SUBTOTAL(9,BJ8:BJ83) -> 34841977 | BK7: =+SUBTOTAL(9,BK8:BK83) -> 42699628 | BL7: =+SUBTOTAL(9,BL8:BL83) -> 50902140 | BM7: =+SUBTOTAL(9,BM8:BM83) -> 59039676 | BN7: =+SUBTOTAL(9,BN8:BN83) -> 66222385 | ... BQ7: =+SUBTOTAL(9,BQ8:BQ83) -> 90998622 | BS7: Setting | BW7: 2024
A8: Direct Material cost | B8: Direct Material cost | C8: Direct Material | D8: DM | E8: 600000 | F8: 62100100 | G8: Direct material for mass production | H8: 2496210.4 | I8: =SUMIFS(INDIRECT(I$5&"!N:N"),INDIRECT(I$5&"!L:L"),$E8,INDIRECT(I$5&"!K:K"),50)-SUMIFS(INDIRECT(I$5&"!N:N"),INDIRECT(I$5&"!L:L"),$E8,INDIRECT(I$5&"!K:K"),40) -> 2981091.5 | J8: =SUMIFS(INDIRECT(J$5&"!N:N"),INDIRECT(J$5&"!L:L"),$E8,INDIRECT(J$5&"!K:K"),50)-SUMIFS(INDIRECT(J$5&"!N:N"),INDIRECT(J$5&"!L:L"),$E8,INDIRECT(J$5&"!K:K"),40) -> 0 | K8: =SUMIFS(INDIRECT(K$5&"!N:N"),INDIRECT(K$5&"!L:L"),$E8,INDIRECT(K$5&"!K:K"),50)-SUMIFS(INDIRECT(K$5&"!N:N"),INDIRECT(K$5&"!L:L"),$E8,INDIRECT(K$5&"!K:K"),40) -> 0 | L8: =SUMIFS(INDIRECT(L$5&"!N:N"),INDIRECT(L$5&"!L:L"),$E8,INDIRECT(L$5&"!K:K"),50)-SUMIFS(INDIRECT(L$5&"!N:N"),INDIRECT(L$5&"!L:L"),$E8,INDIRECT(L$5&"!K:K"),40) -> 0 | M8: =SUMIFS(INDIRECT(M$5&"!N:N"),INDIRECT(M$5&"!L:L"),$E8,INDIRECT(M$5&"!K:K"),50)-SUMIFS(INDIRECT(M$5&"!N:N"),INDIRECT(M$5&"!L:L"),$E8,INDIRECT(M$5&"!K:K"),40) -> 0 | N8: =SUMIFS(INDIRECT(N$5&"!N:N"),INDIRECT(N$5&"!L:L"),$E8,INDIRECT(N$5&"!K:K"),50)-SUMIFS(INDIRECT(N$5&"!N:N"),INDIRECT(N$5&"!L:L"),$E8,INDIRECT(N$5&"!K:K"),40) -> 0 | O8: =SUMIFS(INDIRECT(O$5&"!N:N"),INDIRECT(O$5&"!L:L"),$E8,INDIRECT(O$5&"!K:K"),50)-SUMIFS(INDIRECT(O$5&"!N:N"),INDIRECT(O$5&"!L:L"),$E8,INDIRECT(O$5&"!K:K"),40) -> 0 | P8: =SUMIFS(INDIRECT(P$5&"!N:N"),INDIRECT(P$5&"!L:L"),$E8,INDIRECT(P$5&"!K:K"),50)-SUMIFS(INDIRECT(P$5&"!N:N"),INDIRECT(P$5&"!L:L"),$E8,INDIRECT(P$5&"!K:K"),40) -> 0 | ... T8: =SUMIFS(INDIRECT(T$5&"!N:N"),INDIRECT(T$5&"!L:L"),$E8,INDIRECT(T$5&"!K:K"),50)-SUMIFS(INDIRECT(T$5&"!N:N"),INDIRECT(T$5&"!L:L"),$E8,INDIRECT(T$5&"!K:K"),40) -> 0 | U8: {=INDEX($I8:$T8,$U$2)} -> 2981091.5 | X8: =U8+V8-W8 -> 2981091.5 | Z8: {=IFERROR(U8/OFFSET($H8,,MATCH($G$2,$H$5:$U$5,0)-2,,),"-")} -> 1.1942469 | AA8: {=U8-OFFSET($H8,,MATCH($G$2,$H$5:$U$5,0)-2,,)} -> 484881.11 | AD8: {=IFERROR(U8/OFFSET($AT8,,MATCH($G$2,$AT$5:$BE$5,0)-1,,),"-")} -> 0.88715729 | AE8: {=U8-OFFSET($AT8,,MATCH($G$2,$AT$5:$BE$5,0)-1,,)} -> -379182.41 | AH8: {=IFERROR(INDEX($I8:$T8,$U$2)/$AH$3,0)} -> 4332.6963 | AI8: =H8/PrvMonthProductionRRT -> 3241.3118 | AJ8: {=IFERROR(OFFSET($AT8,,MATCH($G$2,$AT$5:$BE$5,0)-1,,)/$AJ$3,"")} -> 4224.5079 | AL8: =SUM(I8:T8) -> 2981091.5 | AM8: {=INDEX($BG$8:$BQ$83,ROW()-7,MATCH($G$3,$BG$5:$BQ$5,0))} -> #N/A | AN8: =AL8-AM8 -> #N/A | AO8: =IFERROR(AL8/AM8,"") | AR8: =BQ8-AL8 -> 39616124 | AT8: 3360274 | AU8: 2470065.1 | AV8: 3397741.4 | AW8: 3331787.6 | AX8: 3249758.5 | AY8: 3678343.1 | AZ8: 4076030.5 | BA8: 3955084 | BB8: 3199182.3 | BC8: 4172372.4 | BD8: 3877777.5 | BE8: 3828798.7 | BG8: =SUM(AT8:AU8) -> 5830339 | BH8: =SUM(AT8:AV8) -> 9228080.4 | BI8: =SUM(AT8:AW8) -> 12559868 | BJ8: =SUM(AT8:AX8) -> 15809627 | BK8: =SUM(AT8:AY8) -> 19487970 | BL8: =SUM(AT8:AZ8) -> 23564000 | BM8: =SUM(AT8:BA8) -> 27519084 | BN8: =SUM(AT8:BB8) -> 30718266 | BO8: =SUM(AT8:BC8) -> 34890639 | BP8: =SUM(AT8:BD8) -> 38768416 | BQ8: =SUM(AT8:BE8) -> 42597215 | BS8: 1 | BT8: Jan | BU8: 1 | BW8: =$BT$8&"_"&BT8&"-"&RIGHT($BW$7,2) -> Jan_Jan-24
A9: Scrap Cost (g) | B9: Scrap Cost | C9: Waste | D9: Waste | E9: 691200 | F9: 62100200 | G9: Direct material loss (W&S) | H9: 107427.44 | I9: =SUMIFS(INDIRECT(I$5&"!N:N"),INDIRECT(I$5&"!L:L"),$E9,INDIRECT(I$5&"!K:K"),50)-SUMIFS(INDIRECT(I$5&"!N:N"),INDIRECT(I$5&"!L:L"),$E9,INDIRECT(I$5&"!K:K"),40) -> 99114.03 | J9: =SUMIFS(INDIRECT(J$5&"!N:N"),INDIRECT(J$5&"!L:L"),$E9,INDIRECT(J$5&"!K:K"),50)-SUMIFS(INDIRECT(J$5&"!N:N"),INDIRECT(J$5&"!L:L"),$E9,INDIRECT(J$5&"!K:K"),40) -> 0 | K9: =SUMIFS(INDIRECT(K$5&"!N:N"),INDIRECT(K$5&"!L:L"),$E9,INDIRECT(K$5&"!K:K"),50)-SUMIFS(INDIRECT(K$5&"!N:N"),INDIRECT(K$5&"!L:L"),$E9,INDIRECT(K$5&"!K:K"),40) -> 0 | L9: =SUMIFS(INDIRECT(L$5&"!N:N"),INDIRECT(L$5&"!L:L"),$E9,INDIRECT(L$5&"!K:K"),50)-SUMIFS(INDIRECT(L$5&"!N:N"),INDIRECT(L$5&"!L:L"),$E9,INDIRECT(L$5&"!K:K"),40) -> 0 | M9: =SUMIFS(INDIRECT(M$5&"!N:N"),INDIRECT(M$5&"!L:L"),$E9,INDIRECT(M$5&"!K:K"),50)-SUMIFS(INDIRECT(M$5&"!N:N"),INDIRECT(M$5&"!L:L"),$E9,INDIRECT(M$5&"!K:K"),40) -> 0 | N9: =SUMIFS(INDIRECT(N$5&"!N:N"),INDIRECT(N$5&"!L:L"),$E9,INDIRECT(N$5&"!K:K"),50)-SUMIFS(INDIRECT(N$5&"!N:N"),INDIRECT(N$5&"!L:L"),$E9,INDIRECT(N$5&"!K:K"),40) -> 0 | O9: =SUMIFS(INDIRECT(O$5&"!N:N"),INDIRECT(O$5&"!L:L"),$E9,INDIRECT(O$5&"!K:K"),50)-SUMIFS(INDIRECT(O$5&"!N:N"),INDIRECT(O$5&"!L:L"),$E9,INDIRECT(O$5&"!K:K"),40) -> 0 | P9: =SUMIFS(INDIRECT(P$5&"!N:N"),INDIRECT(P$5&"!L:L"),$E9,INDIRECT(P$5&"!K:K"),50)-SUMIFS(INDIRECT(P$5&"!N:N"),INDIRECT(P$5&"!L:L"),$E9,INDIRECT(P$5&"!K:K"),40) -> 0 | ... T9: =SUMIFS(INDIRECT(T$5&"!N:N"),INDIRECT(T$5&"!L:L"),$E9,INDIRECT(T$5&"!K:K"),50)-SUMIFS(INDIRECT(T$5&"!N:N"),INDIRECT(T$5&"!L:L"),$E9,INDIRECT(T$5&"!K:K"),40) -> 0 | U9: {=INDEX($I9:$T9,$U$2)} -> 99114.03 | X9: =U9+V9-W9 -> 99114.03 | Z9: {=IFERROR(U9/OFFSET($H9,,MATCH($G$2,$H$5:$U$5,0)-2,,),"-")} -> 0.92261372 | AA9: {=U9-OFFSET($H9,,MATCH($G$2,$H$5:$U$5,0)-2,,)} -> -8313.41 | AD9: {=IFERROR(U9/OFFSET($AT9,,MATCH($G$2,$AT$5:$BE$5,0)-1,,),"-")} -> 0.98063495 | AE9: {=U9-OFFSET($AT9,,MATCH($G$2,$AT$5:$BE$5,0)-1,,)} -> -1957.2508 | AH9: {=IFERROR(INDEX($I9:$T9,$U$2)/$AH$3,0)} -> 144.0516 | AI9: =H9/PrvMonthProductionRRT -> 139.49378 | AJ9: {=IFERROR(OFFSET($AT9,,MATCH($G$2,$AT$5:$BE$5,0)-1,,)/$AJ$3,"")} -> 127.06596 | AL9: =SUM(I9:T9) -> 99114.03 | AM9: {=INDEX($BG$8:$BQ$83,ROW()-7,MATCH($G$3,$BG$5:$BQ$5,0))} -> #N/A | AN9: =AL9-AM9 -> #N/A | AO9: =IFERROR(AL9/AM9,"") | AR9: =BQ9-AL9 -> 1184276.5 | AT9: 101071.28 | AU9: 73771.253 | AV9: 101477.34 | AW9: 101275.36 | AX9: 99472.151 | AY9: 112200.08 | AZ9: 123465.17 | BA9: 119381.85 | BB9: 96565.408 | BC9: 123727.68 | BD9: 116225.49 | BE9: 114757.49 | BG9: =SUM(AT9:AU9) -> 174842.53 | BH9: =SUM(AT9:AV9) -> 276319.88 | BI9: =SUM(AT9:AW9) -> 377595.24 | BJ9: =SUM(AT9:AX9) -> 477067.39 | BK9: =SUM(AT9:AY9) -> 589267.46 | BL9: =SUM(AT9:AZ9) -> 712732.64 | BM9: =SUM(AT9:BA9) -> 832114.49 | BN9: =SUM(AT9:BB9) -> 928679.89 | BO9: =SUM(AT9:BC9) -> 1052407.6 | BP9: =SUM(AT9:BD9) -> 1168633.1 | BQ9: =SUM(AT9:BE9) -> 1283390.5 | BS9: 2 | BT9: Feb | BU9: 2 | BW9: =$BT$8&"_"&BT9&"-"&RIGHT($BW$7,2) -> Jan_Feb-24
A10: Labor | B10: Labor | C10: Labor_Direct | D10: CC | E10: 621001 | F10: 62200101 | G10: Remuneration_Local_Direct | H10: 417488.12 | I10: =SUMIFS(INDIRECT(I$5&"!N:N"),INDIRECT(I$5&"!L:L"),$E10,INDIRECT(I$5&"!K:K"),50)-SUMIFS(INDIRECT(I$5&"!N:N"),INDIRECT(I$5&"!L:L"),$E10,INDIRECT(I$5&"!K:K"),40) -> 383727.88 | J10: =SUMIFS(INDIRECT(J$5&"!N:N"),INDIRECT(J$5&"!L:L"),$E10,INDIRECT(J$5&"!K:K"),50)-SUMIFS(INDIRECT(J$5&"!N:N"),INDIRECT(J$5&"!L:L"),$E10,INDIRECT(J$5&"!K:K"),40) -> 0 | K10: =SUMIFS(INDIRECT(K$5&"!N:N"),INDIRECT(K$5&"!L:L"),$E10,INDIRECT(K$5&"!K:K"),50)-SUMIFS(INDIRECT(K$5&"!N:N"),INDIRECT(K$5&"!L:L"),$E10,INDIRECT(K$5&"!K:K"),40) -> 0 | L10: =SUMIFS(INDIRECT(L$5&"!N:N"),INDIRECT(L$5&"!L:L"),$E10,INDIRECT(L$5&"!K:K"),50)-SUMIFS(INDIRECT(L$5&"!N:N"),INDIRECT(L$5&"!L:L"),$E10,INDIRECT(L$5&"!K:K"),40) -> 0 | M10: =SUMIFS(INDIRECT(M$5&"!N:N"),INDIRECT(M$5&"!L:L"),$E10,INDIRECT(M$5&"!K:K"),50)-SUMIFS(INDIRECT(M$5&"!N:N"),INDIRECT(M$5&"!L:L"),$E10,INDIRECT(M$5&"!K:K"),40) -> 0 | N10: =SUMIFS(INDIRECT(N$5&"!N:N"),INDIRECT(N$5&"!L:L"),$E10,INDIRECT(N$5&"!K:K"),50)-SUMIFS(INDIRECT(N$5&"!N:N"),INDIRECT(N$5&"!L:L"),$E10,INDIRECT(N$5&"!K:K"),40) -> 0 | O10: =SUMIFS(INDIRECT(O$5&"!N:N"),INDIRECT(O$5&"!L:L"),$E10,INDIRECT(O$5&"!K:K"),50)-SUMIFS(INDIRECT(O$5&"!N:N"),INDIRECT(O$5&"!L:L"),$E10,INDIRECT(O$5&"!K:K"),40) -> 0 | P10: =SUMIFS(INDIRECT(P$5&"!N:N"),INDIRECT(P$5&"!L:L"),$E10,INDIRECT(P$5&"!K:K"),50)-SUMIFS(INDIRECT(P$5&"!N:N"),INDIRECT(P$5&"!L:L"),$E10,INDIRECT(P$5&"!K:K"),40) -> 0 | ... T10: =SUMIFS(INDIRECT(T$5&"!N:N"),INDIRECT(T$5&"!L:L"),$E10,INDIRECT(T$5&"!K:K"),50)-SUMIFS(INDIRECT(T$5&"!N:N"),INDIRECT(T$5&"!L:L"),$E10,INDIRECT(T$5&"!K:K"),40) -> 0 | U10: {=INDEX($I10:$T10,$U$2)} -> 383727.88 | X10: =U10+V10-W10 -> 383727.88 | Z10: {=IFERROR(U10/OFFSET($H10,,MATCH($G$2,$H$5:$U$5,0)-2,,),"-")} -> 0.91913485 | AA10: {=U10-OFFSET($H10,,MATCH($G$2,$H$5:$U$5,0)-2,,)} -> -33760.24 | AD10: {=IFERROR(U10/OFFSET($AT10,,MATCH($G$2,$AT$5:$BE$5,0)-1,,),"-")} -> 1.0027829 | AE10: {=U10-OFFSET($AT10,,MATCH($G$2,$AT$5:$BE$5,0)-1,,)} -> 1064.8952 | AL10: =SUM(I10:T10) -> 383727.88 | AM10: {=INDEX($BG$8:$BQ$83,ROW()-7,MATCH($G$3,$BG$5:$BQ$5,0))} -> #N/A | AN10: =AL10-AM10 -> #N/A | AO10: =IFERROR(AL10/AM10,"") | AR10: =BQ10-AL10 -> 4378479.9 | AT10: 382662.98 | AU10: 387894.52 | AV10: 379786.3 | AW10: 384176.04 | AX10: 382458.02 | AY10: 385713.95 | AZ10: 397256.79 | BA10: 414896.08 | BB10: 411432.73 | BC10: 415827.54 | BD10: 412023.87 | BE10: 408078.99 | BG10: =SUM(AT10:AU10) -> 770557.5 | BH10: =SUM(AT10:AV10) -> 1150343.8 | BI10: =SUM(AT10:AW10) -> 1534519.8 | BJ10: =SUM(AT10:AX10) -> 1916977.9 | BK10: =SUM(AT10:AY10) -> 2302691.8 | BL10: =SUM(AT10:AZ10) -> 2699948.6 | BM10: =SUM(AT10:BA10) -> 3114844.7 | BN10: =SUM(AT10:BB10) -> 3526277.4 | BO10: =SUM(AT10:BC10) -> 3942105 | BP10: =SUM(AT10:BD10) -> 4354128.8 | BQ10: =SUM(AT10:BE10) -> 4762207.8 | BS10: 3 | BT10: Mar | BU10: 3 | BW10: =$BT$8&"_"&BT10&"-"&RIGHT($BW$7,2) -> Jan_Mar-24
A11: Labor | B11: Labor | C11: Labor_Direct | D11: CC | E11: 621003 | F11: 62200103 | G11: Remuneration_Local_Other_Direct | H11: 0 | I11: =SUMIFS(INDIRECT(I$5&"!N:N"),INDIRECT(I$5&"!L:L"),$E11,INDIRECT(I$5&"!K:K"),50)-SUMIFS(INDIRECT(I$5&"!N:N"),INDIRECT(I$5&"!L:L"),$E11,INDIRECT(I$5&"!K:K"),40) -> 0 | J11: =SUMIFS(INDIRECT(J$5&"!N:N"),INDIRECT(J$5&"!L:L"),$E11,INDIRECT(J$5&"!K:K"),50)-SUMIFS(INDIRECT(J$5&"!N:N"),INDIRECT(J$5&"!L:L"),$E11,INDIRECT(J$5&"!K:K"),40) -> 0 | K11: =SUMIFS(INDIRECT(K$5&"!N:N"),INDIRECT(K$5&"!L:L"),$E11,INDIRECT(K$5&"!K:K"),50)-SUMIFS(INDIRECT(K$5&"!N:N"),INDIRECT(K$5&"!L:L"),$E11,INDIRECT(K$5&"!K:K"),40) -> 0 | L11: =SUMIFS(INDIRECT(L$5&"!N:N"),INDIRECT(L$5&"!L:L"),$E11,INDIRECT(L$5&"!K:K"),50)-SUMIFS(INDIRECT(L$5&"!N:N"),INDIRECT(L$5&"!L:L"),$E11,INDIRECT(L$5&"!K:K"),40) -> 0 | M11: =SUMIFS(INDIRECT(M$5&"!N:N"),INDIRECT(M$5&"!L:L"),$E11,INDIRECT(M$5&"!K:K"),50)-SUMIFS(INDIRECT(M$5&"!N:N"),INDIRECT(M$5&"!L:L"),$E11,INDIRECT(M$5&"!K:K"),40) -> 0 | N11: =SUMIFS(INDIRECT(N$5&"!N:N"),INDIRECT(N$5&"!L:L"),$E11,INDIRECT(N$5&"!K:K"),50)-SUMIFS(INDIRECT(N$5&"!N:N"),INDIRECT(N$5&"!L:L"),$E11,INDIRECT(N$5&"!K:K"),40) -> 0 | O11: =SUMIFS(INDIRECT(O$5&"!N:N"),INDIRECT(O$5&"!L:L"),$E11,INDIRECT(O$5&"!K:K"),50)-SUMIFS(INDIRECT(O$5&"!N:N"),INDIRECT(O$5&"!L:L"),$E11,INDIRECT(O$5&"!K:K"),40) -> 0 | P11: =SUMIFS(INDIRECT(P$5&"!N:N"),INDIRECT(P$5&"!L:L"),$E11,INDIRECT(P$5&"!K:K"),50)-SUMIFS(INDIRECT(P$5&"!N:N"),INDIRECT(P$5&"!L:L"),$E11,INDIRECT(P$5&"!K:K"),40) -> 0 | ... T11: =SUMIFS(INDIRECT(T$5&"!N:N"),INDIRECT(T$5&"!L:L"),$E11,INDIRECT(T$5&"!K:K"),50)-SUMIFS(INDIRECT(T$5&"!N:N"),INDIRECT(T$5&"!L:L"),$E11,INDIRECT(T$5&"!K:K"),40) -> 0 | U11: {=INDEX($I11:$T11,$U$2)} -> 0 | X11: =U11+V11-W11 -> 0 | Z11: {=IFERROR(U11/OFFSET($H11,,MATCH($G$2,$H$5:$U$5,0)-2,,),"-")} -> - | AA11: {=U11-OFFSET($H11,,MATCH($G$2,$H$5:$U$5,0)-2,,)} -> 0 | AD11: {=IFERROR(U11/OFFSET($AT11,,MATCH($G$2,$AT$5:$BE$5,0)-1,,),"-")} -> - | AE11: {=U11-OFFSET($AT11,,MATCH($G$2,$AT$5:$BE$5,0)-1,,)} -> 0 | AL11: =SUM(I11:T11) -> 0 | AM11: {=INDEX($BG$8:$BQ$83,ROW()-7,MATCH($G$3,$BG$5:$BQ$5,0))} -> #N/A | AN11: =AL11-AM11 -> #N/A | AO11: =IFERROR(AL11/AM11,"") | AR11: =BQ11-AL11 -> 0 | AT11: 0 | AU11: 0 | AV11: 0 | AW11: 0 | AX11: 0 | AY11: 0 | AZ11: 0 | BA11: 0 | BB11: 0 | BC11: 0 | BD11: 0 | BE11: 0 | BG11: =SUM(AT11:AU11) -> 0 | BH11: =SUM(AT11:AV11) -> 0 | BI11: =SUM(AT11:AW11) -> 0 | BJ11: =SUM(AT11:AX11) -> 0 | BK11: =SUM(AT11:AY11) -> 0 | BL11: =SUM(AT11:AZ11) -> 0 | BM11: =SUM(AT11:BA11) -> 0 | BN11: =SUM(AT11:BB11) -> 0 | BO11: =SUM(AT11:BC11) -> 0 | BP11: =SUM(AT11:BD11) -> 0 | BQ11: =SUM(AT11:BE11) -> 0 | BS11: 4 | BT11: Apr | BU11: 4 | BW11: =$BT$8&"_"&BT11&"-"&RIGHT($BW$7,2) -> Jan_Apr-24
A12: Labor | B12: Labor | C12: Labor_Direct | D12: CC | E12: 622001 | F12: 62200401 | G12: Bonus_Local_Direct | H12: 32368.93 | I12: =SUMIFS(INDIRECT(I$5&"!N:N"),INDIRECT(I$5&"!L:L"),$E12,INDIRECT(I$5&"!K:K"),50)-SUMIFS(INDIRECT(I$5&"!N:N"),INDIRECT(I$5&"!L:L"),$E12,INDIRECT(I$5&"!K:K"),40) -> 96390.89 | J12: =SUMIFS(INDIRECT(J$5&"!N:N"),INDIRECT(J$5&"!L:L"),$E12,INDIRECT(J$5&"!K:K"),50)-SUMIFS(INDIRECT(J$5&"!N:N"),INDIRECT(J$5&"!L:L"),$E12,INDIRECT(J$5&"!K:K"),40) -> 0 | K12: =SUMIFS(INDIRECT(K$5&"!N:N"),INDIRECT(K$5&"!L:L"),$E12,INDIRECT(K$5&"!K:K"),50)-SUMIFS(INDIRECT(K$5&"!N:N"),INDIRECT(K$5&"!L:L"),$E12,INDIRECT(K$5&"!K:K"),40) -> 0 | L12: =SUMIFS(INDIRECT(L$5&"!N:N"),INDIRECT(L$5&"!L:L"),$E12,INDIRECT(L$5&"!K:K"),50)-SUMIFS(INDIRECT(L$5&"!N:N"),INDIRECT(L$5&"!L:L"),$E12,INDIRECT(L$5&"!K:K"),40) -> 0 | M12: =SUMIFS(INDIRECT(M$5&"!N:N"),INDIRECT(M$5&"!L:L"),$E12,INDIRECT(M$5&"!K:K"),50)-SUMIFS(INDIRECT(M$5&"!N:N"),INDIRECT(M$5&"!L:L"),$E12,INDIRECT(M$5&"!K:K"),40) -> 0 | N12: =SUMIFS(INDIRECT(N$5&"!N:N"),INDIRECT(N$5&"!L:L"),$E12,INDIRECT(N$5&"!K:K"),50)-SUMIFS(INDIRECT(N$5&"!N:N"),INDIRECT(N$5&"!L:L"),$E12,INDIRECT(N$5&"!K:K"),40) -> 0 | O12: =SUMIFS(INDIRECT(O$5&"!N:N"),INDIRECT(O$5&"!L:L"),$E12,INDIRECT(O$5&"!K:K"),50)-SUMIFS(INDIRECT(O$5&"!N:N"),INDIRECT(O$5&"!L:L"),$E12,INDIRECT(O$5&"!K:K"),40) -> 0 | P12: =SUMIFS(INDIRECT(P$5&"!N:N"),INDIRECT(P$5&"!L:L"),$E12,INDIRECT(P$5&"!K:K"),50)-SUMIFS(INDIRECT(P$5&"!N:N"),INDIRECT(P$5&"!L:L"),$E12,INDIRECT(P$5&"!K:K"),40) -> 0 | ... T12: =SUMIFS(INDIRECT(T$5&"!N:N"),INDIRECT(T$5&"!L:L"),$E12,INDIRECT(T$5&"!K:K"),50)-SUMIFS(INDIRECT(T$5&"!N:N"),INDIRECT(T$5&"!L:L"),$E12,INDIRECT(T$5&"!K:K"),40) -> 0 | U12: {=INDEX($I12:$T12,$U$2)} -> 96390.89 | X12: =U12+V12-W12 -> 96390.89 | Z12: {=IFERROR(U12/OFFSET($H12,,MATCH($G$2,$H$5:$U$5,0)-2,,),"-")} -> 2.9778831 | AA12: {=U12-OFFSET($H12,,MATCH($G$2,$H$5:$U$5,0)-2,,)} -> 64021.96 | AD12: {=IFERROR(U12/OFFSET($AT12,,MATCH($G$2,$AT$5:$BE$5,0)-1,,),"-")} -> 0.85858737 | AE12: {=U12-OFFSET($AT12,,MATCH($G$2,$AT$5:$BE$5,0)-1,,)} -> -15875.948 | AL12: =SUM(I12:T12) -> 96390.89 | AM12: {=INDEX($BG$8:$BQ$83,ROW()-7,MATCH($G$3,$BG$5:$BQ$5,0))} -> #N/A | AN12: =AL12-AM12 -> #N/A | AO12: =IFERROR(AL12/AM12,"") | AR12: =BQ12-AL12 -> 1272346.5 | AT12: 112266.84 | AU12: 110673.65 | AV12: 107208.54 | AW12: 126366.55 | AX12: 103432.27 | AY12: 106005.68 | AZ12: 119188.02 | BA12: 101699.71 | BB12: 102854.75 | BC12: 123484.07 | BD12: 124942.47 | BE12: 130614.86 | BG12: =SUM(AT12:AU12) -> 222940.49 | BH12: =SUM(AT12:AV12) -> 330149.03 | BI12: =SUM(AT12:AW12) -> 456515.58 | BJ12: =SUM(AT12:AX12) -> 559947.85 | BK12: =SUM(AT12:AY12) -> 665953.53 | BL12: =SUM(AT12:AZ12) -> 785141.54 | BM12: =SUM(AT12:BA12) -> 886841.25 | BN12: =SUM(AT12:BB12) -> 989696 | BO12: =SUM(AT12:BC12) -> 1113180.1 | BP12: =SUM(AT12:BD12) -> 1238122.5 | BQ12: =SUM(AT12:BE12) -> 1368737.4 | BS12: 5 | BT12: May | BU12: 5 | BW12: =$BT$8&"_"&BT12&"-"&RIGHT($BW$7,2) -> Jan_May-24
A13: Labor | B13: Labor | C13: Labor_Direct | D13: CC | E13: 624010 | F13: 62202000 | G13: LU fee_Local_Direct | H13: 5787.46 | I13: =SUMIFS(INDIRECT(I$5&"!N:N"),INDIRECT(I$5&"!L:L"),$E13,INDIRECT(I$5&"!K:K"),50)-SUMIFS(INDIRECT(I$5&"!N:N"),INDIRECT(I$5&"!L:L"),$E13,INDIRECT(I$5&"!K:K"),40) -> 5738.88 | J13: =SUMIFS(INDIRECT(J$5&"!N:N"),INDIRECT(J$5&"!L:L"),$E13,INDIRECT(J$5&"!K:K"),50)-SUMIFS(INDIRECT(J$5&"!N:N"),INDIRECT(J$5&"!L:L"),$E13,INDIRECT(J$5&"!K:K"),40) -> 0 | K13: =SUMIFS(INDIRECT(K$5&"!N:N"),INDIRECT(K$5&"!L:L"),$E13,INDIRECT(K$5&"!K:K"),50)-SUMIFS(INDIRECT(K$5&"!N:N"),INDIRECT(K$5&"!L:L"),$E13,INDIRECT(K$5&"!K:K"),40) -> 0 | L13: =SUMIFS(INDIRECT(L$5&"!N:N"),INDIRECT(L$5&"!L:L"),$E13,INDIRECT(L$5&"!K:K"),50)-SUMIFS(INDIRECT(L$5&"!N:N"),INDIRECT(L$5&"!L:L"),$E13,INDIRECT(L$5&"!K:K"),40) -> 0 | M13: =SUMIFS(INDIRECT(M$5&"!N:N"),INDIRECT(M$5&"!L:L"),$E13,INDIRECT(M$5&"!K:K"),50)-SUMIFS(INDIRECT(M$5&"!N:N"),INDIRECT(M$5&"!L:L"),$E13,INDIRECT(M$5&"!K:K"),40) -> 0 | N13: =SUMIFS(INDIRECT(N$5&"!N:N"),INDIRECT(N$5&"!L:L"),$E13,INDIRECT(N$5&"!K:K"),50)-SUMIFS(INDIRECT(N$5&"!N:N"),INDIRECT(N$5&"!L:L"),$E13,INDIRECT(N$5&"!K:K"),40) -> 0 | O13: =SUMIFS(INDIRECT(O$5&"!N:N"),INDIRECT(O$5&"!L:L"),$E13,INDIRECT(O$5&"!K:K"),50)-SUMIFS(INDIRECT(O$5&"!N:N"),INDIRECT(O$5&"!L:L"),$E13,INDIRECT(O$5&"!K:K"),40) -> 0 | P13: =SUMIFS(INDIRECT(P$5&"!N:N"),INDIRECT(P$5&"!L:L"),$E13,INDIRECT(P$5&"!K:K"),50)-SUMIFS(INDIRECT(P$5&"!N:N"),INDIRECT(P$5&"!L:L"),$E13,INDIRECT(P$5&"!K:K"),40) -> 0 | ... T13: =SUMIFS(INDIRECT(T$5&"!N:N"),INDIRECT(T$5&"!L:L"),$E13,INDIRECT(T$5&"!K:K"),50)-SUMIFS(INDIRECT(T$5&"!N:N"),INDIRECT(T$5&"!L:L"),$E13,INDIRECT(T$5&"!K:K"),40) -> 0 | U13: {=INDEX($I13:$T13,$U$2)} -> 5738.88 | X13: =U13+V13-W13 -> 5738.88 | Z13: {=IFERROR(U13/OFFSET($H13,,MATCH($G$2,$H$5:$U$5,0)-2,,),"-")} -> 0.99160599 | AA13: {=U13-OFFSET($H13,,MATCH($G$2,$H$5:$U$5,0)-2,,)} -> -48.58 | AD13: {=IFERROR(U13/OFFSET($AT13,,MATCH($G$2,$AT$5:$BE$5,0)-1,,),"-")} -> 1.0441347 | AE13: {=U13-OFFSET($AT13,,MATCH($G$2,$AT$5:$BE$5,0)-1,,)} -> 242.57753 | AL13: =SUM(I13:T13) -> 5738.88 | AM13: {=INDEX($BG$8:$BQ$83,ROW()-7,MATCH($G$3,$BG$5:$BQ$5,0))} -> #N/A | AN13: =AL13-AM13 -> #N/A | AO13: =IFERROR(AL13/AM13,"") | AR13: =BQ13-AL13 -> 58608.224 | AT13: 5496.3025 | AU13: 5597.5637 | AV13: 5433.2976 | AW13: 5407.5714 | AX13: 5309.0118 | AY13: 5210.4521 | AZ13: 5133.7946 | BA13: 5226.8787 | BB13: 5281.6341 | BC13: 5371.4605 | BD13: 5425.9469 | BE13: 5453.1901 | BG13: =SUM(AT13:AU13) -> 11093.866 | BH13: =SUM(AT13:AV13) -> 16527.164 | BI13: =SUM(AT13:AW13) -> 21934.735 | BJ13: =SUM(AT13:AX13) -> 27243.747 | BK13: =SUM(AT13:AY13) -> 32454.199 | BL13: =SUM(AT13:AZ13) -> 37587.994 | BM13: =SUM(AT13:BA13) -> 42814.872 | BN13: =SUM(AT13:BB13) -> 48096.506 | BO13: =SUM(AT13:BC13) -> 53467.967 | BP13: =SUM(AT13:BD13) -> 58893.914 | BQ13: =SUM(AT13:BE13) -> 64347.104 | BS13: 6 | BT13: Jun | BU13: 6 | BW13: =$BT$8&"_"&BT13&"-"&RIGHT($BW$7,2) -> Jan_Jun-24
A14: Labor | B14: Labor | C14: Labor_Direct | D14: CC | E14: 624011 | F14: 62203100 | G14: Social insurance_Direct | H14: 40512.13 | I14: =SUMIFS(INDIRECT(I$5&"!N:N"),INDIRECT(I$5&"!L:L"),$E14,INDIRECT(I$5&"!K:K"),50)-SUMIFS(INDIRECT(I$5&"!N:N"),INDIRECT(I$5&"!L:L"),$E14,INDIRECT(I$5&"!K:K"),40) -> 40172.18 | J14: =SUMIFS(INDIRECT(J$5&"!N:N"),INDIRECT(J$5&"!L:L"),$E14,INDIRECT(J$5&"!K:K"),50)-SUMIFS(INDIRECT(J$5&"!N:N"),INDIRECT(J$5&"!L:L"),$E14,INDIRECT(J$5&"!K:K"),40) -> 0 | K14: =SUMIFS(INDIRECT(K$5&"!N:N"),INDIRECT(K$5&"!L:L"),$E14,INDIRECT(K$5&"!K:K"),50)-SUMIFS(INDIRECT(K$5&"!N:N"),INDIRECT(K$5&"!L:L"),$E14,INDIRECT(K$5&"!K:K"),40) -> 0 | L14: =SUMIFS(INDIRECT(L$5&"!N:N"),INDIRECT(L$5&"!L:L"),$E14,INDIRECT(L$5&"!K:K"),50)-SUMIFS(INDIRECT(L$5&"!N:N"),INDIRECT(L$5&"!L:L"),$E14,INDIRECT(L$5&"!K:K"),40) -> 0 | M14: =SUMIFS(INDIRECT(M$5&"!N:N"),INDIRECT(M$5&"!L:L"),$E14,INDIRECT(M$5&"!K:K"),50)-SUMIFS(INDIRECT(M$5&"!N:N"),INDIRECT(M$5&"!L:L"),$E14,INDIRECT(M$5&"!K:K"),40) -> 0 | N14: =SUMIFS(INDIRECT(N$5&"!N:N"),INDIRECT(N$5&"!L:L"),$E14,INDIRECT(N$5&"!K:K"),50)-SUMIFS(INDIRECT(N$5&"!N:N"),INDIRECT(N$5&"!L:L"),$E14,INDIRECT(N$5&"!K:K"),40) -> 0 | O14: =SUMIFS(INDIRECT(O$5&"!N:N"),INDIRECT(O$5&"!L:L"),$E14,INDIRECT(O$5&"!K:K"),50)-SUMIFS(INDIRECT(O$5&"!N:N"),INDIRECT(O$5&"!L:L"),$E14,INDIRECT(O$5&"!K:K"),40) -> 0 | P14: =SUMIFS(INDIRECT(P$5&"!N:N"),INDIRECT(P$5&"!L:L"),$E14,INDIRECT(P$5&"!K:K"),50)-SUMIFS(INDIRECT(P$5&"!N:N"),INDIRECT(P$5&"!L:L"),$E14,INDIRECT(P$5&"!K:K"),40) -> 0 | ... T14: =SUMIFS(INDIRECT(T$5&"!N:N"),INDIRECT(T$5&"!L:L"),$E14,INDIRECT(T$5&"!K:K"),50)-SUMIFS(INDIRECT(T$5&"!N:N"),INDIRECT(T$5&"!L:L"),$E14,INDIRECT(T$5&"!K:K"),40) -> 0 | U14: {=INDEX($I14:$T14,$U$2)} -> 40172.18 | X14: =U14+V14-W14 -> 40172.18 | Z14: {=IFERROR(U14/OFFSET($H14,,MATCH($G$2,$H$5:$U$5,0)-2,,),"-")} -> 0.99160869 | AA14: {=U14-OFFSET($H14,,MATCH($G$2,$H$5:$U$5,0)-2,,)} -> -339.95 | AD14: {=IFERROR(U14/OFFSET($AT14,,MATCH($G$2,$AT$5:$BE$5,0)-1,,),"-")} -> 1.0441352 | AE14: {=U14-OFFSET($AT14,,MATCH($G$2,$AT$5:$BE$5,0)-1,,)} -> 1698.0627 | AL14: =SUM(I14:T14) -> 40172.18 | AM14: {=INDEX($BG$8:$BQ$83,ROW()-7,MATCH($G$3,$BG$5:$BQ$5,0))} -> #N/A | AN14: =AL14-AM14 -> #N/A | AO14: =IFERROR(AL14/AM14,"") | AR14: =BQ14-AL14 -> 410257.55 | AT14: 38474.117 | AU14: 39182.946 | AV14: 38033.083 | AW14: 37853 | AX14: 37163.082 | AY14: 36473.165 | AZ14: 35936.562 | BA14: 36588.151 | BB14: 36971.439 | BC14: 37600.223 | BD14: 37981.628 | BE14: 38172.331 | BG14: =SUM(AT14:AU14) -> 77657.063 | BH14: =SUM(AT14:AV14) -> 115690.15 | BI14: =SUM(AT14:AW14) -> 153543.15 | BJ14: =SUM(AT14:AX14) -> 190706.23 | BK14: =SUM(AT14:AY14) -> 227179.39 | BL14: =SUM(AT14:AZ14) -> 263115.96 | BM14: =SUM(AT14:BA14) -> 299704.11 | BN14: =SUM(AT14:BB14) -> 336675.55 | BO14: =SUM(AT14:BC14) -> 374275.77 | BP14: =SUM(AT14:BD14) -> 412257.4 | BQ14: =SUM(AT14:BE14) -> 450429.73 | BS14: 7 | BT14: Jul | BU14: 7 | BW14: =$BT$8&"_"&BT14&"-"&RIGHT($BW$7,2) -> Jan_Jul-24
A15: Labor | B15: Labor | C15: Labor_Direct | D15: CC | E15: 624014 | F15: 62203120 | G15: Illness & maternity insurance_Direct | H15: 8681.16 | I15: =SUMIFS(INDIRECT(I$5&"!N:N"),INDIRECT(I$5&"!L:L"),$E15,INDIRECT(I$5&"!K:K"),50)-SUMIFS(INDIRECT(I$5&"!N:N"),INDIRECT(I$5&"!L:L"),$E15,INDIRECT(I$5&"!K:K"),40) -> 8608.32 | J15: =SUMIFS(INDIRECT(J$5&"!N:N"),INDIRECT(J$5&"!L:L"),$E15,INDIRECT(J$5&"!K:K"),50)-SUMIFS(INDIRECT(J$5&"!N:N"),INDIRECT(J$5&"!L:L"),$E15,INDIRECT(J$5&"!K:K"),40) -> 0 | K15: =SUMIFS(INDIRECT(K$5&"!N:N"),INDIRECT(K$5&"!L:L"),$E15,INDIRECT(K$5&"!K:K"),50)-SUMIFS(INDIRECT(K$5&"!N:N"),INDIRECT(K$5&"!L:L"),$E15,INDIRECT(K$5&"!K:K"),40) -> 0 | L15: =SUMIFS(INDIRECT(L$5&"!N:N"),INDIRECT(L$5&"!L:L"),$E15,INDIRECT(L$5&"!K:K"),50)-SUMIFS(INDIRECT(L$5&"!N:N"),INDIRECT(L$5&"!L:L"),$E15,INDIRECT(L$5&"!K:K"),40) -> 0 | M15: =SUMIFS(INDIRECT(M$5&"!N:N"),INDIRECT(M$5&"!L:L"),$E15,INDIRECT(M$5&"!K:K"),50)-SUMIFS(INDIRECT(M$5&"!N:N"),INDIRECT(M$5&"!L:L"),$E15,INDIRECT(M$5&"!K:K"),40) -> 0 | N15: =SUMIFS(INDIRECT(N$5&"!N:N"),INDIRECT(N$5&"!L:L"),$E15,INDIRECT(N$5&"!K:K"),50)-SUMIFS(INDIRECT(N$5&"!N:N"),INDIRECT(N$5&"!L:L"),$E15,INDIRECT(N$5&"!K:K"),40) -> 0 | O15: =SUMIFS(INDIRECT(O$5&"!N:N"),INDIRECT(O$5&"!L:L"),$E15,INDIRECT(O$5&"!K:K"),50)-SUMIFS(INDIRECT(O$5&"!N:N"),INDIRECT(O$5&"!L:L"),$E15,INDIRECT(O$5&"!K:K"),40) -> 0 | P15: =SUMIFS(INDIRECT(P$5&"!N:N"),INDIRECT(P$5&"!L:L"),$E15,INDIRECT(P$5&"!K:K"),50)-SUMIFS(INDIRECT(P$5&"!N:N"),INDIRECT(P$5&"!L:L"),$E15,INDIRECT(P$5&"!K:K"),40) -> 0 | ... T15: =SUMIFS(INDIRECT(T$5&"!N:N"),INDIRECT(T$5&"!L:L"),$E15,INDIRECT(T$5&"!K:K"),50)-SUMIFS(INDIRECT(T$5&"!N:N"),INDIRECT(T$5&"!L:L"),$E15,INDIRECT(T$5&"!K:K"),40) -> 0 | U15: {=INDEX($I15:$T15,$U$2)} -> 8608.32 | X15: =U15+V15-W15 -> 8608.32 | Z15: {=IFERROR(U15/OFFSET($H15,,MATCH($G$2,$H$5:$U$5,0)-2,,),"-")} -> 0.99160942 | AA15: {=U15-OFFSET($H15,,MATCH($G$2,$H$5:$U$5,0)-2,,)} -> -72.84 | AD15: {=IFERROR(U15/OFFSET($AT15,,MATCH($G$2,$AT$5:$BE$5,0)-1,,),"-")} -> 1.0441347 | AE15: {=U15-OFFSET($AT15,,MATCH($G$2,$AT$5:$BE$5,0)-1,,)} -> 363.8663 | AL15: =SUM(I15:T15) -> 8608.32 | AM15: {=INDEX($BG$8:$BQ$83,ROW()-7,MATCH($G$3,$BG$5:$BQ$5,0))} -> #N/A | AN15: =AL15-AM15 -> #N/A | AO15: =IFERROR(AL15/AM15,"") | AR15: =BQ15-AL15 -> 87912.336 | AT15: 8244.4537 | AU15: 8396.3455 | AV15: 8149.9463 | AW15: 8111.3572 | AX15: 7963.5177 | AY15: 7815.6782 | AZ15: 7700.6919 | BA15: 7840.3181 | BB15: 7922.4512 | BC15: 8057.1907 | BD15: 8138.9204 | BE15: 8179.7852 | BG15: =SUM(AT15:AU15) -> 16640.799 | BH15: =SUM(AT15:AV15) -> 24790.746 | BI15: =SUM(AT15:AW15) -> 32902.103 | BJ15: =SUM(AT15:AX15) -> 40865.62 | BK15: =SUM(AT15:AY15) -> 48681.299 | BL15: =SUM(AT15:AZ15) -> 56381.99 | BM15: =SUM(AT15:BA15) -> 64222.309 | BN15: =SUM(AT15:BB15) -> 72144.76 | BO15: =SUM(AT15:BC15) -> 80201.95 | BP15: =SUM(AT15:BD15) -> 88340.871 | BQ15: =SUM(AT15:BE15) -> 96520.656 | BS15: 8 | BT15: Aug | BU15: 8 | BW15: =$BT$8&"_"&BT15&"-"&RIGHT($BW$7,2) -> Jan_Aug-24
A16: Labor | B16: Labor | C16: Labor_Direct | D16: CC | E16: 624015 | F16: 62203300 | G16: Occupational insurance_Direct | H16: 1446.87 | I16: =SUMIFS(INDIRECT(I$5&"!N:N"),INDIRECT(I$5&"!L:L"),$E16,INDIRECT(I$5&"!K:K"),50)-SUMIFS(INDIRECT(I$5&"!N:N"),INDIRECT(I$5&"!L:L"),$E16,INDIRECT(I$5&"!K:K"),40) -> 1434.73 | J16: =SUMIFS(INDIRECT(J$5&"!N:N"),INDIRECT(J$5&"!L:L"),$E16,INDIRECT(J$5&"!K:K"),50)-SUMIFS(INDIRECT(J$5&"!N:N"),INDIRECT(J$5&"!L:L"),$E16,INDIRECT(J$5&"!K:K"),40) -> 0 | K16: =SUMIFS(INDIRECT(K$5&"!N:N"),INDIRECT(K$5&"!L:L"),$E16,INDIRECT(K$5&"!K:K"),50)-SUMIFS(INDIRECT(K$5&"!N:N"),INDIRECT(K$5&"!L:L"),$E16,INDIRECT(K$5&"!K:K"),40) -> 0 | L16: =SUMIFS(INDIRECT(L$5&"!N:N"),INDIRECT(L$5&"!L:L"),$E16,INDIRECT(L$5&"!K:K"),50)-SUMIFS(INDIRECT(L$5&"!N:N"),INDIRECT(L$5&"!L:L"),$E16,INDIRECT(L$5&"!K:K"),40) -> 0 | M16: =SUMIFS(INDIRECT(M$5&"!N:N"),INDIRECT(M$5&"!L:L"),$E16,INDIRECT(M$5&"!K:K"),50)-SUMIFS(INDIRECT(M$5&"!N:N"),INDIRECT(M$5&"!L:L"),$E16,INDIRECT(M$5&"!K:K"),40) -> 0 | N16: =SUMIFS(INDIRECT(N$5&"!N:N"),INDIRECT(N$5&"!L:L"),$E16,INDIRECT(N$5&"!K:K"),50)-SUMIFS(INDIRECT(N$5&"!N:N"),INDIRECT(N$5&"!L:L"),$E16,INDIRECT(N$5&"!K:K"),40) -> 0 | O16: =SUMIFS(INDIRECT(O$5&"!N:N"),INDIRECT(O$5&"!L:L"),$E16,INDIRECT(O$5&"!K:K"),50)-SUMIFS(INDIRECT(O$5&"!N:N"),INDIRECT(O$5&"!L:L"),$E16,INDIRECT(O$5&"!K:K"),40) -> 0 | P16: =SUMIFS(INDIRECT(P$5&"!N:N"),INDIRECT(P$5&"!L:L"),$E16,INDIRECT(P$5&"!K:K"),50)-SUMIFS(INDIRECT(P$5&"!N:N"),INDIRECT(P$5&"!L:L"),$E16,INDIRECT(P$5&"!K:K"),40) -> 0 | ... T16: =SUMIFS(INDIRECT(T$5&"!N:N"),INDIRECT(T$5&"!L:L"),$E16,INDIRECT(T$5&"!K:K"),50)-SUMIFS(INDIRECT(T$5&"!N:N"),INDIRECT(T$5&"!L:L"),$E16,INDIRECT(T$5&"!K:K"),40) -> 0 | U16: {=INDEX($I16:$T16,$U$2)} -> 1434.73 | X16: =U16+V16-W16 -> 1434.73 | Z16: {=IFERROR(U16/OFFSET($H16,,MATCH($G$2,$H$5:$U$5,0)-2,,),"-")} -> 0.99160947 | AA16: {=U16-OFFSET($H16,,MATCH($G$2,$H$5:$U$5,0)-2,,)} -> -12.14 | AD16: {=IFERROR(U16/OFFSET($AT16,,MATCH($G$2,$AT$5:$BE$5,0)-1,,),"-")} -> 1.044142 | AE16: {=U16-OFFSET($AT16,,MATCH($G$2,$AT$5:$BE$5,0)-1,,)} -> 60.654383 | AL16: =SUM(I16:T16) -> 1434.73 | AM16: {=INDEX($BG$8:$BQ$83,ROW()-7,MATCH($G$3,$BG$5:$BQ$5,0))} -> #N/A | AN16: =AL16-AM16 -> #N/A | AO16: =IFERROR(AL16/AM16,"") | AR16: =BQ16-AL16 -> 14652.046 | AT16: 1374.0756 | AU16: 1399.3909 | AV16: 1358.3244 | AW16: 1351.8929 | AX16: 1327.2529 | AY16: 1302.613 | AZ16: 1283.4487 | BA16: 1306.7197 | BB16: 1320.4085 | BC16: 1342.8651 | BD16: 1356.4867 | BE16: 1363.2975 | BG16: =SUM(AT16:AU16) -> 2773.4665 | BH16: =SUM(AT16:AV16) -> 4131.7909 | BI16: =SUM(AT16:AW16) -> 5483.6838 | BJ16: =SUM(AT16:AX16) -> 6810.9367 | BK16: =SUM(AT16:AY16) -> 8113.5498 | BL16: =SUM(AT16:AZ16) -> 9396.9984 | BM16: =SUM(AT16:BA16) -> 10703.718 | BN16: =SUM(AT16:BB16) -> 12024.127 | BO16: =SUM(AT16:BC16) -> 13366.992 | BP16: =SUM(AT16:BD16) -> 14723.478 | BQ16: =SUM(AT16:BE16) -> 16086.776 | BS16: 9 | BT16: Sep | BU16: 9 | BW16: =$BT$8&"_"&BT16&"-"&RIGHT($BW$7,2) -> Jan_Sep-24
A17: Labor | B17: Labor | C17: Labor_Direct | D17: CC | E17: 624013 | F17: 62204000 | G17: Health insurance_Direct | H17: 8754.22 | I17: =SUMIFS(INDIRECT(I$5&"!N:N"),INDIRECT(I$5&"!L:L"),$E17,INDIRECT(I$5&"!K:K"),50)-SUMIFS(INDIRECT(I$5&"!N:N"),INDIRECT(I$5&"!L:L"),$E17,INDIRECT(I$5&"!K:K"),40) -> 8623.52 | J17: =SUMIFS(INDIRECT(J$5&"!N:N"),INDIRECT(J$5&"!L:L"),$E17,INDIRECT(J$5&"!K:K"),50)-SUMIFS(INDIRECT(J$5&"!N:N"),INDIRECT(J$5&"!L:L"),$E17,INDIRECT(J$5&"!K:K"),40) -> 0 | K17: =SUMIFS(INDIRECT(K$5&"!N:N"),INDIRECT(K$5&"!L:L"),$E17,INDIRECT(K$5&"!K:K"),50)-SUMIFS(INDIRECT(K$5&"!N:N"),INDIRECT(K$5&"!L:L"),$E17,INDIRECT(K$5&"!K:K"),40) -> 0 | L17: =SUMIFS(INDIRECT(L$5&"!N:N"),INDIRECT(L$5&"!L:L"),$E17,INDIRECT(L$5&"!K:K"),50)-SUMIFS(INDIRECT(L$5&"!N:N"),INDIRECT(L$5&"!L:L"),$E17,INDIRECT(L$5&"!K:K"),40) -> 0 | M17: =SUMIFS(INDIRECT(M$5&"!N:N"),INDIRECT(M$5&"!L:L"),$E17,INDIRECT(M$5&"!K:K"),50)-SUMIFS(INDIRECT(M$5&"!N:N"),INDIRECT(M$5&"!L:L"),$E17,INDIRECT(M$5&"!K:K"),40) -> 0 | N17: =SUMIFS(INDIRECT(N$5&"!N:N"),INDIRECT(N$5&"!L:L"),$E17,INDIRECT(N$5&"!K:K"),50)-SUMIFS(INDIRECT(N$5&"!N:N"),INDIRECT(N$5&"!L:L"),$E17,INDIRECT(N$5&"!K:K"),40) -> 0 | O17: =SUMIFS(INDIRECT(O$5&"!N:N"),INDIRECT(O$5&"!L:L"),$E17,INDIRECT(O$5&"!K:K"),50)-SUMIFS(INDIRECT(O$5&"!N:N"),INDIRECT(O$5&"!L:L"),$E17,INDIRECT(O$5&"!K:K"),40) -> 0 | P17: =SUMIFS(INDIRECT(P$5&"!N:N"),INDIRECT(P$5&"!L:L"),$E17,INDIRECT(P$5&"!K:K"),50)-SUMIFS(INDIRECT(P$5&"!N:N"),INDIRECT(P$5&"!L:L"),$E17,INDIRECT(P$5&"!K:K"),40) -> 0 | ... T17: =SUMIFS(INDIRECT(T$5&"!N:N"),INDIRECT(T$5&"!L:L"),$E17,INDIRECT(T$5&"!K:K"),50)-SUMIFS(INDIRECT(T$5&"!N:N"),INDIRECT(T$5&"!L:L"),$E17,INDIRECT(T$5&"!K:K"),40) -> 0 | U17: {=INDEX($I17:$T17,$U$2)} -> 8623.52 | X17: =U17+V17-W17 -> 8623.52 | Z17: {=IFERROR(U17/OFFSET($H17,,MATCH($G$2,$H$5:$U$5,0)-2,,),"-")} -> 0.98507006 | AA17: {=U17-OFFSET($H17,,MATCH($G$2,$H$5:$U$5,0)-2,,)} -> -130.7 | AD17: {=IFERROR(U17/OFFSET($AT17,,MATCH($G$2,$AT$5:$BE$5,0)-1,,),"-")} -> 1.0459783 | AE17: {=U17-OFFSET($AT17,,MATCH($G$2,$AT$5:$BE$5,0)-1,,)} -> 379.0663 | AL17: =SUM(I17:T17) -> 8623.52 | AM17: {=INDEX($BG$8:$BQ$83,ROW()-7,MATCH($G$3,$BG$5:$BQ$5,0))} -> #N/A | AN17: =AL17-AM17 -> #N/A | AO17: =IFERROR(AL17/AM17,"") | AR17: =BQ17-AL17 -> 87897.136 | AT17: 8244.4537 | AU17: 8396.3455 | AV17: 8149.9463 | AW17: 8111.3572 | AX17: 7963.5177 | AY17: 7815.6782 | AZ17: 7700.6919 | BA17: 7840.3181 | BB17: 7922.4512 | BC17: 8057.1907 | BD17: 8138.9204 | BE17: 8179.7852 | BG17: =SUM(AT17:AU17) -> 16640.799 | BH17: =SUM(AT17:AV17) -> 24790.746 | BI17: =SUM(AT17:AW17) -> 32902.103 | BJ17: =SUM(AT17:AX17) -> 40865.62 | BK17: =SUM(AT17:AY17) -> 48681.299 | BL17: =SUM(AT17:AZ17) -> 56381.99 | BM17: =SUM(AT17:BA17) -> 64222.309 | BN17: =SUM(AT17:BB17) -> 72144.76 | BO17: =SUM(AT17:BC17) -> 80201.95 | BP17: =SUM(AT17:BD17) -> 88340.871 | BQ17: =SUM(AT17:BE17) -> 96520.656 | BS17: 10 | BT17: Oct | BU17: 10 | BW17: =$BT$8&"_"&BT17&"-"&RIGHT($BW$7,2) -> Jan_Oct-24
A18: Labor | B18: Labor | C18: Labor_Direct | D18: CC | E18: 624100 | F18: 62204100 | G18: Other insurance_Direct | H18: 494.12 | I18: =SUMIFS(INDIRECT(I$5&"!N:N"),INDIRECT(I$5&"!L:L"),$E18,INDIRECT(I$5&"!K:K"),50)-SUMIFS(INDIRECT(I$5&"!N:N"),INDIRECT(I$5&"!L:L"),$E18,INDIRECT(I$5&"!K:K"),40) -> 424.96 | J18: =SUMIFS(INDIRECT(J$5&"!N:N"),INDIRECT(J$5&"!L:L"),$E18,INDIRECT(J$5&"!K:K"),50)-SUMIFS(INDIRECT(J$5&"!N:N"),INDIRECT(J$5&"!L:L"),$E18,INDIRECT(J$5&"!K:K"),40) -> 0 | K18: =SUMIFS(INDIRECT(K$5&"!N:N"),INDIRECT(K$5&"!L:L"),$E18,INDIRECT(K$5&"!K:K"),50)-SUMIFS(INDIRECT(K$5&"!N:N"),INDIRECT(K$5&"!L:L"),$E18,INDIRECT(K$5&"!K:K"),40) -> 0 | L18: =SUMIFS(INDIRECT(L$5&"!N:N"),INDIRECT(L$5&"!L:L"),$E18,INDIRECT(L$5&"!K:K"),50)-SUMIFS(INDIRECT(L$5&"!N:N"),INDIRECT(L$5&"!L:L"),$E18,INDIRECT(L$5&"!K:K"),40) -> 0 | M18: =SUMIFS(INDIRECT(M$5&"!N:N"),INDIRECT(M$5&"!L:L"),$E18,INDIRECT(M$5&"!K:K"),50)-SUMIFS(INDIRECT(M$5&"!N:N"),INDIRECT(M$5&"!L:L"),$E18,INDIRECT(M$5&"!K:K"),40) -> 0 | N18: =SUMIFS(INDIRECT(N$5&"!N:N"),INDIRECT(N$5&"!L:L"),$E18,INDIRECT(N$5&"!K:K"),50)-SUMIFS(INDIRECT(N$5&"!N:N"),INDIRECT(N$5&"!L:L"),$E18,INDIRECT(N$5&"!K:K"),40) -> 0 | O18: =SUMIFS(INDIRECT(O$5&"!N:N"),INDIRECT(O$5&"!L:L"),$E18,INDIRECT(O$5&"!K:K"),50)-SUMIFS(INDIRECT(O$5&"!N:N"),INDIRECT(O$5&"!L:L"),$E18,INDIRECT(O$5&"!K:K"),40) -> 0 | P18: =SUMIFS(INDIRECT(P$5&"!N:N"),INDIRECT(P$5&"!L:L"),$E18,INDIRECT(P$5&"!K:K"),50)-SUMIFS(INDIRECT(P$5&"!N:N"),INDIRECT(P$5&"!L:L"),$E18,INDIRECT(P$5&"!K:K"),40) -> 0 | ... T18: =SUMIFS(INDIRECT(T$5&"!N:N"),INDIRECT(T$5&"!L:L"),$E18,INDIRECT(T$5&"!K:K"),50)-SUMIFS(INDIRECT(T$5&"!N:N"),INDIRECT(T$5&"!L:L"),$E18,INDIRECT(T$5&"!K:K"),40) -> 0 | U18: {=INDEX($I18:$T18,$U$2)} -> 424.96 | X18: =U18+V18-W18 -> 424.96 | Z18: {=IFERROR(U18/OFFSET($H18,,MATCH($G$2,$H$5:$U$5,0)-2,,),"-")} -> 0.860034 | AA18: {=U18-OFFSET($H18,,MATCH($G$2,$H$5:$U$5,0)-2,,)} -> -69.16 | AD18: {=IFERROR(U18/OFFSET($AT18,,MATCH($G$2,$AT$5:$BE$5,0)-1,,),"-")} -> 0.020422643 | AE18: {=U18-OFFSET($AT18,,MATCH($G$2,$AT$5:$BE$5,0)-1,,)} -> -20383.316 | AF18: - allocate 24/7 - Delay accident insurance for family member & travel insurance -10K | AL18: =SUM(I18:T18) -> 424.96 | AM18: {=INDEX($BG$8:$BQ$83,ROW()-7,MATCH($G$3,$BG$5:$BQ$5,0))} -> #N/A | AN18: =AL18-AM18 -> #N/A | AO18: =IFERROR(AL18/AM18,"") | AR18: =BQ18-AL18 -> 20383.316 | AT18: 20808.276 | AU18: 0 | AV18: 0 | AW18: 0 | AX18: 0 | AY18: 0 | AZ18: 0 | BA18: 0 | BB18: 0 | BC18: 0 | BD18: 0 | BE18: 0 | BG18: =SUM(AT18:AU18) -> 20808.276 | BH18: =SUM(AT18:AV18) -> 20808.276 | BI18: =SUM(AT18:AW18) -> 20808.276 | BJ18: =SUM(AT18:AX18) -> 20808.276 | BK18: =SUM(AT18:AY18) -> 20808.276 | BL18: =SUM(AT18:AZ18) -> 20808.276 | BM18: =SUM(AT18:BA18) -> 20808.276 | BN18: =SUM(AT18:BB18) -> 20808.276 | BO18: =SUM(AT18:BC18) -> 20808.276 | BP18: =SUM(AT18:BD18) -> 20808.276 | BQ18: =SUM(AT18:BE18) -> 20808.276 | BS18: 11 | BT18: Nov | BU18: 11 | BW18: =$BT$8&"_"&BT18&"-"&RIGHT($BW$7,2) -> Jan_Nov-24
A19: Labor | B19: Labor | C19: Labor_Direct | D19: CC | E19: 624103 | F19: 62204200 | G19: Compensation allowances_Direct | H19: 0 | I19: =SUMIFS(INDIRECT(I$5&"!N:N"),INDIRECT(I$5&"!L:L"),$E19,INDIRECT(I$5&"!K:K"),50)-SUMIFS(INDIRECT(I$5&"!N:N"),INDIRECT(I$5&"!L:L"),$E19,INDIRECT(I$5&"!K:K"),40) -> 0 | J19: =SUMIFS(INDIRECT(J$5&"!N:N"),INDIRECT(J$5&"!L:L"),$E19,INDIRECT(J$5&"!K:K"),50)-SUMIFS(INDIRECT(J$5&"!N:N"),INDIRECT(J$5&"!L:L"),$E19,INDIRECT(J$5&"!K:K"),40) -> 0 | K19: =SUMIFS(INDIRECT(K$5&"!N:N"),INDIRECT(K$5&"!L:L"),$E19,INDIRECT(K$5&"!K:K"),50)-SUMIFS(INDIRECT(K$5&"!N:N"),INDIRECT(K$5&"!L:L"),$E19,INDIRECT(K$5&"!K:K"),40) -> 0 | L19: =SUMIFS(INDIRECT(L$5&"!N:N"),INDIRECT(L$5&"!L:L"),$E19,INDIRECT(L$5&"!K:K"),50)-SUMIFS(INDIRECT(L$5&"!N:N"),INDIRECT(L$5&"!L:L"),$E19,INDIRECT(L$5&"!K:K"),40) -> 0 | M19: =SUMIFS(INDIRECT(M$5&"!N:N"),INDIRECT(M$5&"!L:L"),$E19,INDIRECT(M$5&"!K:K"),50)-SUMIFS(INDIRECT(M$5&"!N:N"),INDIRECT(M$5&"!L:L"),$E19,INDIRECT(M$5&"!K:K"),40) -> 0 | N19: =SUMIFS(INDIRECT(N$5&"!N:N"),INDIRECT(N$5&"!L:L"),$E19,INDIRECT(N$5&"!K:K"),50)-SUMIFS(INDIRECT(N$5&"!N:N"),INDIRECT(N$5&"!L:L"),$E19,INDIRECT(N$5&"!K:K"),40) -> 0 | O19: =SUMIFS(INDIRECT(O$5&"!N:N"),INDIRECT(O$5&"!L:L"),$E19,INDIRECT(O$5&"!K:K"),50)-SUMIFS(INDIRECT(O$5&"!N:N"),INDIRECT(O$5&"!L:L"),$E19,INDIRECT(O$5&"!K:K"),40) -> 0 | P19: =SUMIFS(INDIRECT(P$5&"!N:N"),INDIRECT(P$5&"!L:L"),$E19,INDIRECT(P$5&"!K:K"),50)-SUMIFS(INDIRECT(P$5&"!N:N"),INDIRECT(P$5&"!L:L"),$E19,INDIRECT(P$5&"!K:K"),40) -> 0 | ... T19: =SUMIFS(INDIRECT(T$5&"!N:N"),INDIRECT(T$5&"!L:L"),$E19,INDIRECT(T$5&"!K:K"),50)-SUMIFS(INDIRECT(T$5&"!N:N"),INDIRECT(T$5&"!L:L"),$E19,INDIRECT(T$5&"!K:K"),40) -> 0 | U19: {=INDEX($I19:$T19,$U$2)} -> 0 | X19: =U19+V19-W19 -> 0 | Z19: {=IFERROR(U19/OFFSET($H19,,MATCH($G$2,$H$5:$U$5,0)-2,,),"-")} -> - | AA19: {=U19-OFFSET($H19,,MATCH($G$2,$H$5:$U$5,0)-2,,)} -> 0 | AD19: {=IFERROR(U19/OFFSET($AT19,,MATCH($G$2,$AT$5:$BE$5,0)-1,,),"-")} -> - | AE19: {=U19-OFFSET($AT19,,MATCH($G$2,$AT$5:$BE$5,0)-1,,)} -> 0 | AL19: =SUM(I19:T19) -> 0 | AM19: {=INDEX($BG$8:$BQ$83,ROW()-7,MATCH($G$3,$BG$5:$BQ$5,0))} -> #N/A | AN19: =AL19-AM19 -> #N/A | AO19: =IFERROR(AL19/AM19,"") | AR19: =BQ19-AL19 -> 0 | AT19: 0 | AU19: 0 | AV19: 0 | AW19: 0 | AX19: 0 | AY19: 0 | AZ19: 0 | BA19: 0 | BB19: 0 | BC19: 0 | BD19: 0 | BE19: 0 | BG19: =SUM(AT19:AU19) -> 0 | BH19: =SUM(AT19:AV19) -> 0 | BI19: =SUM(AT19:AW19) -> 0 | BJ19: =SUM(AT19:AX19) -> 0 | BK19: =SUM(AT19:AY19) -> 0 | BL19: =SUM(AT19:AZ19) -> 0 | BM19: =SUM(AT19:BA19) -> 0 | BN19: =SUM(AT19:BB19) -> 0 | BO19: =SUM(AT19:BC19) -> 0 | BP19: =SUM(AT19:BD19) -> 0 | BQ19: =SUM(AT19:BE19) -> 0 | BS19: 12 | BT19: Dec | BU19: 12 | BW19: =$BT$8&"_"&BT19&"-"&RIGHT($BW$7,2) -> Jan_Dec-24
A20: Labor | B20: Labor | C20: Labor_Direct | D20: CC | E20: 624012 | F20: 62206000 | G20: Unemployment insurance_Direct | H20: 2893.72 | I20: =SUMIFS(INDIRECT(I$5&"!N:N"),INDIRECT(I$5&"!L:L"),$E20,INDIRECT(I$5&"!K:K"),50)-SUMIFS(INDIRECT(I$5&"!N:N"),INDIRECT(I$5&"!L:L"),$E20,INDIRECT(I$5&"!K:K"),40) -> 2869.44 | J20: =SUMIFS(INDIRECT(J$5&"!N:N"),INDIRECT(J$5&"!L:L"),$E20,INDIRECT(J$5&"!K:K"),50)-SUMIFS(INDIRECT(J$5&"!N:N"),INDIRECT(J$5&"!L:L"),$E20,INDIRECT(J$5&"!K:K"),40) -> 0 | K20: =SUMIFS(INDIRECT(K$5&"!N:N"),INDIRECT(K$5&"!L:L"),$E20,INDIRECT(K$5&"!K:K"),50)-SUMIFS(INDIRECT(K$5&"!N:N"),INDIRECT(K$5&"!L:L"),$E20,INDIRECT(K$5&"!K:K"),40) -> 0 | L20: =SUMIFS(INDIRECT(L$5&"!N:N"),INDIRECT(L$5&"!L:L"),$E20,INDIRECT(L$5&"!K:K"),50)-SUMIFS(INDIRECT(L$5&"!N:N"),INDIRECT(L$5&"!L:L"),$E20,INDIRECT(L$5&"!K:K"),40) -> 0 | M20: =SUMIFS(INDIRECT(M$5&"!N:N"),INDIRECT(M$5&"!L:L"),$E20,INDIRECT(M$5&"!K:K"),50)-SUMIFS(INDIRECT(M$5&"!N:N"),INDIRECT(M$5&"!L:L"),$E20,INDIRECT(M$5&"!K:K"),40) -> 0 | N20: =SUMIFS(INDIRECT(N$5&"!N:N"),INDIRECT(N$5&"!L:L"),$E20,INDIRECT(N$5&"!K:K"),50)-SUMIFS(INDIRECT(N$5&"!N:N"),INDIRECT(N$5&"!L:L"),$E20,INDIRECT(N$5&"!K:K"),40) -> 0 | O20: =SUMIFS(INDIRECT(O$5&"!N:N"),INDIRECT(O$5&"!L:L"),$E20,INDIRECT(O$5&"!K:K"),50)-SUMIFS(INDIRECT(O$5&"!N:N"),INDIRECT(O$5&"!L:L"),$E20,INDIRECT(O$5&"!K:K"),40) -> 0 | P20: =SUMIFS(INDIRECT(P$5&"!N:N"),INDIRECT(P$5&"!L:L"),$E20,INDIRECT(P$5&"!K:K"),50)-SUMIFS(INDIRECT(P$5&"!N:N"),INDIRECT(P$5&"!L:L"),$E20,INDIRECT(P$5&"!K:K"),40) -> 0 | ... T20: =SUMIFS(INDIRECT(T$5&"!N:N"),INDIRECT(T$5&"!L:L"),$E20,INDIRECT(T$5&"!K:K"),50)-SUMIFS(INDIRECT(T$5&"!N:N"),INDIRECT(T$5&"!L:L"),$E20,INDIRECT(T$5&"!K:K"),40) -> 0 | U20: {=INDEX($I20:$T20,$U$2)} -> 2869.44 | X20: =U20+V20-W20 -> 2869.44 | Z20: {=IFERROR(U20/OFFSET($H20,,MATCH($G$2,$H$5:$U$5,0)-2,,),"-")} -> 0.99160942 | AA20: {=U20-OFFSET($H20,,MATCH($G$2,$H$5:$U$5,0)-2,,)} -> -24.28 | AD20: {=IFERROR(U20/OFFSET($AT20,,MATCH($G$2,$AT$5:$BE$5,0)-1,,),"-")} -> 1.0440305 | AE20: {=U20-OFFSET($AT20,,MATCH($G$2,$AT$5:$BE$5,0)-1,,)} -> 121.01466 | AL20: =SUM(I20:T20) -> 2869.44 | AM20: {=INDEX($BG$8:$BQ$83,ROW()-7,MATCH($G$3,$BG$5:$BQ$5,0))} -> #N/A | AN20: =AL20-AM20 -> #N/A | AO20: =IFERROR(AL20/AM20,"") | AR20: =BQ20-AL20 -> 30804.329 | AT20: 2748.4253 | AU20: 2798.7532 | AV20: 2716.6202 | AW20: 2703.7857 | AX20: 2654.5059 | AY20: 2605.2261 | AZ20: 2566.8973 | BA20: 2613.4394 | BB20: 2640.8171 | BC20: 2685.7302 | BD20: 2712.9735 | BE20: 4226.5951 | BG20: =SUM(AT20:AU20) -> 5547.1786 | BH20: =SUM(AT20:AV20) -> 8263.7987 | BI20: =SUM(AT20:AW20) -> 10967.584 | BJ20: =SUM(AT20:AX20) -> 13622.09 | BK20: =SUM(AT20:AY20) -> 16227.316 | BL20: =SUM(AT20:AZ20) -> 18794.214 | BM20: =SUM(AT20:BA20) -> 21407.653 | BN20: =SUM(AT20:BB20) -> 24048.47 | BO20: =SUM(AT20:BC20) -> 26734.2 | BP20: =SUM(AT20:BD20) -> 29447.174 | BQ20: =SUM(AT20:BE20) -> 33673.769
A21: Labor | B21: Labor | C21: Labor_Indirect | D21: CC | E21: 621011 | F21: 62710101 | G21: Remuneration_Local_Indirect | H21: 222758.42 | I21: =SUMIFS(INDIRECT(I$5&"!N:N"),INDIRECT(I$5&"!L:L"),$E21,INDIRECT(I$5&"!K:K"),50)-SUMIFS(INDIRECT(I$5&"!N:N"),INDIRECT(I$5&"!L:L"),$E21,INDIRECT(I$5&"!K:K"),40) -> 209833.31 | J21: =SUMIFS(INDIRECT(J$5&"!N:N"),INDIRECT(J$5&"!L:L"),$E21,INDIRECT(J$5&"!K:K"),50)-SUMIFS(INDIRECT(J$5&"!N:N"),INDIRECT(J$5&"!L:L"),$E21,INDIRECT(J$5&"!K:K"),40) -> 0 | K21: =SUMIFS(INDIRECT(K$5&"!N:N"),INDIRECT(K$5&"!L:L"),$E21,INDIRECT(K$5&"!K:K"),50)-SUMIFS(INDIRECT(K$5&"!N:N"),INDIRECT(K$5&"!L:L"),$E21,INDIRECT(K$5&"!K:K"),40) -> 0 | L21: =SUMIFS(INDIRECT(L$5&"!N:N"),INDIRECT(L$5&"!L:L"),$E21,INDIRECT(L$5&"!K:K"),50)-SUMIFS(INDIRECT(L$5&"!N:N"),INDIRECT(L$5&"!L:L"),$E21,INDIRECT(L$5&"!K:K"),40) -> 0 | M21: =SUMIFS(INDIRECT(M$5&"!N:N"),INDIRECT(M$5&"!L:L"),$E21,INDIRECT(M$5&"!K:K"),50)-SUMIFS(INDIRECT(M$5&"!N:N"),INDIRECT(M$5&"!L:L"),$E21,INDIRECT(M$5&"!K:K"),40) -> 0 | N21: =SUMIFS(INDIRECT(N$5&"!N:N"),INDIRECT(N$5&"!L:L"),$E21,INDIRECT(N$5&"!K:K"),50)-SUMIFS(INDIRECT(N$5&"!N:N"),INDIRECT(N$5&"!L:L"),$E21,INDIRECT(N$5&"!K:K"),40) -> 0 | O21: =SUMIFS(INDIRECT(O$5&"!N:N"),INDIRECT(O$5&"!L:L"),$E21,INDIRECT(O$5&"!K:K"),50)-SUMIFS(INDIRECT(O$5&"!N:N"),INDIRECT(O$5&"!L:L"),$E21,INDIRECT(O$5&"!K:K"),40) -> 0 | P21: =SUMIFS(INDIRECT(P$5&"!N:N"),INDIRECT(P$5&"!L:L"),$E21,INDIRECT(P$5&"!K:K"),50)-SUMIFS(INDIRECT(P$5&"!N:N"),INDIRECT(P$5&"!L:L"),$E21,INDIRECT(P$5&"!K:K"),40) -> 0 | ... T21: =SUMIFS(INDIRECT(T$5&"!N:N"),INDIRECT(T$5&"!L:L"),$E21,INDIRECT(T$5&"!K:K"),50)-SUMIFS(INDIRECT(T$5&"!N:N"),INDIRECT(T$5&"!L:L"),$E21,INDIRECT(T$5&"!K:K"),40) -> 0 | U21: {=INDEX($I21:$T21,$U$2)} -> 209833.31 | X21: =U21+V21-W21 -> 209833.31 | Z21: {=IFERROR(U21/OFFSET($H21,,MATCH($G$2,$H$5:$U$5,0)-2,,),"-")} -> 0.94197701 | AA21: {=U21-OFFSET($H21,,MATCH($G$2,$H$5:$U$5,0)-2,,)} -> -12925.11 | AD21: {=IFERROR(U21/OFFSET($AT21,,MATCH($G$2,$AT$5:$BE$5,0)-1,,),"-")} -> 0.95870787 | AE21: {=U21-OFFSET($AT21,,MATCH($G$2,$AT$5:$BE$5,0)-1,,)} -> -9037.6474 | AL21: =SUM(I21:T21) -> 209833.31 | AM21: {=INDEX($BG$8:$BQ$83,ROW()-7,MATCH($G$3,$BG$5:$BQ$5,0))} -> #N/A | AN21: =AL21-AM21 -> #N/A | AO21: =IFERROR(AL21/AM21,"") | AR21: =BQ21-AL21 -> 2567937.7 | AT21: 218870.96 | AU21: 219691.12 | AV21: 219669.87 | AW21: 235628.25 | AX21: 234949.08 | AY21: 234970.33 | AZ21: 234916.37 | BA21: 234916.37 | BB21: 234916.37 | BC21: 236433.49 | BD21: 236433.49 | BE21: 236375.35 | BG21: =SUM(AT21:AU21) -> 438562.08 | BH21: =SUM(AT21:AV21) -> 658231.95 | BI21: =SUM(AT21:AW21) -> 893860.2 | BJ21: =SUM(AT21:AX21) -> 1128809.3 | BK21: =SUM(AT21:AY21) -> 1363779.6 | BL21: =SUM(AT21:AZ21) -> 1598696 | BM21: =SUM(AT21:BA21) -> 1833612.3 | BN21: =SUM(AT21:BB21) -> 2068528.7 | BO21: =SUM(AT21:BC21) -> 2304962.2 | BP21: =SUM(AT21:BD21) -> 2541395.7 | BQ21: =SUM(AT21:BE21) -> 2777771
A22: Labor | B22: Labor | C22: Labor_Indirect | D22: CC | E22: 621012 | F22: 62710102 | G22: Remuneration_Expat_Indirect | H22: 33078.05 | I22: =SUMIFS(INDIRECT(I$5&"!N:N"),INDIRECT(I$5&"!L:L"),$E22,INDIRECT(I$5&"!K:K"),50)-SUMIFS(INDIRECT(I$5&"!N:N"),INDIRECT(I$5&"!L:L"),$E22,INDIRECT(I$5&"!K:K"),40) -> 32492.62 | J22: =SUMIFS(INDIRECT(J$5&"!N:N"),INDIRECT(J$5&"!L:L"),$E22,INDIRECT(J$5&"!K:K"),50)-SUMIFS(INDIRECT(J$5&"!N:N"),INDIRECT(J$5&"!L:L"),$E22,INDIRECT(J$5&"!K:K"),40) -> 0 | K22: =SUMIFS(INDIRECT(K$5&"!N:N"),INDIRECT(K$5&"!L:L"),$E22,INDIRECT(K$5&"!K:K"),50)-SUMIFS(INDIRECT(K$5&"!N:N"),INDIRECT(K$5&"!L:L"),$E22,INDIRECT(K$5&"!K:K"),40) -> 0 | L22: =SUMIFS(INDIRECT(L$5&"!N:N"),INDIRECT(L$5&"!L:L"),$E22,INDIRECT(L$5&"!K:K"),50)-SUMIFS(INDIRECT(L$5&"!N:N"),INDIRECT(L$5&"!L:L"),$E22,INDIRECT(L$5&"!K:K"),40) -> 0 | M22: =SUMIFS(INDIRECT(M$5&"!N:N"),INDIRECT(M$5&"!L:L"),$E22,INDIRECT(M$5&"!K:K"),50)-SUMIFS(INDIRECT(M$5&"!N:N"),INDIRECT(M$5&"!L:L"),$E22,INDIRECT(M$5&"!K:K"),40) -> 0 | N22: =SUMIFS(INDIRECT(N$5&"!N:N"),INDIRECT(N$5&"!L:L"),$E22,INDIRECT(N$5&"!K:K"),50)-SUMIFS(INDIRECT(N$5&"!N:N"),INDIRECT(N$5&"!L:L"),$E22,INDIRECT(N$5&"!K:K"),40) -> 0 | O22: =SUMIFS(INDIRECT(O$5&"!N:N"),INDIRECT(O$5&"!L:L"),$E22,INDIRECT(O$5&"!K:K"),50)-SUMIFS(INDIRECT(O$5&"!N:N"),INDIRECT(O$5&"!L:L"),$E22,INDIRECT(O$5&"!K:K"),40) -> 0 | P22: =SUMIFS(INDIRECT(P$5&"!N:N"),INDIRECT(P$5&"!L:L"),$E22,INDIRECT(P$5&"!K:K"),50)-SUMIFS(INDIRECT(P$5&"!N:N"),INDIRECT(P$5&"!L:L"),$E22,INDIRECT(P$5&"!K:K"),40) -> 0 | ... T22: =SUMIFS(INDIRECT(T$5&"!N:N"),INDIRECT(T$5&"!L:L"),$E22,INDIRECT(T$5&"!K:K"),50)-SUMIFS(INDIRECT(T$5&"!N:N"),INDIRECT(T$5&"!L:L"),$E22,INDIRECT(T$5&"!K:K"),40) -> 0 | U22: {=INDEX($I22:$T22,$U$2)} -> 32492.62 | X22: =U22+V22-W22 -> 32492.62 | Z22: {=IFERROR(U22/OFFSET($H22,,MATCH($G$2,$H$5:$U$5,0)-2,,),"-")} -> 0.98230156 | AA22: {=U22-OFFSET($H22,,MATCH($G$2,$H$5:$U$5,0)-2,,)} -> -585.43 | AD22: {=IFERROR(U22/OFFSET($AT22,,MATCH($G$2,$AT$5:$BE$5,0)-1,,),"-")} -> 0.87807176 | AE22: {=U22-OFFSET($AT22,,MATCH($G$2,$AT$5:$BE$5,0)-1,,)} -> -4511.8954 | AL22: =SUM(I22:T22) -> 32492.62 | AM22: {=INDEX($BG$8:$BQ$83,ROW()-7,MATCH($G$3,$BG$5:$BQ$5,0))} -> #N/A | AN22: =AL22-AM22 -> #N/A | AO22: =IFERROR(AL22/AM22,"") | AR22: =BQ22-AL22 -> 425728.46 | AT22: 37004.515 | AU22: 37004.515 | AV22: 37004.515 | AW22: 51171.412 | AX22: 37004.515 | AY22: 37004.515 | AZ22: 37004.515 | BA22: 37004.515 | BB22: 37004.515 | BC22: 37004.515 | BD22: 37004.515 | BE22: 37004.515 | BG22: =SUM(AT22:AU22) -> 74009.031 | BH22: =SUM(AT22:AV22) -> 111013.55 | BI22: =SUM(AT22:AW22) -> 162184.96 | BJ22: =SUM(AT22:AX22) -> 199189.47 | BK22: =SUM(AT22:AY22) -> 236193.99 | BL22: =SUM(AT22:AZ22) -> 273198.5 | BM22: =SUM(AT22:BA22) -> 310203.02 | BN22: =SUM(AT22:BB22) -> 347207.53 | BO22: =SUM(AT22:BC22) -> 384212.05 | BP22: =SUM(AT22:BD22) -> 421216.57 | BQ22: =SUM(AT22:BE22) -> 458221.08
A23: Labor | B23: Labor | C23: Labor_Indirect | D23: CC | E23: 621013 | F23: 62710103 | G23: Remuneration_Local_Other_Indirect | H23: 435.28 | I23: =SUMIFS(INDIRECT(I$5&"!N:N"),INDIRECT(I$5&"!L:L"),$E23,INDIRECT(I$5&"!K:K"),50)-SUMIFS(INDIRECT(I$5&"!N:N"),INDIRECT(I$5&"!L:L"),$E23,INDIRECT(I$5&"!K:K"),40) -> 266.28 | J23: =SUMIFS(INDIRECT(J$5&"!N:N"),INDIRECT(J$5&"!L:L"),$E23,INDIRECT(J$5&"!K:K"),50)-SUMIFS(INDIRECT(J$5&"!N:N"),INDIRECT(J$5&"!L:L"),$E23,INDIRECT(J$5&"!K:K"),40) -> 0 | K23: =SUMIFS(INDIRECT(K$5&"!N:N"),INDIRECT(K$5&"!L:L"),$E23,INDIRECT(K$5&"!K:K"),50)-SUMIFS(INDIRECT(K$5&"!N:N"),INDIRECT(K$5&"!L:L"),$E23,INDIRECT(K$5&"!K:K"),40) -> 0 | L23: =SUMIFS(INDIRECT(L$5&"!N:N"),INDIRECT(L$5&"!L:L"),$E23,INDIRECT(L$5&"!K:K"),50)-SUMIFS(INDIRECT(L$5&"!N:N"),INDIRECT(L$5&"!L:L"),$E23,INDIRECT(L$5&"!K:K"),40) -> 0 | M23: =SUMIFS(INDIRECT(M$5&"!N:N"),INDIRECT(M$5&"!L:L"),$E23,INDIRECT(M$5&"!K:K"),50)-SUMIFS(INDIRECT(M$5&"!N:N"),INDIRECT(M$5&"!L:L"),$E23,INDIRECT(M$5&"!K:K"),40) -> 0 | N23: =SUMIFS(INDIRECT(N$5&"!N:N"),INDIRECT(N$5&"!L:L"),$E23,INDIRECT(N$5&"!K:K"),50)-SUMIFS(INDIRECT(N$5&"!N:N"),INDIRECT(N$5&"!L:L"),$E23,INDIRECT(N$5&"!K:K"),40) -> 0 | O23: =SUMIFS(INDIRECT(O$5&"!N:N"),INDIRECT(O$5&"!L:L"),$E23,INDIRECT(O$5&"!K:K"),50)-SUMIFS(INDIRECT(O$5&"!N:N"),INDIRECT(O$5&"!L:L"),$E23,INDIRECT(O$5&"!K:K"),40) -> 0 | P23: =SUMIFS(INDIRECT(P$5&"!N:N"),INDIRECT(P$5&"!L:L"),$E23,INDIRECT(P$5&"!K:K"),50)-SUMIFS(INDIRECT(P$5&"!N:N"),INDIRECT(P$5&"!L:L"),$E23,INDIRECT(P$5&"!K:K"),40) -> 0 | ... T23: =SUMIFS(INDIRECT(T$5&"!N:N"),INDIRECT(T$5&"!L:L"),$E23,INDIRECT(T$5&"!K:K"),50)-SUMIFS(INDIRECT(T$5&"!N:N"),INDIRECT(T$5&"!L:L"),$E23,INDIRECT(T$5&"!K:K"),40) -> 0 | U23: {=INDEX($I23:$T23,$U$2)} -> 266.28 | X23: =U23+V23-W23 -> 266.28 | Z23: {=IFERROR(U23/OFFSET($H23,,MATCH($G$2,$H$5:$U$5,0)-2,,),"-")} -> 0.61174416 | AA23: {=U23-OFFSET($H23,,MATCH($G$2,$H$5:$U$5,0)-2,,)} -> -169 | AD23: {=IFERROR(U23/OFFSET($AT23,,MATCH($G$2,$AT$5:$BE$5,0)-1,,),"-")} -> - | AE23: {=U23-OFFSET($AT23,,MATCH($G$2,$AT$5:$BE$5,0)-1,,)} -> 266.28 | AL23: =SUM(I23:T23) -> 266.28 | AM23: {=INDEX($BG$8:$BQ$83,ROW()-7,MATCH($G$3,$BG$5:$BQ$5,0))} -> #N/A | AN23: =AL23-AM23 -> #N/A | AO23: =IFERROR(AL23/AM23,"") | AR23: =BQ23-AL23 -> -266.28 | AT23: 0 | AU23: 0 | AV23: 0 | AW23: 0 | AX23: 0 | AY23: 0 | AZ23: 0 | BA23: 0 | BB23: 0 | BC23: 0 | BD23: 0 | BE23: 0 | BG23: =SUM(AT23:AU23) -> 0 | BH23: =SUM(AT23:AV23) -> 0 | BI23: =SUM(AT23:AW23) -> 0 | BJ23: =SUM(AT23:AX23) -> 0 | BK23: =SUM(AT23:AY23) -> 0 | BL23: =SUM(AT23:AZ23) -> 0 | BM23: =SUM(AT23:BA23) -> 0 | BN23: =SUM(AT23:BB23) -> 0 | BO23: =SUM(AT23:BC23) -> 0 | BP23: =SUM(AT23:BD23) -> 0 | BQ23: =SUM(AT23:BE23) -> 0
A24: Labor | B24: Labor | C24: Labor_Indirect | D24: CC | E24: 621014 | F24: 62710104 | G24: Remuneration_Expat_Other_Indirect | H24: 0 | I24: =SUMIFS(INDIRECT(I$5&"!N:N"),INDIRECT(I$5&"!L:L"),$E24,INDIRECT(I$5&"!K:K"),50)-SUMIFS(INDIRECT(I$5&"!N:N"),INDIRECT(I$5&"!L:L"),$E24,INDIRECT(I$5&"!K:K"),40) -> 0 | J24: =SUMIFS(INDIRECT(J$5&"!N:N"),INDIRECT(J$5&"!L:L"),$E24,INDIRECT(J$5&"!K:K"),50)-SUMIFS(INDIRECT(J$5&"!N:N"),INDIRECT(J$5&"!L:L"),$E24,INDIRECT(J$5&"!K:K"),40) -> 0 | K24: =SUMIFS(INDIRECT(K$5&"!N:N"),INDIRECT(K$5&"!L:L"),$E24,INDIRECT(K$5&"!K:K"),50)-SUMIFS(INDIRECT(K$5&"!N:N"),INDIRECT(K$5&"!L:L"),$E24,INDIRECT(K$5&"!K:K"),40) -> 0 | L24: =SUMIFS(INDIRECT(L$5&"!N:N"),INDIRECT(L$5&"!L:L"),$E24,INDIRECT(L$5&"!K:K"),50)-SUMIFS(INDIRECT(L$5&"!N:N"),INDIRECT(L$5&"!L:L"),$E24,INDIRECT(L$5&"!K:K"),40) -> 0 | M24: =SUMIFS(INDIRECT(M$5&"!N:N"),INDIRECT(M$5&"!L:L"),$E24,INDIRECT(M$5&"!K:K"),50)-SUMIFS(INDIRECT(M$5&"!N:N"),INDIRECT(M$5&"!L:L"),$E24,INDIRECT(M$5&"!K:K"),40) -> 0 | N24: =SUMIFS(INDIRECT(N$5&"!N:N"),INDIRECT(N$5&"!L:L"),$E24,INDIRECT(N$5&"!K:K"),50)-SUMIFS(INDIRECT(N$5&"!N:N"),INDIRECT(N$5&"!L:L"),$E24,INDIRECT(N$5&"!K:K"),40) -> 0 | O24: =SUMIFS(INDIRECT(O$5&"!N:N"),INDIRECT(O$5&"!L:L"),$E24,INDIRECT(O$5&"!K:K"),50)-SUMIFS(INDIRECT(O$5&"!N:N"),INDIRECT(O$5&"!L:L"),$E24,INDIRECT(O$5&"!K:K"),40) -> 0 | P24: =SUMIFS(INDIRECT(P$5&"!N:N"),INDIRECT(P$5&"!L:L"),$E24,INDIRECT(P$5&"!K:K"),50)-SUMIFS(INDIRECT(P$5&"!N:N"),INDIRECT(P$5&"!L:L"),$E24,INDIRECT(P$5&"!K:K"),40) -> 0 | ... T24: =SUMIFS(INDIRECT(T$5&"!N:N"),INDIRECT(T$5&"!L:L"),$E24,INDIRECT(T$5&"!K:K"),50)-SUMIFS(INDIRECT(T$5&"!N:N"),INDIRECT(T$5&"!L:L"),$E24,INDIRECT(T$5&"!K:K"),40) -> 0 | U24: {=INDEX($I24:$T24,$U$2)} -> 0 | X24: =U24+V24-W24 -> 0 | Z24: {=IFERROR(U24/OFFSET($H24,,MATCH($G$2,$H$5:$U$5,0)-2,,),"-")} -> - | AA24: {=U24-OFFSET($H24,,MATCH($G$2,$H$5:$U$5,0)-2,,)} -> 0 | AD24: {=IFERROR(U24/OFFSET($AT24,,MATCH($G$2,$AT$5:$BE$5,0)-1,,),"-")} -> - | AE24: {=U24-OFFSET($AT24,,MATCH($G$2,$AT$5:$BE$5,0)-1,,)} -> 0 | AL24: =SUM(I24:T24) -> 0 | AM24: {=INDEX($BG$8:$BQ$83,ROW()-7,MATCH($G$3,$BG$5:$BQ$5,0))} -> #N/A | AN24: =AL24-AM24 -> #N/A | AO24: =IFERROR(AL24/AM24,"") | AR24: =BQ24-AL24 -> 0 | AT24: 0 | AU24: 0 | AV24: 0 | AW24: 0 | AX24: 0 | AY24: 0 | AZ24: 0 | BA24: 0 | BB24: 0 | BC24: 0 | BD24: 0 | BE24: 0 | BG24: =SUM(AT24:AU24) -> 0 | BH24: =SUM(AT24:AV24) -> 0 | BI24: =SUM(AT24:AW24) -> 0 | BJ24: =SUM(AT24:AX24) -> 0 | BK24: =SUM(AT24:AY24) -> 0 | BL24: =SUM(AT24:AZ24) -> 0 | BM24: =SUM(AT24:BA24) -> 0 | BN24: =SUM(AT24:BB24) -> 0 | BO24: =SUM(AT24:BC24) -> 0 | BP24: =SUM(AT24:BD24) -> 0 | BQ24: =SUM(AT24:BE24) -> 0
A25: Labor | B25: Labor | C25: Labor_Indirect | D25: CC | E25: 622011 | F25: 62710401 | G25: Bonus_Local_Indirect | H25: 16405.28 | I25: =SUMIFS(INDIRECT(I$5&"!N:N"),INDIRECT(I$5&"!L:L"),$E25,INDIRECT(I$5&"!K:K"),50)-SUMIFS(INDIRECT(I$5&"!N:N"),INDIRECT(I$5&"!L:L"),$E25,INDIRECT(I$5&"!K:K"),40) -> 33763.15 | J25: =SUMIFS(INDIRECT(J$5&"!N:N"),INDIRECT(J$5&"!L:L"),$E25,INDIRECT(J$5&"!K:K"),50)-SUMIFS(INDIRECT(J$5&"!N:N"),INDIRECT(J$5&"!L:L"),$E25,INDIRECT(J$5&"!K:K"),40) -> 0 | K25: =SUMIFS(INDIRECT(K$5&"!N:N"),INDIRECT(K$5&"!L:L"),$E25,INDIRECT(K$5&"!K:K"),50)-SUMIFS(INDIRECT(K$5&"!N:N"),INDIRECT(K$5&"!L:L"),$E25,INDIRECT(K$5&"!K:K"),40) -> 0 | L25: =SUMIFS(INDIRECT(L$5&"!N:N"),INDIRECT(L$5&"!L:L"),$E25,INDIRECT(L$5&"!K:K"),50)-SUMIFS(INDIRECT(L$5&"!N:N"),INDIRECT(L$5&"!L:L"),$E25,INDIRECT(L$5&"!K:K"),40) -> 0 | M25: =SUMIFS(INDIRECT(M$5&"!N:N"),INDIRECT(M$5&"!L:L"),$E25,INDIRECT(M$5&"!K:K"),50)-SUMIFS(INDIRECT(M$5&"!N:N"),INDIRECT(M$5&"!L:L"),$E25,INDIRECT(M$5&"!K:K"),40) -> 0 | N25: =SUMIFS(INDIRECT(N$5&"!N:N"),INDIRECT(N$5&"!L:L"),$E25,INDIRECT(N$5&"!K:K"),50)-SUMIFS(INDIRECT(N$5&"!N:N"),INDIRECT(N$5&"!L:L"),$E25,INDIRECT(N$5&"!K:K"),40) -> 0 | O25: =SUMIFS(INDIRECT(O$5&"!N:N"),INDIRECT(O$5&"!L:L"),$E25,INDIRECT(O$5&"!K:K"),50)-SUMIFS(INDIRECT(O$5&"!N:N"),INDIRECT(O$5&"!L:L"),$E25,INDIRECT(O$5&"!K:K"),40) -> 0 | P25: =SUMIFS(INDIRECT(P$5&"!N:N"),INDIRECT(P$5&"!L:L"),$E25,INDIRECT(P$5&"!K:K"),50)-SUMIFS(INDIRECT(P$5&"!N:N"),INDIRECT(P$5&"!L:L"),$E25,INDIRECT(P$5&"!K:K"),40) -> 0 | ... T25: =SUMIFS(INDIRECT(T$5&"!N:N"),INDIRECT(T$5&"!L:L"),$E25,INDIRECT(T$5&"!K:K"),50)-SUMIFS(INDIRECT(T$5&"!N:N"),INDIRECT(T$5&"!L:L"),$E25,INDIRECT(T$5&"!K:K"),40) -> 0 | U25: {=INDEX($I25:$T25,$U$2)} -> 33763.15 | X25: =U25+V25-W25 -> 33763.15 | Z25: {=IFERROR(U25/OFFSET($H25,,MATCH($G$2,$H$5:$U$5,0)-2,,),"-")} -> 2.0580661 | AA25: {=U25-OFFSET($H25,,MATCH($G$2,$H$5:$U$5,0)-2,,)} -> 17357.87 | AD25: {=IFERROR(U25/OFFSET($AT25,,MATCH($G$2,$AT$5:$BE$5,0)-1,,),"-")} -> 0.79790363 | AE25: {=U25-OFFSET($AT25,,MATCH($G$2,$AT$5:$BE$5,0)-1,,)} -> -8551.672 | AL25: =SUM(I25:T25) -> 33763.15 | AM25: {=INDEX($BG$8:$BQ$83,ROW()-7,MATCH($G$3,$BG$5:$BQ$5,0))} -> #N/A | AN25: =AL25-AM25 -> #N/A | AO25: =IFERROR(AL25/AM25,"") | AR25: =BQ25-AL25 -> 554248.51 | AT25: 42314.822 | AU25: 42410.131 | AV25: 42410.131 | AW25: 52531.59 | AX25: 44856.262 | AY25: 46489.818 | AZ25: 52441.538 | BA25: 44856.262 | BB25: 44856.262 | BC25: 52663.772 | BD25: 52678.081 | BE25: 69502.993 | BG25: =SUM(AT25:AU25) -> 84724.953 | BH25: =SUM(AT25:AV25) -> 127135.08 | BI25: =SUM(AT25:AW25) -> 179666.67 | BJ25: =SUM(AT25:AX25) -> 224522.94 | BK25: =SUM(AT25:AY25) -> 271012.75 | BL25: =SUM(AT25:AZ25) -> 323454.29 | BM25: =SUM(AT25:BA25) -> 368310.55 | BN25: =SUM(AT25:BB25) -> 413166.82 | BO25: =SUM(AT25:BC25) -> 465830.59 | BP25: =SUM(AT25:BD25) -> 518508.67 | BQ25: =SUM(AT25:BE25) -> 588011.66
A26: Labor | B26: Labor | C26: Labor_Indirect | D26: CC | E26: 622012 | F26: 62710402 | G26: Bonus_Expat_Indirect | H26: 6617.44 | I26: =SUMIFS(INDIRECT(I$5&"!N:N"),INDIRECT(I$5&"!L:L"),$E26,INDIRECT(I$5&"!K:K"),50)-SUMIFS(INDIRECT(I$5&"!N:N"),INDIRECT(I$5&"!L:L"),$E26,INDIRECT(I$5&"!K:K"),40) -> 4436.81 | J26: =SUMIFS(INDIRECT(J$5&"!N:N"),INDIRECT(J$5&"!L:L"),$E26,INDIRECT(J$5&"!K:K"),50)-SUMIFS(INDIRECT(J$5&"!N:N"),INDIRECT(J$5&"!L:L"),$E26,INDIRECT(J$5&"!K:K"),40) -> 0 | K26: =SUMIFS(INDIRECT(K$5&"!N:N"),INDIRECT(K$5&"!L:L"),$E26,INDIRECT(K$5&"!K:K"),50)-SUMIFS(INDIRECT(K$5&"!N:N"),INDIRECT(K$5&"!L:L"),$E26,INDIRECT(K$5&"!K:K"),40) -> 0 | L26: =SUMIFS(INDIRECT(L$5&"!N:N"),INDIRECT(L$5&"!L:L"),$E26,INDIRECT(L$5&"!K:K"),50)-SUMIFS(INDIRECT(L$5&"!N:N"),INDIRECT(L$5&"!L:L"),$E26,INDIRECT(L$5&"!K:K"),40) -> 0 | M26: =SUMIFS(INDIRECT(M$5&"!N:N"),INDIRECT(M$5&"!L:L"),$E26,INDIRECT(M$5&"!K:K"),50)-SUMIFS(INDIRECT(M$5&"!N:N"),INDIRECT(M$5&"!L:L"),$E26,INDIRECT(M$5&"!K:K"),40) -> 0 | N26: =SUMIFS(INDIRECT(N$5&"!N:N"),INDIRECT(N$5&"!L:L"),$E26,INDIRECT(N$5&"!K:K"),50)-SUMIFS(INDIRECT(N$5&"!N:N"),INDIRECT(N$5&"!L:L"),$E26,INDIRECT(N$5&"!K:K"),40) -> 0 | O26: =SUMIFS(INDIRECT(O$5&"!N:N"),INDIRECT(O$5&"!L:L"),$E26,INDIRECT(O$5&"!K:K"),50)-SUMIFS(INDIRECT(O$5&"!N:N"),INDIRECT(O$5&"!L:L"),$E26,INDIRECT(O$5&"!K:K"),40) -> 0 | P26: =SUMIFS(INDIRECT(P$5&"!N:N"),INDIRECT(P$5&"!L:L"),$E26,INDIRECT(P$5&"!K:K"),50)-SUMIFS(INDIRECT(P$5&"!N:N"),INDIRECT(P$5&"!L:L"),$E26,INDIRECT(P$5&"!K:K"),40) -> 0 | ... T26: =SUMIFS(INDIRECT(T$5&"!N:N"),INDIRECT(T$5&"!L:L"),$E26,INDIRECT(T$5&"!K:K"),50)-SUMIFS(INDIRECT(T$5&"!N:N"),INDIRECT(T$5&"!L:L"),$E26,INDIRECT(T$5&"!K:K"),40) -> 0 | U26: {=INDEX($I26:$T26,$U$2)} -> 4436.81 | X26: =U26+V26-W26 -> 4436.81 | Z26: {=IFERROR(U26/OFFSET($H26,,MATCH($G$2,$H$5:$U$5,0)-2,,),"-")} -> 0.67047227 | AA26: {=U26-OFFSET($H26,,MATCH($G$2,$H$5:$U$5,0)-2,,)} -> -2180.63 | AD26: {=IFERROR(U26/OFFSET($AT26,,MATCH($G$2,$AT$5:$BE$5,0)-1,,),"-")} -> 0.64354541 | AE26: {=U26-OFFSET($AT26,,MATCH($G$2,$AT$5:$BE$5,0)-1,,)} -> -2457.5131 | AL26: =SUM(I26:T26) -> 4436.81 | AM26: {=INDEX($BG$8:$BQ$83,ROW()-7,MATCH($G$3,$BG$5:$BQ$5,0))} -> #N/A | AN26: =AL26-AM26 -> #N/A | AO26: =IFERROR(AL26/AM26,"") | AR26: =BQ26-AL26 -> 81425.928 | AT26: 6894.3231 | AU26: 6894.3231 | AV26: 6894.3231 | AW26: 10025.185 | AX26: 6894.3231 | AY26: 6894.3231 | AZ26: 6894.3231 | BA26: 6894.3231 | BB26: 6894.3231 | BC26: 6894.3231 | BD26: 6894.3231 | BE26: 6894.3231 | BG26: =SUM(AT26:AU26) -> 13788.646 | BH26: =SUM(AT26:AV26) -> 20682.969 | BI26: =SUM(AT26:AW26) -> 30708.154 | BJ26: =SUM(AT26:AX26) -> 37602.477 | BK26: =SUM(AT26:AY26) -> 44496.8 | BL26: =SUM(AT26:AZ26) -> 51391.123 | BM26: =SUM(AT26:BA26) -> 58285.446 | BN26: =SUM(AT26:BB26) -> 65179.769 | BO26: =SUM(AT26:BC26) -> 72074.092 | BP26: =SUM(AT26:BD26) -> 78968.415 | BQ26: =SUM(AT26:BE26) -> 85862.738
A27: Labor | B27: Labor | C27: Labor_Indirect | D27: CC | E27: 624020 | F27: 62712000 | G27: LU fee_Local_Indirect | H27: 3354.32 | I27: =SUMIFS(INDIRECT(I$5&"!N:N"),INDIRECT(I$5&"!L:L"),$E27,INDIRECT(I$5&"!K:K"),50)-SUMIFS(INDIRECT(I$5&"!N:N"),INDIRECT(I$5&"!L:L"),$E27,INDIRECT(I$5&"!K:K"),40) -> 3339.19 | J27: =SUMIFS(INDIRECT(J$5&"!N:N"),INDIRECT(J$5&"!L:L"),$E27,INDIRECT(J$5&"!K:K"),50)-SUMIFS(INDIRECT(J$5&"!N:N"),INDIRECT(J$5&"!L:L"),$E27,INDIRECT(J$5&"!K:K"),40) -> 0 | K27: =SUMIFS(INDIRECT(K$5&"!N:N"),INDIRECT(K$5&"!L:L"),$E27,INDIRECT(K$5&"!K:K"),50)-SUMIFS(INDIRECT(K$5&"!N:N"),INDIRECT(K$5&"!L:L"),$E27,INDIRECT(K$5&"!K:K"),40) -> 0 | L27: =SUMIFS(INDIRECT(L$5&"!N:N"),INDIRECT(L$5&"!L:L"),$E27,INDIRECT(L$5&"!K:K"),50)-SUMIFS(INDIRECT(L$5&"!N:N"),INDIRECT(L$5&"!L:L"),$E27,INDIRECT(L$5&"!K:K"),40) -> 0 | M27: =SUMIFS(INDIRECT(M$5&"!N:N"),INDIRECT(M$5&"!L:L"),$E27,INDIRECT(M$5&"!K:K"),50)-SUMIFS(INDIRECT(M$5&"!N:N"),INDIRECT(M$5&"!L:L"),$E27,INDIRECT(M$5&"!K:K"),40) -> 0 | N27: =SUMIFS(INDIRECT(N$5&"!N:N"),INDIRECT(N$5&"!L:L"),$E27,INDIRECT(N$5&"!K:K"),50)-SUMIFS(INDIRECT(N$5&"!N:N"),INDIRECT(N$5&"!L:L"),$E27,INDIRECT(N$5&"!K:K"),40) -> 0 | O27: =SUMIFS(INDIRECT(O$5&"!N:N"),INDIRECT(O$5&"!L:L"),$E27,INDIRECT(O$5&"!K:K"),50)-SUMIFS(INDIRECT(O$5&"!N:N"),INDIRECT(O$5&"!L:L"),$E27,INDIRECT(O$5&"!K:K"),40) -> 0 | P27: =SUMIFS(INDIRECT(P$5&"!N:N"),INDIRECT(P$5&"!L:L"),$E27,INDIRECT(P$5&"!K:K"),50)-SUMIFS(INDIRECT(P$5&"!N:N"),INDIRECT(P$5&"!L:L"),$E27,INDIRECT(P$5&"!K:K"),40) -> 0 | ... T27: =SUMIFS(INDIRECT(T$5&"!N:N"),INDIRECT(T$5&"!L:L"),$E27,INDIRECT(T$5&"!K:K"),50)-SUMIFS(INDIRECT(T$5&"!N:N"),INDIRECT(T$5&"!L:L"),$E27,INDIRECT(T$5&"!K:K"),40) -> 0 | U27: {=INDEX($I27:$T27,$U$2)} -> 3339.19 | X27: =U27+V27-W27 -> 3339.19 | Z27: {=IFERROR(U27/OFFSET($H27,,MATCH($G$2,$H$5:$U$5,0)-2,,),"-")} -> 0.9954894 | AA27: {=U27-OFFSET($H27,,MATCH($G$2,$H$5:$U$5,0)-2,,)} -> -15.13 | AD27: {=IFERROR(U27/OFFSET($AT27,,MATCH($G$2,$AT$5:$BE$5,0)-1,,),"-")} -> 0.98580588 | AE27: {=U27-OFFSET($AT27,,MATCH($G$2,$AT$5:$BE$5,0)-1,,)} -> -48.079315 | AL27: =SUM(I27:T27) -> 3339.19 | AM27: {=INDEX($BG$8:$BQ$83,ROW()-7,MATCH($G$3,$BG$5:$BQ$5,0))} -> #N/A | AN27: =AL27-AM27 -> #N/A | AO27: =IFERROR(AL27/AM27,"") | AR27: =BQ27-AL27 -> 39356.196 | AT27: 3387.2693 | AU27: 3399.4364 | AV27: 3399.4364 | AW27: 3595.6168 | AX27: 3583.2972 | AY27: 3583.2972 | AZ27: 3612.6729 | BA27: 3612.6729 | BB27: 3612.6729 | BC27: 3636.3379 | BD27: 3636.3379 | BE27: 3636.3379 | BG27: =SUM(AT27:AU27) -> 6786.7057 | BH27: =SUM(AT27:AV27) -> 10186.142 | BI27: =SUM(AT27:AW27) -> 13781.759 | BJ27: =SUM(AT27:AX27) -> 17365.056 | BK27: =SUM(AT27:AY27) -> 20948.353 | BL27: =SUM(AT27:AZ27) -> 24561.026 | BM27: =SUM(AT27:BA27) -> 28173.699 | BN27: =SUM(AT27:BB27) -> 31786.372 | BO27: =SUM(AT27:BC27) -> 35422.71 | BP27: =SUM(AT27:BD27) -> 39059.048 | BQ27: =SUM(AT27:BE27) -> 42695.386
A28: Labor | B28: Labor | C28: Labor_Indirect | D28: CC | E28: 624021 | F28: 62713100 | G28: Social insurance_Indirect | H28: 23480.33 | I28: =SUMIFS(INDIRECT(I$5&"!N:N"),INDIRECT(I$5&"!L:L"),$E28,INDIRECT(I$5&"!K:K"),50)-SUMIFS(INDIRECT(I$5&"!N:N"),INDIRECT(I$5&"!L:L"),$E28,INDIRECT(I$5&"!K:K"),40) -> 23305.63 | J28: =SUMIFS(INDIRECT(J$5&"!N:N"),INDIRECT(J$5&"!L:L"),$E28,INDIRECT(J$5&"!K:K"),50)-SUMIFS(INDIRECT(J$5&"!N:N"),INDIRECT(J$5&"!L:L"),$E28,INDIRECT(J$5&"!K:K"),40) -> 0 | K28: =SUMIFS(INDIRECT(K$5&"!N:N"),INDIRECT(K$5&"!L:L"),$E28,INDIRECT(K$5&"!K:K"),50)-SUMIFS(INDIRECT(K$5&"!N:N"),INDIRECT(K$5&"!L:L"),$E28,INDIRECT(K$5&"!K:K"),40) -> 0 | L28: =SUMIFS(INDIRECT(L$5&"!N:N"),INDIRECT(L$5&"!L:L"),$E28,INDIRECT(L$5&"!K:K"),50)-SUMIFS(INDIRECT(L$5&"!N:N"),INDIRECT(L$5&"!L:L"),$E28,INDIRECT(L$5&"!K:K"),40) -> 0 | M28: =SUMIFS(INDIRECT(M$5&"!N:N"),INDIRECT(M$5&"!L:L"),$E28,INDIRECT(M$5&"!K:K"),50)-SUMIFS(INDIRECT(M$5&"!N:N"),INDIRECT(M$5&"!L:L"),$E28,INDIRECT(M$5&"!K:K"),40) -> 0 | N28: =SUMIFS(INDIRECT(N$5&"!N:N"),INDIRECT(N$5&"!L:L"),$E28,INDIRECT(N$5&"!K:K"),50)-SUMIFS(INDIRECT(N$5&"!N:N"),INDIRECT(N$5&"!L:L"),$E28,INDIRECT(N$5&"!K:K"),40) -> 0 | O28: =SUMIFS(INDIRECT(O$5&"!N:N"),INDIRECT(O$5&"!L:L"),$E28,INDIRECT(O$5&"!K:K"),50)-SUMIFS(INDIRECT(O$5&"!N:N"),INDIRECT(O$5&"!L:L"),$E28,INDIRECT(O$5&"!K:K"),40) -> 0 | P28: =SUMIFS(INDIRECT(P$5&"!N:N"),INDIRECT(P$5&"!L:L"),$E28,INDIRECT(P$5&"!K:K"),50)-SUMIFS(INDIRECT(P$5&"!N:N"),INDIRECT(P$5&"!L:L"),$E28,INDIRECT(P$5&"!K:K"),40) -> 0 | ... T28: =SUMIFS(INDIRECT(T$5&"!N:N"),INDIRECT(T$5&"!L:L"),$E28,INDIRECT(T$5&"!K:K"),50)-SUMIFS(INDIRECT(T$5&"!N:N"),INDIRECT(T$5&"!L:L"),$E28,INDIRECT(T$5&"!K:K"),40) -> 0 | U28: {=INDEX($I28:$T28,$U$2)} -> 23305.63 | X28: =U28+V28-W28 -> 23305.63 | Z28: {=IFERROR(U28/OFFSET($H28,,MATCH($G$2,$H$5:$U$5,0)-2,,),"-")} -> 0.99255973 | AA28: {=U28-OFFSET($H28,,MATCH($G$2,$H$5:$U$5,0)-2,,)} -> -174.7 | AD28: {=IFERROR(U28/OFFSET($AT28,,MATCH($G$2,$AT$5:$BE$5,0)-1,,),"-")} -> 0.98278085 | AE28: {=U28-OFFSET($AT28,,MATCH($G$2,$AT$5:$BE$5,0)-1,,)} -> -408.33425 | AL28: =SUM(I28:T28) -> 23305.63 | AM28: {=INDEX($BG$8:$BQ$83,ROW()-7,MATCH($G$3,$BG$5:$BQ$5,0))} -> #N/A | AN28: =AL28-AM28 -> #N/A | AO28: =IFERROR(AL28/AM28,"") | AR28: =BQ28-AL28 -> 275546.16 | AT28: 23713.964 | AU28: 23794.484 | AV28: 23794.484 | AW28: 25167.604 | AX28: 25081.367 | AY28: 25081.367 | AZ28: 25286.997 | BA28: 25286.997 | BB28: 25286.997 | BC28: 25452.509 | BD28: 25452.509 | BE28: 25452.509 | BG28: =SUM(AT28:AU28) -> 47508.448 | BH28: =SUM(AT28:AV28) -> 71302.932 | BI28: =SUM(AT28:AW28) -> 96470.536 | BJ28: =SUM(AT28:AX28) -> 121551.9 | BK28: =SUM(AT28:AY28) -> 146633.27 | BL28: =SUM(AT28:AZ28) -> 171920.27 | BM28: =SUM(AT28:BA28) -> 197207.26 | BN28: =SUM(AT28:BB28) -> 222494.26 | BO28: =SUM(AT28:BC28) -> 247946.77 | BP28: =SUM(AT28:BD28) -> 273399.28 | BQ28: =SUM(AT28:BE28) -> 298851.79
A29: Labor | B29: Labor | C29: Labor_Indirect | D29: CC | E29: 624024 | F29: 62713120 | G29: Illness & maternity insurance_Indirect | H29: 5031.51 | I29: =SUMIFS(INDIRECT(I$5&"!N:N"),INDIRECT(I$5&"!L:L"),$E29,INDIRECT(I$5&"!K:K"),50)-SUMIFS(INDIRECT(I$5&"!N:N"),INDIRECT(I$5&"!L:L"),$E29,INDIRECT(I$5&"!K:K"),40) -> 4994.07 | J29: =SUMIFS(INDIRECT(J$5&"!N:N"),INDIRECT(J$5&"!L:L"),$E29,INDIRECT(J$5&"!K:K"),50)-SUMIFS(INDIRECT(J$5&"!N:N"),INDIRECT(J$5&"!L:L"),$E29,INDIRECT(J$5&"!K:K"),40) -> 0 | K29: =SUMIFS(INDIRECT(K$5&"!N:N"),INDIRECT(K$5&"!L:L"),$E29,INDIRECT(K$5&"!K:K"),50)-SUMIFS(INDIRECT(K$5&"!N:N"),INDIRECT(K$5&"!L:L"),$E29,INDIRECT(K$5&"!K:K"),40) -> 0 | L29: =SUMIFS(INDIRECT(L$5&"!N:N"),INDIRECT(L$5&"!L:L"),$E29,INDIRECT(L$5&"!K:K"),50)-SUMIFS(INDIRECT(L$5&"!N:N"),INDIRECT(L$5&"!L:L"),$E29,INDIRECT(L$5&"!K:K"),40) -> 0 | M29: =SUMIFS(INDIRECT(M$5&"!N:N"),INDIRECT(M$5&"!L:L"),$E29,INDIRECT(M$5&"!K:K"),50)-SUMIFS(INDIRECT(M$5&"!N:N"),INDIRECT(M$5&"!L:L"),$E29,INDIRECT(M$5&"!K:K"),40) -> 0 | N29: =SUMIFS(INDIRECT(N$5&"!N:N"),INDIRECT(N$5&"!L:L"),$E29,INDIRECT(N$5&"!K:K"),50)-SUMIFS(INDIRECT(N$5&"!N:N"),INDIRECT(N$5&"!L:L"),$E29,INDIRECT(N$5&"!K:K"),40) -> 0 | O29: =SUMIFS(INDIRECT(O$5&"!N:N"),INDIRECT(O$5&"!L:L"),$E29,INDIRECT(O$5&"!K:K"),50)-SUMIFS(INDIRECT(O$5&"!N:N"),INDIRECT(O$5&"!L:L"),$E29,INDIRECT(O$5&"!K:K"),40) -> 0 | P29: =SUMIFS(INDIRECT(P$5&"!N:N"),INDIRECT(P$5&"!L:L"),$E29,INDIRECT(P$5&"!K:K"),50)-SUMIFS(INDIRECT(P$5&"!N:N"),INDIRECT(P$5&"!L:L"),$E29,INDIRECT(P$5&"!K:K"),40) -> 0 | ... T29: =SUMIFS(INDIRECT(T$5&"!N:N"),INDIRECT(T$5&"!L:L"),$E29,INDIRECT(T$5&"!K:K"),50)-SUMIFS(INDIRECT(T$5&"!N:N"),INDIRECT(T$5&"!L:L"),$E29,INDIRECT(T$5&"!K:K"),40) -> 0 | U29: {=INDEX($I29:$T29,$U$2)} -> 4994.07 | X29: =U29+V29-W29 -> 4994.07 | Z29: {=IFERROR(U29/OFFSET($H29,,MATCH($G$2,$H$5:$U$5,0)-2,,),"-")} -> 0.99255889 | AA29: {=U29-OFFSET($H29,,MATCH($G$2,$H$5:$U$5,0)-2,,)} -> -37.44 | AD29: {=IFERROR(U29/OFFSET($AT29,,MATCH($G$2,$AT$5:$BE$5,0)-1,,),"-")} -> 0.98278212 | AE29: {=U29-OFFSET($AT29,,MATCH($G$2,$AT$5:$BE$5,0)-1,,)} -> -87.493768 | AL29: =SUM(I29:T29) -> 4994.07 | AM29: {=INDEX($BG$8:$BQ$83,ROW()-7,MATCH($G$3,$BG$5:$BQ$5,0))} -> #N/A | AN29: =AL29-AM29 -> #N/A | AO29: =IFERROR(AL29/AM29,"") | AR29: =BQ29-AL29 -> 59045.599 | AT29: 5081.5638 | AU29: 5098.818 | AV29: 5098.818 | AW29: 5393.0581 | AX29: 5374.5786 | AY29: 5374.5786 | AZ29: 5418.6422 | BA29: 5418.6422 | BB29: 5418.6422 | BC29: 5454.109 | BD29: 5454.109 | BE29: 5454.109 | BG29: =SUM(AT29:AU29) -> 10180.382 | BH29: =SUM(AT29:AV29) -> 15279.2 | BI29: =SUM(AT29:AW29) -> 20672.258 | BJ29: =SUM(AT29:AX29) -> 26046.836 | BK29: =SUM(AT29:AY29) -> 31421.415 | BL29: =SUM(AT29:AZ29) -> 36840.057 | BM29: =SUM(AT29:BA29) -> 42258.699 | BN29: =SUM(AT29:BB29) -> 47677.342 | BO29: =SUM(AT29:BC29) -> 53131.451 | BP29: =SUM(AT29:BD29) -> 58585.56 | BQ29: =SUM(AT29:BE29) -> 64039.669
A30: Labor | B30: Labor | C30: Labor_Indirect | D30: CC | E30: 624025 | F30: 62713300 | G30: Occupational insurance_Indirect | H30: 838.58 | I30: =SUMIFS(INDIRECT(I$5&"!N:N"),INDIRECT(I$5&"!L:L"),$E30,INDIRECT(I$5&"!K:K"),50)-SUMIFS(INDIRECT(I$5&"!N:N"),INDIRECT(I$5&"!L:L"),$E30,INDIRECT(I$5&"!K:K"),40) -> 832.36 | J30: =SUMIFS(INDIRECT(J$5&"!N:N"),INDIRECT(J$5&"!L:L"),$E30,INDIRECT(J$5&"!K:K"),50)-SUMIFS(INDIRECT(J$5&"!N:N"),INDIRECT(J$5&"!L:L"),$E30,INDIRECT(J$5&"!K:K"),40) -> 0 | K30: =SUMIFS(INDIRECT(K$5&"!N:N"),INDIRECT(K$5&"!L:L"),$E30,INDIRECT(K$5&"!K:K"),50)-SUMIFS(INDIRECT(K$5&"!N:N"),INDIRECT(K$5&"!L:L"),$E30,INDIRECT(K$5&"!K:K"),40) -> 0 | L30: =SUMIFS(INDIRECT(L$5&"!N:N"),INDIRECT(L$5&"!L:L"),$E30,INDIRECT(L$5&"!K:K"),50)-SUMIFS(INDIRECT(L$5&"!N:N"),INDIRECT(L$5&"!L:L"),$E30,INDIRECT(L$5&"!K:K"),40) -> 0 | M30: =SUMIFS(INDIRECT(M$5&"!N:N"),INDIRECT(M$5&"!L:L"),$E30,INDIRECT(M$5&"!K:K"),50)-SUMIFS(INDIRECT(M$5&"!N:N"),INDIRECT(M$5&"!L:L"),$E30,INDIRECT(M$5&"!K:K"),40) -> 0 | N30: =SUMIFS(INDIRECT(N$5&"!N:N"),INDIRECT(N$5&"!L:L"),$E30,INDIRECT(N$5&"!K:K"),50)-SUMIFS(INDIRECT(N$5&"!N:N"),INDIRECT(N$5&"!L:L"),$E30,INDIRECT(N$5&"!K:K"),40) -> 0 | O30: =SUMIFS(INDIRECT(O$5&"!N:N"),INDIRECT(O$5&"!L:L"),$E30,INDIRECT(O$5&"!K:K"),50)-SUMIFS(INDIRECT(O$5&"!N:N"),INDIRECT(O$5&"!L:L"),$E30,INDIRECT(O$5&"!K:K"),40) -> 0 | P30: =SUMIFS(INDIRECT(P$5&"!N:N"),INDIRECT(P$5&"!L:L"),$E30,INDIRECT(P$5&"!K:K"),50)-SUMIFS(INDIRECT(P$5&"!N:N"),INDIRECT(P$5&"!L:L"),$E30,INDIRECT(P$5&"!K:K"),40) -> 0 | ... T30: =SUMIFS(INDIRECT(T$5&"!N:N"),INDIRECT(T$5&"!L:L"),$E30,INDIRECT(T$5&"!K:K"),50)-SUMIFS(INDIRECT(T$5&"!N:N"),INDIRECT(T$5&"!L:L"),$E30,INDIRECT(T$5&"!K:K"),40) -> 0 | U30: {=INDEX($I30:$T30,$U$2)} -> 832.36 | X30: =U30+V30-W30 -> 832.36 | Z30: {=IFERROR(U30/OFFSET($H30,,MATCH($G$2,$H$5:$U$5,0)-2,,),"-")} -> 0.9925827 | AA30: {=U30-OFFSET($H30,,MATCH($G$2,$H$5:$U$5,0)-2,,)} -> -6.22 | AD30: {=IFERROR(U30/OFFSET($AT30,,MATCH($G$2,$AT$5:$BE$5,0)-1,,),"-")} -> 0.98292745 | AE30: {=U30-OFFSET($AT30,,MATCH($G$2,$AT$5:$BE$5,0)-1,,)} -> -14.457329 | AL30: =SUM(I30:T30) -> 832.36 | AM30: {=INDEX($BG$8:$BQ$83,ROW()-7,MATCH($G$3,$BG$5:$BQ$5,0))} -> #N/A | AN30: =AL30-AM30 -> #N/A | AO30: =IFERROR(AL30/AM30,"") | AR30: =BQ30-AL30 -> 9840.0373 | AT30: 846.81733 | AU30: 849.85909 | AV30: 849.85909 | AW30: 898.17962 | AX30: 895.0997 | AY30: 895.82429 | AZ30: 903.16824 | BA30: 903.16824 | BB30: 903.16824 | BC30: 909.08447 | BD30: 909.08447 | BE30: 909.08447 | BG30: =SUM(AT30:AU30) -> 1696.6764 | BH30: =SUM(AT30:AV30) -> 2546.5355 | BI30: =SUM(AT30:AW30) -> 3444.7151 | BJ30: =SUM(AT30:AX30) -> 4339.8148 | BK30: =SUM(AT30:AY30) -> 5235.6391 | BL30: =SUM(AT30:AZ30) -> 6138.8074 | BM30: =SUM(AT30:BA30) -> 7041.9756 | BN30: =SUM(AT30:BB30) -> 7945.1438 | BO30: =SUM(AT30:BC30) -> 8854.2283 | BP30: =SUM(AT30:BD30) -> 9763.3128 | BQ30: =SUM(AT30:BE30) -> 10672.397
A31: Labor | B31: Labor | C31: Labor_Indirect | D31: CC | E31: 624023 | F31: 62714000 | G31: Health insurance_Indirect | H31: 5031.51 | I31: =SUMIFS(INDIRECT(I$5&"!N:N"),INDIRECT(I$5&"!L:L"),$E31,INDIRECT(I$5&"!K:K"),50)-SUMIFS(INDIRECT(I$5&"!N:N"),INDIRECT(I$5&"!L:L"),$E31,INDIRECT(I$5&"!K:K"),40) -> 5011.38 | J31: =SUMIFS(INDIRECT(J$5&"!N:N"),INDIRECT(J$5&"!L:L"),$E31,INDIRECT(J$5&"!K:K"),50)-SUMIFS(INDIRECT(J$5&"!N:N"),INDIRECT(J$5&"!L:L"),$E31,INDIRECT(J$5&"!K:K"),40) -> 0 | K31: =SUMIFS(INDIRECT(K$5&"!N:N"),INDIRECT(K$5&"!L:L"),$E31,INDIRECT(K$5&"!K:K"),50)-SUMIFS(INDIRECT(K$5&"!N:N"),INDIRECT(K$5&"!L:L"),$E31,INDIRECT(K$5&"!K:K"),40) -> 0 | L31: =SUMIFS(INDIRECT(L$5&"!N:N"),INDIRECT(L$5&"!L:L"),$E31,INDIRECT(L$5&"!K:K"),50)-SUMIFS(INDIRECT(L$5&"!N:N"),INDIRECT(L$5&"!L:L"),$E31,INDIRECT(L$5&"!K:K"),40) -> 0 | M31: =SUMIFS(INDIRECT(M$5&"!N:N"),INDIRECT(M$5&"!L:L"),$E31,INDIRECT(M$5&"!K:K"),50)-SUMIFS(INDIRECT(M$5&"!N:N"),INDIRECT(M$5&"!L:L"),$E31,INDIRECT(M$5&"!K:K"),40) -> 0 | N31: =SUMIFS(INDIRECT(N$5&"!N:N"),INDIRECT(N$5&"!L:L"),$E31,INDIRECT(N$5&"!K:K"),50)-SUMIFS(INDIRECT(N$5&"!N:N"),INDIRECT(N$5&"!L:L"),$E31,INDIRECT(N$5&"!K:K"),40) -> 0 | O31: =SUMIFS(INDIRECT(O$5&"!N:N"),INDIRECT(O$5&"!L:L"),$E31,INDIRECT(O$5&"!K:K"),50)-SUMIFS(INDIRECT(O$5&"!N:N"),INDIRECT(O$5&"!L:L"),$E31,INDIRECT(O$5&"!K:K"),40) -> 0 | P31: =SUMIFS(INDIRECT(P$5&"!N:N"),INDIRECT(P$5&"!L:L"),$E31,INDIRECT(P$5&"!K:K"),50)-SUMIFS(INDIRECT(P$5&"!N:N"),INDIRECT(P$5&"!L:L"),$E31,INDIRECT(P$5&"!K:K"),40) -> 0 | ... T31: =SUMIFS(INDIRECT(T$5&"!N:N"),INDIRECT(T$5&"!L:L"),$E31,INDIRECT(T$5&"!K:K"),50)-SUMIFS(INDIRECT(T$5&"!N:N"),INDIRECT(T$5&"!L:L"),$E31,INDIRECT(T$5&"!K:K"),40) -> 0 | U31: {=INDEX($I31:$T31,$U$2)} -> 5011.38 | X31: =U31+V31-W31 -> 5011.38 | Z31: {=IFERROR(U31/OFFSET($H31,,MATCH($G$2,$H$5:$U$5,0)-2,,),"-")} -> 0.99599921 | AA31: {=U31-OFFSET($H31,,MATCH($G$2,$H$5:$U$5,0)-2,,)} -> -20.13 | AD31: {=IFERROR(U31/OFFSET($AT31,,MATCH($G$2,$AT$5:$BE$5,0)-1,,),"-")} -> 0.98631661 | AE31: {=U31-OFFSET($AT31,,MATCH($G$2,$AT$5:$BE$5,0)-1,,)} -> -69.523973 | AL31: =SUM(I31:T31) -> 5011.38 | AM31: {=INDEX($BG$8:$BQ$83,ROW()-7,MATCH($G$3,$BG$5:$BQ$5,0))} -> #N/A | AN31: =AL31-AM31 -> #N/A | AO31: =IFERROR(AL31/AM31,"") | AR31: =BQ31-AL31 -> 59031.699 | AT31: 5080.904 | AU31: 5099.1546 | AV31: 5099.1546 | AW31: 5393.4253 | AX31: 5374.9458 | AY31: 5374.9458 | AZ31: 5419.0094 | BA31: 5419.0094 | BB31: 5419.0094 | BC31: 5454.5068 | BD31: 5454.5068 | BE31: 5454.5068 | BG31: =SUM(AT31:AU31) -> 10180.059 | BH31: =SUM(AT31:AV31) -> 15279.213 | BI31: =SUM(AT31:AW31) -> 20672.638 | BJ31: =SUM(AT31:AX31) -> 26047.584 | BK31: =SUM(AT31:AY31) -> 31422.53 | BL31: =SUM(AT31:AZ31) -> 36841.539 | BM31: =SUM(AT31:BA31) -> 42260.549 | BN31: =SUM(AT31:BB31) -> 47679.558 | BO31: =SUM(AT31:BC31) -> 53134.065 | BP31: =SUM(AT31:BD31) -> 58588.572 | BQ31: =SUM(AT31:BE31) -> 64043.079
A32: Labor | B32: Labor | C32: Labor_Indirect | D32: CC | E32: 624101 | F32: 62714100 | G32: Other insurance_Indirect | H32: 324.52 | I32: =SUMIFS(INDIRECT(I$5&"!N:N"),INDIRECT(I$5&"!L:L"),$E32,INDIRECT(I$5&"!K:K"),50)-SUMIFS(INDIRECT(I$5&"!N:N"),INDIRECT(I$5&"!L:L"),$E32,INDIRECT(I$5&"!K:K"),40) -> 256.44 | J32: =SUMIFS(INDIRECT(J$5&"!N:N"),INDIRECT(J$5&"!L:L"),$E32,INDIRECT(J$5&"!K:K"),50)-SUMIFS(INDIRECT(J$5&"!N:N"),INDIRECT(J$5&"!L:L"),$E32,INDIRECT(J$5&"!K:K"),40) -> 0 | K32: =SUMIFS(INDIRECT(K$5&"!N:N"),INDIRECT(K$5&"!L:L"),$E32,INDIRECT(K$5&"!K:K"),50)-SUMIFS(INDIRECT(K$5&"!N:N"),INDIRECT(K$5&"!L:L"),$E32,INDIRECT(K$5&"!K:K"),40) -> 0 | L32: =SUMIFS(INDIRECT(L$5&"!N:N"),INDIRECT(L$5&"!L:L"),$E32,INDIRECT(L$5&"!K:K"),50)-SUMIFS(INDIRECT(L$5&"!N:N"),INDIRECT(L$5&"!L:L"),$E32,INDIRECT(L$5&"!K:K"),40) -> 0 | M32: =SUMIFS(INDIRECT(M$5&"!N:N"),INDIRECT(M$5&"!L:L"),$E32,INDIRECT(M$5&"!K:K"),50)-SUMIFS(INDIRECT(M$5&"!N:N"),INDIRECT(M$5&"!L:L"),$E32,INDIRECT(M$5&"!K:K"),40) -> 0 | N32: =SUMIFS(INDIRECT(N$5&"!N:N"),INDIRECT(N$5&"!L:L"),$E32,INDIRECT(N$5&"!K:K"),50)-SUMIFS(INDIRECT(N$5&"!N:N"),INDIRECT(N$5&"!L:L"),$E32,INDIRECT(N$5&"!K:K"),40) -> 0 | O32: =SUMIFS(INDIRECT(O$5&"!N:N"),INDIRECT(O$5&"!L:L"),$E32,INDIRECT(O$5&"!K:K"),50)-SUMIFS(INDIRECT(O$5&"!N:N"),INDIRECT(O$5&"!L:L"),$E32,INDIRECT(O$5&"!K:K"),40) -> 0 | P32: =SUMIFS(INDIRECT(P$5&"!N:N"),INDIRECT(P$5&"!L:L"),$E32,INDIRECT(P$5&"!K:K"),50)-SUMIFS(INDIRECT(P$5&"!N:N"),INDIRECT(P$5&"!L:L"),$E32,INDIRECT(P$5&"!K:K"),40) -> 0 | ... T32: =SUMIFS(INDIRECT(T$5&"!N:N"),INDIRECT(T$5&"!L:L"),$E32,INDIRECT(T$5&"!K:K"),50)-SUMIFS(INDIRECT(T$5&"!N:N"),INDIRECT(T$5&"!L:L"),$E32,INDIRECT(T$5&"!K:K"),40) -> 0 | U32: {=INDEX($I32:$T32,$U$2)} -> 256.44 | X32: =U32+V32-W32 -> 256.44 | Z32: {=IFERROR(U32/OFFSET($H32,,MATCH($G$2,$H$5:$U$5,0)-2,,),"-")} -> 0.79021324 | AA32: {=U32-OFFSET($H32,,MATCH($G$2,$H$5:$U$5,0)-2,,)} -> -68.08 | AD32: {=IFERROR(U32/OFFSET($AT32,,MATCH($G$2,$AT$5:$BE$5,0)-1,,),"-")} -> 0.018928409 | AE32: {=U32-OFFSET($AT32,,MATCH($G$2,$AT$5:$BE$5,0)-1,,)} -> -13291.45 | AF32: - allocate 24/7 - Delay accident insurance for family member & travel insurance -10K | AL32: =SUM(I32:T32) -> 256.44 | AM32: {=INDEX($BG$8:$BQ$83,ROW()-7,MATCH($G$3,$BG$5:$BQ$5,0))} -> #N/A | AN32: =AL32-AM32 -> #N/A | AO32: =IFERROR(AL32/AM32,"") | AR32: =BQ32-AL32 -> 13291.45 | AT32: 13547.89 | AU32: 0 | AV32: 0 | AW32: 0 | AX32: 0 | AY32: 0 | AZ32: 0 | BA32: 0 | BB32: 0 | BC32: 0 | BD32: 0 | BE32: 0 | BG32: =SUM(AT32:AU32) -> 13547.89 | BH32: =SUM(AT32:AV32) -> 13547.89 | BI32: =SUM(AT32:AW32) -> 13547.89 | BJ32: =SUM(AT32:AX32) -> 13547.89 | BK32: =SUM(AT32:AY32) -> 13547.89 | BL32: =SUM(AT32:AZ32) -> 13547.89 | BM32: =SUM(AT32:BA32) -> 13547.89 | BN32: =SUM(AT32:BB32) -> 13547.89 | BO32: =SUM(AT32:BC32) -> 13547.89 | BP32: =SUM(AT32:BD32) -> 13547.89 | BQ32: =SUM(AT32:BE32) -> 13547.89
A33: Labor | B33: Labor | C33: Labor_Indirect | D33: CC | E33: 624104 | F33: 62714200 | G33: Compensation allowances_Indirect | H33: 0 | I33: =SUMIFS(INDIRECT(I$5&"!N:N"),INDIRECT(I$5&"!L:L"),$E33,INDIRECT(I$5&"!K:K"),50)-SUMIFS(INDIRECT(I$5&"!N:N"),INDIRECT(I$5&"!L:L"),$E33,INDIRECT(I$5&"!K:K"),40) -> 0 | J33: =SUMIFS(INDIRECT(J$5&"!N:N"),INDIRECT(J$5&"!L:L"),$E33,INDIRECT(J$5&"!K:K"),50)-SUMIFS(INDIRECT(J$5&"!N:N"),INDIRECT(J$5&"!L:L"),$E33,INDIRECT(J$5&"!K:K"),40) -> 0 | K33: =SUMIFS(INDIRECT(K$5&"!N:N"),INDIRECT(K$5&"!L:L"),$E33,INDIRECT(K$5&"!K:K"),50)-SUMIFS(INDIRECT(K$5&"!N:N"),INDIRECT(K$5&"!L:L"),$E33,INDIRECT(K$5&"!K:K"),40) -> 0 | L33: =SUMIFS(INDIRECT(L$5&"!N:N"),INDIRECT(L$5&"!L:L"),$E33,INDIRECT(L$5&"!K:K"),50)-SUMIFS(INDIRECT(L$5&"!N:N"),INDIRECT(L$5&"!L:L"),$E33,INDIRECT(L$5&"!K:K"),40) -> 0 | M33: =SUMIFS(INDIRECT(M$5&"!N:N"),INDIRECT(M$5&"!L:L"),$E33,INDIRECT(M$5&"!K:K"),50)-SUMIFS(INDIRECT(M$5&"!N:N"),INDIRECT(M$5&"!L:L"),$E33,INDIRECT(M$5&"!K:K"),40) -> 0 | N33: =SUMIFS(INDIRECT(N$5&"!N:N"),INDIRECT(N$5&"!L:L"),$E33,INDIRECT(N$5&"!K:K"),50)-SUMIFS(INDIRECT(N$5&"!N:N"),INDIRECT(N$5&"!L:L"),$E33,INDIRECT(N$5&"!K:K"),40) -> 0 | O33: =SUMIFS(INDIRECT(O$5&"!N:N"),INDIRECT(O$5&"!L:L"),$E33,INDIRECT(O$5&"!K:K"),50)-SUMIFS(INDIRECT(O$5&"!N:N"),INDIRECT(O$5&"!L:L"),$E33,INDIRECT(O$5&"!K:K"),40) -> 0 | P33: =SUMIFS(INDIRECT(P$5&"!N:N"),INDIRECT(P$5&"!L:L"),$E33,INDIRECT(P$5&"!K:K"),50)-SUMIFS(INDIRECT(P$5&"!N:N"),INDIRECT(P$5&"!L:L"),$E33,INDIRECT(P$5&"!K:K"),40) -> 0 | ... T33: =SUMIFS(INDIRECT(T$5&"!N:N"),INDIRECT(T$5&"!L:L"),$E33,INDIRECT(T$5&"!K:K"),50)-SUMIFS(INDIRECT(T$5&"!N:N"),INDIRECT(T$5&"!L:L"),$E33,INDIRECT(T$5&"!K:K"),40) -> 0 | U33: {=INDEX($I33:$T33,$U$2)} -> 0 | X33: =U33+V33-W33 -> 0 | Z33: {=IFERROR(U33/OFFSET($H33,,MATCH($G$2,$H$5:$U$5,0)-2,,),"-")} -> - | AA33: {=U33-OFFSET($H33,,MATCH($G$2,$H$5:$U$5,0)-2,,)} -> 0 | AD33: {=IFERROR(U33/OFFSET($AT33,,MATCH($G$2,$AT$5:$BE$5,0)-1,,),"-")} -> - | AE33: {=U33-OFFSET($AT33,,MATCH($G$2,$AT$5:$BE$5,0)-1,,)} -> 0 | AL33: =SUM(I33:T33) -> 0 | AM33: {=INDEX($BG$8:$BQ$83,ROW()-7,MATCH($G$3,$BG$5:$BQ$5,0))} -> #N/A | AN33: =AL33-AM33 -> #N/A | AO33: =IFERROR(AL33/AM33,"") | AR33: =BQ33-AL33 -> 0 | AT33: 0 | AU33: 0 | AV33: 0 | AW33: 0 | AX33: 0 | AY33: 0 | AZ33: 0 | BA33: 0 | BB33: 0 | BC33: 0 | BD33: 0 | BE33: 0 | BG33: =SUM(AT33:AU33) -> 0 | BH33: =SUM(AT33:AV33) -> 0 | BI33: =SUM(AT33:AW33) -> 0 | BJ33: =SUM(AT33:AX33) -> 0 | BK33: =SUM(AT33:AY33) -> 0 | BL33: =SUM(AT33:AZ33) -> 0 | BM33: =SUM(AT33:BA33) -> 0 | BN33: =SUM(AT33:BB33) -> 0 | BO33: =SUM(AT33:BC33) -> 0 | BP33: =SUM(AT33:BD33) -> 0 | BQ33: =SUM(AT33:BE33) -> 0
A34: Labor | B34: Labor | C34: Labor_Indirect | D34: CC | E34: 624022 | F34: 62716000 | G34: Unemployment insurance_Indirect | H34: 1800.51 | I34: =SUMIFS(INDIRECT(I$5&"!N:N"),INDIRECT(I$5&"!L:L"),$E34,INDIRECT(I$5&"!K:K"),50)-SUMIFS(INDIRECT(I$5&"!N:N"),INDIRECT(I$5&"!L:L"),$E34,INDIRECT(I$5&"!K:K"),40) -> 1786.99 | J34: =SUMIFS(INDIRECT(J$5&"!N:N"),INDIRECT(J$5&"!L:L"),$E34,INDIRECT(J$5&"!K:K"),50)-SUMIFS(INDIRECT(J$5&"!N:N"),INDIRECT(J$5&"!L:L"),$E34,INDIRECT(J$5&"!K:K"),40) -> 0 | K34: =SUMIFS(INDIRECT(K$5&"!N:N"),INDIRECT(K$5&"!L:L"),$E34,INDIRECT(K$5&"!K:K"),50)-SUMIFS(INDIRECT(K$5&"!N:N"),INDIRECT(K$5&"!L:L"),$E34,INDIRECT(K$5&"!K:K"),40) -> 0 | L34: =SUMIFS(INDIRECT(L$5&"!N:N"),INDIRECT(L$5&"!L:L"),$E34,INDIRECT(L$5&"!K:K"),50)-SUMIFS(INDIRECT(L$5&"!N:N"),INDIRECT(L$5&"!L:L"),$E34,INDIRECT(L$5&"!K:K"),40) -> 0 | M34: =SUMIFS(INDIRECT(M$5&"!N:N"),INDIRECT(M$5&"!L:L"),$E34,INDIRECT(M$5&"!K:K"),50)-SUMIFS(INDIRECT(M$5&"!N:N"),INDIRECT(M$5&"!L:L"),$E34,INDIRECT(M$5&"!K:K"),40) -> 0 | N34: =SUMIFS(INDIRECT(N$5&"!N:N"),INDIRECT(N$5&"!L:L"),$E34,INDIRECT(N$5&"!K:K"),50)-SUMIFS(INDIRECT(N$5&"!N:N"),INDIRECT(N$5&"!L:L"),$E34,INDIRECT(N$5&"!K:K"),40) -> 0 | O34: =SUMIFS(INDIRECT(O$5&"!N:N"),INDIRECT(O$5&"!L:L"),$E34,INDIRECT(O$5&"!K:K"),50)-SUMIFS(INDIRECT(O$5&"!N:N"),INDIRECT(O$5&"!L:L"),$E34,INDIRECT(O$5&"!K:K"),40) -> 0 | P34: =SUMIFS(INDIRECT(P$5&"!N:N"),INDIRECT(P$5&"!L:L"),$E34,INDIRECT(P$5&"!K:K"),50)-SUMIFS(INDIRECT(P$5&"!N:N"),INDIRECT(P$5&"!L:L"),$E34,INDIRECT(P$5&"!K:K"),40) -> 0 | ... T34: =SUMIFS(INDIRECT(T$5&"!N:N"),INDIRECT(T$5&"!L:L"),$E34,INDIRECT(T$5&"!K:K"),50)-SUMIFS(INDIRECT(T$5&"!N:N"),INDIRECT(T$5&"!L:L"),$E34,INDIRECT(T$5&"!K:K"),40) -> 0 | U34: {=INDEX($I34:$T34,$U$2)} -> 1786.99 | X34: =U34+V34-W34 -> 1786.99 | Z34: {=IFERROR(U34/OFFSET($H34,,MATCH($G$2,$H$5:$U$5,0)-2,,),"-")} -> 0.99249102 | AA34: {=U34-OFFSET($H34,,MATCH($G$2,$H$5:$U$5,0)-2,,)} -> -13.52 | AD34: {=IFERROR(U34/OFFSET($AT34,,MATCH($G$2,$AT$5:$BE$5,0)-1,,),"-")} -> 0.98312644 | AE34: {=U34-OFFSET($AT34,,MATCH($G$2,$AT$5:$BE$5,0)-1,,)} -> -30.670401 | AL34: =SUM(I34:T34) -> 1786.99 | AM34: {=INDEX($BG$8:$BQ$83,ROW()-7,MATCH($G$3,$BG$5:$BQ$5,0))} -> #N/A | AN34: =AL34-AM34 -> #N/A | AO34: =IFERROR(AL34/AM34,"") | AR34: =BQ34-AL34 -> 24424.911 | AT34: 1817.6604 | AU34: 1823.7439 | AV34: 1823.7439 | AW34: 1973.3926 | AX34: 1967.2328 | AY34: 1967.2328 | AZ34: 1967.2328 | BA34: 1967.2328 | BB34: 1967.2328 | BC34: 1979.0653 | BD34: 1979.0653 | BE34: 4979.0653 | BG34: =SUM(AT34:AU34) -> 3641.4043 | BH34: =SUM(AT34:AV34) -> 5465.1483 | BI34: =SUM(AT34:AW34) -> 7438.5409 | BJ34: =SUM(AT34:AX34) -> 9405.7737 | BK34: =SUM(AT34:AY34) -> 11373.007 | BL34: =SUM(AT34:AZ34) -> 13340.239 | BM34: =SUM(AT34:BA34) -> 15307.472 | BN34: =SUM(AT34:BB34) -> 17274.705 | BO34: =SUM(AT34:BC34) -> 19253.77 | BP34: =SUM(AT34:BD34) -> 21232.835 | BQ34: =SUM(AT34:BE34) -> 26211.901
A35: Other | B35: Other | C35: Other | D35: CC | E35: 665000 | F35: 62720100 | G35: Material & tire testing | H35: 79018.39 | I35: =SUMIFS(INDIRECT(I$5&"!N:N"),INDIRECT(I$5&"!L:L"),$E35,INDIRECT(I$5&"!K:K"),50)-SUMIFS(INDIRECT(I$5&"!N:N"),INDIRECT(I$5&"!L:L"),$E35,INDIRECT(I$5&"!K:K"),40) -> 49604.98 | J35: =SUMIFS(INDIRECT(J$5&"!N:N"),INDIRECT(J$5&"!L:L"),$E35,INDIRECT(J$5&"!K:K"),50)-SUMIFS(INDIRECT(J$5&"!N:N"),INDIRECT(J$5&"!L:L"),$E35,INDIRECT(J$5&"!K:K"),40) -> 0 | K35: =SUMIFS(INDIRECT(K$5&"!N:N"),INDIRECT(K$5&"!L:L"),$E35,INDIRECT(K$5&"!K:K"),50)-SUMIFS(INDIRECT(K$5&"!N:N"),INDIRECT(K$5&"!L:L"),$E35,INDIRECT(K$5&"!K:K"),40) -> 0 | L35: =SUMIFS(INDIRECT(L$5&"!N:N"),INDIRECT(L$5&"!L:L"),$E35,INDIRECT(L$5&"!K:K"),50)-SUMIFS(INDIRECT(L$5&"!N:N"),INDIRECT(L$5&"!L:L"),$E35,INDIRECT(L$5&"!K:K"),40) -> 0 | M35: =SUMIFS(INDIRECT(M$5&"!N:N"),INDIRECT(M$5&"!L:L"),$E35,INDIRECT(M$5&"!K:K"),50)-SUMIFS(INDIRECT(M$5&"!N:N"),INDIRECT(M$5&"!L:L"),$E35,INDIRECT(M$5&"!K:K"),40) -> 0 | N35: =SUMIFS(INDIRECT(N$5&"!N:N"),INDIRECT(N$5&"!L:L"),$E35,INDIRECT(N$5&"!K:K"),50)-SUMIFS(INDIRECT(N$5&"!N:N"),INDIRECT(N$5&"!L:L"),$E35,INDIRECT(N$5&"!K:K"),40) -> 0 | O35: =SUMIFS(INDIRECT(O$5&"!N:N"),INDIRECT(O$5&"!L:L"),$E35,INDIRECT(O$5&"!K:K"),50)-SUMIFS(INDIRECT(O$5&"!N:N"),INDIRECT(O$5&"!L:L"),$E35,INDIRECT(O$5&"!K:K"),40) -> 0 | P35: =SUMIFS(INDIRECT(P$5&"!N:N"),INDIRECT(P$5&"!L:L"),$E35,INDIRECT(P$5&"!K:K"),50)-SUMIFS(INDIRECT(P$5&"!N:N"),INDIRECT(P$5&"!L:L"),$E35,INDIRECT(P$5&"!K:K"),40) -> 0 | ... T35: =SUMIFS(INDIRECT(T$5&"!N:N"),INDIRECT(T$5&"!L:L"),$E35,INDIRECT(T$5&"!K:K"),50)-SUMIFS(INDIRECT(T$5&"!N:N"),INDIRECT(T$5&"!L:L"),$E35,INDIRECT(T$5&"!K:K"),40) -> 0 | U35: {=INDEX($I35:$T35,$U$2)} -> 49604.98 | X35: =U35+V35-W35 -> 49604.98 | Z35: {=IFERROR(U35/OFFSET($H35,,MATCH($G$2,$H$5:$U$5,0)-2,,),"-")} -> 0.62776501 | AA35: {=U35-OFFSET($H35,,MATCH($G$2,$H$5:$U$5,0)-2,,)} -> -29413.41 | AD35: {=IFERROR(U35/OFFSET($AT35,,MATCH($G$2,$AT$5:$BE$5,0)-1,,),"-")} -> 0.75921148 | AE35: {=U35-OFFSET($AT35,,MATCH($G$2,$AT$5:$BE$5,0)-1,,)} -> -15732.52 | AL35: =SUM(I35:T35) -> 49604.98 | AM35: {=INDEX($BG$8:$BQ$83,ROW()-7,MATCH($G$3,$BG$5:$BQ$5,0))} -> #N/A | AN35: =AL35-AM35 -> #N/A | AO35: =IFERROR(AL35/AM35,"") | AR35: =BQ35-AL35 -> 700725.02 | AT35: 65337.5 | AU35: 52687.5 | AV35: 65777.5 | AW35: 62117.5 | AX35: 67377.5 | AY35: 64307.5 | AZ35: 62207.5 | BA35: 58117.5 | BB35: 57137.5 | BC35: 61497.5 | BD35: 69167.5 | BE35: 64597.5 | BG35: =SUM(AT35:AU35) -> 118025 | BH35: =SUM(AT35:AV35) -> 183802.5 | BI35: =SUM(AT35:AW35) -> 245920 | BJ35: =SUM(AT35:AX35) -> 313297.5 | BK35: =SUM(AT35:AY35) -> 377605 | BL35: =SUM(AT35:AZ35) -> 439812.5 | BM35: =SUM(AT35:BA35) -> 497930 | BN35: =SUM(AT35:BB35) -> 555067.5 | BO35: =SUM(AT35:BC35) -> 616565 | BP35: =SUM(AT35:BD35) -> 685732.5 | BQ35: =SUM(AT35:BE35) -> 750330
A36: Other | B36: Consumable | C36: Other | D36: CC | E36: 641000 | F36: 62720200 | G36: Indirect materials | H36: 116160.72 | I36: =SUMIFS(INDIRECT(I$5&"!N:N"),INDIRECT(I$5&"!L:L"),$E36,INDIRECT(I$5&"!K:K"),50)-SUMIFS(INDIRECT(I$5&"!N:N"),INDIRECT(I$5&"!L:L"),$E36,INDIRECT(I$5&"!K:K"),40) -> 62012.18 | J36: =SUMIFS(INDIRECT(J$5&"!N:N"),INDIRECT(J$5&"!L:L"),$E36,INDIRECT(J$5&"!K:K"),50)-SUMIFS(INDIRECT(J$5&"!N:N"),INDIRECT(J$5&"!L:L"),$E36,INDIRECT(J$5&"!K:K"),40) -> 0 | K36: =SUMIFS(INDIRECT(K$5&"!N:N"),INDIRECT(K$5&"!L:L"),$E36,INDIRECT(K$5&"!K:K"),50)-SUMIFS(INDIRECT(K$5&"!N:N"),INDIRECT(K$5&"!L:L"),$E36,INDIRECT(K$5&"!K:K"),40) -> 0 | L36: =SUMIFS(INDIRECT(L$5&"!N:N"),INDIRECT(L$5&"!L:L"),$E36,INDIRECT(L$5&"!K:K"),50)-SUMIFS(INDIRECT(L$5&"!N:N"),INDIRECT(L$5&"!L:L"),$E36,INDIRECT(L$5&"!K:K"),40) -> 0 | M36: =SUMIFS(INDIRECT(M$5&"!N:N"),INDIRECT(M$5&"!L:L"),$E36,INDIRECT(M$5&"!K:K"),50)-SUMIFS(INDIRECT(M$5&"!N:N"),INDIRECT(M$5&"!L:L"),$E36,INDIRECT(M$5&"!K:K"),40) -> 0 | N36: =SUMIFS(INDIRECT(N$5&"!N:N"),INDIRECT(N$5&"!L:L"),$E36,INDIRECT(N$5&"!K:K"),50)-SUMIFS(INDIRECT(N$5&"!N:N"),INDIRECT(N$5&"!L:L"),$E36,INDIRECT(N$5&"!K:K"),40) -> 0 | O36: =SUMIFS(INDIRECT(O$5&"!N:N"),INDIRECT(O$5&"!L:L"),$E36,INDIRECT(O$5&"!K:K"),50)-SUMIFS(INDIRECT(O$5&"!N:N"),INDIRECT(O$5&"!L:L"),$E36,INDIRECT(O$5&"!K:K"),40) -> 0 | P36: =SUMIFS(INDIRECT(P$5&"!N:N"),INDIRECT(P$5&"!L:L"),$E36,INDIRECT(P$5&"!K:K"),50)-SUMIFS(INDIRECT(P$5&"!N:N"),INDIRECT(P$5&"!L:L"),$E36,INDIRECT(P$5&"!K:K"),40) -> 0 | ... T36: =SUMIFS(INDIRECT(T$5&"!N:N"),INDIRECT(T$5&"!L:L"),$E36,INDIRECT(T$5&"!K:K"),50)-SUMIFS(INDIRECT(T$5&"!N:N"),INDIRECT(T$5&"!L:L"),$E36,INDIRECT(T$5&"!K:K"),40) -> 0 | U36: {=INDEX($I36:$T36,$U$2)} -> 62012.18 | X36: =U36+V36-W36 -> 62012.18 | Z36: {=IFERROR(U36/OFFSET($H36,,MATCH($G$2,$H$5:$U$5,0)-2,,),"-")} -> 0.5338481 | AA36: {=U36-OFFSET($H36,,MATCH($G$2,$H$5:$U$5,0)-2,,)} -> -54148.54 | AD36: {=IFERROR(U36/OFFSET($AT36,,MATCH($G$2,$AT$5:$BE$5,0)-1,,),"-")} -> 0.90450688 | AE36: {=U36-OFFSET($AT36,,MATCH($G$2,$AT$5:$BE$5,0)-1,,)} -> -6546.9227 | AH36: {=IFERROR(INDEX($I36:$T36,$U$2)/$AH$3,0)} -> 90.128042 | AI36: =H36/PrvMonthProductionRRT -> 150.83388 | AJ36: {=IFERROR(OFFSET($AT36,,MATCH($G$2,$AT$5:$BE$5,0)-1,,)/$AJ$3,"")} -> 86.191922 | AL36: =SUM(I36:T36) -> 62012.18 | AM36: {=INDEX($BG$8:$BQ$83,ROW()-7,MATCH($G$3,$BG$5:$BQ$5,0))} -> #N/A | AN36: =AL36-AM36 -> #N/A | AO36: =IFERROR(AL36/AM36,"") | AR36: =BQ36-AL36 -> 926754.29 | AT36: 68559.103 | AU36: 56536.682 | AV36: 77826.3 | AW36: 88527.093 | AX36: 75488.112 | AY36: 84426.726 | AZ36: 87248.773 | BA36: 84381.349 | BB36: 80453.242 | BC36: 95603.846 | BD36: 94047.922 | BE36: 95667.323 | BG36: =SUM(AT36:AU36) -> 125095.78 | BH36: =SUM(AT36:AV36) -> 202922.08 | BI36: =SUM(AT36:AW36) -> 291449.18 | BJ36: =SUM(AT36:AX36) -> 366937.29 | BK36: =SUM(AT36:AY36) -> 451364.02 | BL36: =SUM(AT36:AZ36) -> 538612.79 | BM36: =SUM(AT36:BA36) -> 622994.14 | BN36: =SUM(AT36:BB36) -> 703447.38 | BO36: =SUM(AT36:BC36) -> 799051.23 | BP36: =SUM(AT36:BD36) -> 893099.15 | BQ36: =SUM(AT36:BE36) -> 988766.47
A37: Other | B37: Energy | C37: Other | D37: CC | E37: 642000 | F37: 62720300 | G37: Energy | H37: 96753.03 | I37: =SUMIFS(INDIRECT(I$5&"!N:N"),INDIRECT(I$5&"!L:L"),$E37,INDIRECT(I$5&"!K:K"),50)-SUMIFS(INDIRECT(I$5&"!N:N"),INDIRECT(I$5&"!L:L"),$E37,INDIRECT(I$5&"!K:K"),40) -> 76313.48 | J37: =SUMIFS(INDIRECT(J$5&"!N:N"),INDIRECT(J$5&"!L:L"),$E37,INDIRECT(J$5&"!K:K"),50)-SUMIFS(INDIRECT(J$5&"!N:N"),INDIRECT(J$5&"!L:L"),$E37,INDIRECT(J$5&"!K:K"),40) -> 0 | K37: =SUMIFS(INDIRECT(K$5&"!N:N"),INDIRECT(K$5&"!L:L"),$E37,INDIRECT(K$5&"!K:K"),50)-SUMIFS(INDIRECT(K$5&"!N:N"),INDIRECT(K$5&"!L:L"),$E37,INDIRECT(K$5&"!K:K"),40) -> 0 | L37: =SUMIFS(INDIRECT(L$5&"!N:N"),INDIRECT(L$5&"!L:L"),$E37,INDIRECT(L$5&"!K:K"),50)-SUMIFS(INDIRECT(L$5&"!N:N"),INDIRECT(L$5&"!L:L"),$E37,INDIRECT(L$5&"!K:K"),40) -> 0 | M37: =SUMIFS(INDIRECT(M$5&"!N:N"),INDIRECT(M$5&"!L:L"),$E37,INDIRECT(M$5&"!K:K"),50)-SUMIFS(INDIRECT(M$5&"!N:N"),INDIRECT(M$5&"!L:L"),$E37,INDIRECT(M$5&"!K:K"),40) -> 0 | N37: =SUMIFS(INDIRECT(N$5&"!N:N"),INDIRECT(N$5&"!L:L"),$E37,INDIRECT(N$5&"!K:K"),50)-SUMIFS(INDIRECT(N$5&"!N:N"),INDIRECT(N$5&"!L:L"),$E37,INDIRECT(N$5&"!K:K"),40) -> 0 | O37: =SUMIFS(INDIRECT(O$5&"!N:N"),INDIRECT(O$5&"!L:L"),$E37,INDIRECT(O$5&"!K:K"),50)-SUMIFS(INDIRECT(O$5&"!N:N"),INDIRECT(O$5&"!L:L"),$E37,INDIRECT(O$5&"!K:K"),40) -> 0 | P37: =SUMIFS(INDIRECT(P$5&"!N:N"),INDIRECT(P$5&"!L:L"),$E37,INDIRECT(P$5&"!K:K"),50)-SUMIFS(INDIRECT(P$5&"!N:N"),INDIRECT(P$5&"!L:L"),$E37,INDIRECT(P$5&"!K:K"),40) -> 0 | ... T37: =SUMIFS(INDIRECT(T$5&"!N:N"),INDIRECT(T$5&"!L:L"),$E37,INDIRECT(T$5&"!K:K"),50)-SUMIFS(INDIRECT(T$5&"!N:N"),INDIRECT(T$5&"!L:L"),$E37,INDIRECT(T$5&"!K:K"),40) -> 0 | U37: {=INDEX($I37:$T37,$U$2)} -> 76313.48 | X37: =U37+V37-W37 -> 76313.48 | Z37: {=IFERROR(U37/OFFSET($H37,,MATCH($G$2,$H$5:$U$5,0)-2,,),"-")} -> 0.78874512 | AA37: {=U37-OFFSET($H37,,MATCH($G$2,$H$5:$U$5,0)-2,,)} -> -20439.55 | AD37: {=IFERROR(U37/OFFSET($AT37,,MATCH($G$2,$AT$5:$BE$5,0)-1,,),"-")} -> 0.85033275 | AE37: {=U37-OFFSET($AT37,,MATCH($G$2,$AT$5:$BE$5,0)-1,,)} -> -13431.952 | AH37: {=IFERROR(INDEX($I37:$T37,$U$2)/$AH$3,0)} -> 110.91345 | AI37: =H37/PrvMonthProductionRRT -> 125.63313 | AJ37: {=IFERROR(OFFSET($AT37,,MATCH($G$2,$AT$5:$BE$5,0)-1,,)/$AJ$3,"")} -> 112.8272 | AL37: =SUM(I37:T37) -> 76313.48 | AM37: {=INDEX($BG$8:$BQ$83,ROW()-7,MATCH($G$3,$BG$5:$BQ$5,0))} -> #N/A | AN37: =AL37-AM37 -> #N/A | AO37: =IFERROR(AL37/AM37,"") | AR37: =BQ37-AL37 -> 991850.38 | AT37: 89745.432 | AU37: 70814.396 | AV37: 90447.286 | AW37: 87030.763 | AX37: 84188.519 | AY37: 90578.425 | AZ37: 92288.667 | BA37: 96237.288 | BB37: 80794.437 | BC37: 99269.607 | BD37: 93881.475 | BE37: 92887.561 | BG37: =SUM(AT37:AU37) -> 160559.83 | BH37: =SUM(AT37:AV37) -> 251007.11 | BI37: =SUM(AT37:AW37) -> 338037.88 | BJ37: =SUM(AT37:AX37) -> 422226.4 | BK37: =SUM(AT37:AY37) -> 512804.82 | BL37: =SUM(AT37:AZ37) -> 605093.49 | BM37: =SUM(AT37:BA37) -> 701330.78 | BN37: =SUM(AT37:BB37) -> 782125.21 | BO37: =SUM(AT37:BC37) -> 881394.82 | BP37: =SUM(AT37:BD37) -> 975276.3 | BQ37: =SUM(AT37:BE37) -> 1068163.9
A38: Other | B38: Consumable | C38: Other | D38: CC | E38: 644100 | F38: 62720800 | G38: Consumable goods | H38: 90169.65 | I38: =SUMIFS(INDIRECT(I$5&"!N:N"),INDIRECT(I$5&"!L:L"),$E38,INDIRECT(I$5&"!K:K"),50)-SUMIFS(INDIRECT(I$5&"!N:N"),INDIRECT(I$5&"!L:L"),$E38,INDIRECT(I$5&"!K:K"),40) -> 44790.71 | J38: =SUMIFS(INDIRECT(J$5&"!N:N"),INDIRECT(J$5&"!L:L"),$E38,INDIRECT(J$5&"!K:K"),50)-SUMIFS(INDIRECT(J$5&"!N:N"),INDIRECT(J$5&"!L:L"),$E38,INDIRECT(J$5&"!K:K"),40) -> 0 | K38: =SUMIFS(INDIRECT(K$5&"!N:N"),INDIRECT(K$5&"!L:L"),$E38,INDIRECT(K$5&"!K:K"),50)-SUMIFS(INDIRECT(K$5&"!N:N"),INDIRECT(K$5&"!L:L"),$E38,INDIRECT(K$5&"!K:K"),40) -> 0 | L38: =SUMIFS(INDIRECT(L$5&"!N:N"),INDIRECT(L$5&"!L:L"),$E38,INDIRECT(L$5&"!K:K"),50)-SUMIFS(INDIRECT(L$5&"!N:N"),INDIRECT(L$5&"!L:L"),$E38,INDIRECT(L$5&"!K:K"),40) -> 0 | M38: =SUMIFS(INDIRECT(M$5&"!N:N"),INDIRECT(M$5&"!L:L"),$E38,INDIRECT(M$5&"!K:K"),50)-SUMIFS(INDIRECT(M$5&"!N:N"),INDIRECT(M$5&"!L:L"),$E38,INDIRECT(M$5&"!K:K"),40) -> 0 | N38: =SUMIFS(INDIRECT(N$5&"!N:N"),INDIRECT(N$5&"!L:L"),$E38,INDIRECT(N$5&"!K:K"),50)-SUMIFS(INDIRECT(N$5&"!N:N"),INDIRECT(N$5&"!L:L"),$E38,INDIRECT(N$5&"!K:K"),40) -> 0 | O38: =SUMIFS(INDIRECT(O$5&"!N:N"),INDIRECT(O$5&"!L:L"),$E38,INDIRECT(O$5&"!K:K"),50)-SUMIFS(INDIRECT(O$5&"!N:N"),INDIRECT(O$5&"!L:L"),$E38,INDIRECT(O$5&"!K:K"),40) -> 0 | P38: =SUMIFS(INDIRECT(P$5&"!N:N"),INDIRECT(P$5&"!L:L"),$E38,INDIRECT(P$5&"!K:K"),50)-SUMIFS(INDIRECT(P$5&"!N:N"),INDIRECT(P$5&"!L:L"),$E38,INDIRECT(P$5&"!K:K"),40) -> 0 | ... T38: =SUMIFS(INDIRECT(T$5&"!N:N"),INDIRECT(T$5&"!L:L"),$E38,INDIRECT(T$5&"!K:K"),50)-SUMIFS(INDIRECT(T$5&"!N:N"),INDIRECT(T$5&"!L:L"),$E38,INDIRECT(T$5&"!K:K"),40) -> 0 | U38: {=INDEX($I38:$T38,$U$2)} -> 44790.71 | X38: =U38+V38-W38 -> 44790.71 | Z38: {=IFERROR(U38/OFFSET($H38,,MATCH($G$2,$H$5:$U$5,0)-2,,),"-")} -> 0.4967382 | AA38: {=U38-OFFSET($H38,,MATCH($G$2,$H$5:$U$5,0)-2,,)} -> -45378.94 | AD38: {=IFERROR(U38/OFFSET($AT38,,MATCH($G$2,$AT$5:$BE$5,0)-1,,),"-")} -> 0.78256321 | AE38: {=U38-OFFSET($AT38,,MATCH($G$2,$AT$5:$BE$5,0)-1,,)} -> -12445.191 | AI38: =H38/PrvMonthProductionRRT -> 117.08466 | AL38: =SUM(I38:T38) -> 44790.71 | AM38: {=INDEX($BG$8:$BQ$83,ROW()-7,MATCH($G$3,$BG$5:$BQ$5,0))} -> #N/A | AN38: =AL38-AM38 -> #N/A | AO38: =IFERROR(AL38/AM38,"") | AR38: =BQ38-AL38 -> 1059850.7 | AT38: 57235.901 | AU38: 65155.881 | AV38: 81054.144 | AW38: 81716.543 | AX38: 71214.438 | AY38: 97663.042 | AZ38: 106103.06 | BA38: 111294.77 | BB38: 101280.06 | BC38: 118744.18 | BD38: 110821.43 | BE38: 102357.96 | BG38: =SUM(AT38:AU38) -> 122391.78 | BH38: =SUM(AT38:AV38) -> 203445.93 | BI38: =SUM(AT38:AW38) -> 285162.47 | BJ38: =SUM(AT38:AX38) -> 356376.91 | BK38: =SUM(AT38:AY38) -> 454039.95 | BL38: =SUM(AT38:AZ38) -> 560143.01 | BM38: =SUM(AT38:BA38) -> 671437.78 | BN38: =SUM(AT38:BB38) -> 772717.84 | BO38: =SUM(AT38:BC38) -> 891462.03 | BP38: =SUM(AT38:BD38) -> 1002283.5 | BQ38: =SUM(AT38:BE38) -> 1104641.4
A39: Other | B39: Other | C39: Other | D39: CC | E39: 644500 | F39: 62730100 | G39: Factory tools & supplies | H39: 32144.45 | I39: =SUMIFS(INDIRECT(I$5&"!N:N"),INDIRECT(I$5&"!L:L"),$E39,INDIRECT(I$5&"!K:K"),50)-SUMIFS(INDIRECT(I$5&"!N:N"),INDIRECT(I$5&"!L:L"),$E39,INDIRECT(I$5&"!K:K"),40) -> 17874.01 | J39: =SUMIFS(INDIRECT(J$5&"!N:N"),INDIRECT(J$5&"!L:L"),$E39,INDIRECT(J$5&"!K:K"),50)-SUMIFS(INDIRECT(J$5&"!N:N"),INDIRECT(J$5&"!L:L"),$E39,INDIRECT(J$5&"!K:K"),40) -> 0 | K39: =SUMIFS(INDIRECT(K$5&"!N:N"),INDIRECT(K$5&"!L:L"),$E39,INDIRECT(K$5&"!K:K"),50)-SUMIFS(INDIRECT(K$5&"!N:N"),INDIRECT(K$5&"!L:L"),$E39,INDIRECT(K$5&"!K:K"),40) -> 0 | L39: =SUMIFS(INDIRECT(L$5&"!N:N"),INDIRECT(L$5&"!L:L"),$E39,INDIRECT(L$5&"!K:K"),50)-SUMIFS(INDIRECT(L$5&"!N:N"),INDIRECT(L$5&"!L:L"),$E39,INDIRECT(L$5&"!K:K"),40) -> 0 | M39: =SUMIFS(INDIRECT(M$5&"!N:N"),INDIRECT(M$5&"!L:L"),$E39,INDIRECT(M$5&"!K:K"),50)-SUMIFS(INDIRECT(M$5&"!N:N"),INDIRECT(M$5&"!L:L"),$E39,INDIRECT(M$5&"!K:K"),40) -> 0 | N39: =SUMIFS(INDIRECT(N$5&"!N:N"),INDIRECT(N$5&"!L:L"),$E39,INDIRECT(N$5&"!K:K"),50)-SUMIFS(INDIRECT(N$5&"!N:N"),INDIRECT(N$5&"!L:L"),$E39,INDIRECT(N$5&"!K:K"),40) -> 0 | O39: =SUMIFS(INDIRECT(O$5&"!N:N"),INDIRECT(O$5&"!L:L"),$E39,INDIRECT(O$5&"!K:K"),50)-SUMIFS(INDIRECT(O$5&"!N:N"),INDIRECT(O$5&"!L:L"),$E39,INDIRECT(O$5&"!K:K"),40) -> 0 | P39: =SUMIFS(INDIRECT(P$5&"!N:N"),INDIRECT(P$5&"!L:L"),$E39,INDIRECT(P$5&"!K:K"),50)-SUMIFS(INDIRECT(P$5&"!N:N"),INDIRECT(P$5&"!L:L"),$E39,INDIRECT(P$5&"!K:K"),40) -> 0 | ... T39: =SUMIFS(INDIRECT(T$5&"!N:N"),INDIRECT(T$5&"!L:L"),$E39,INDIRECT(T$5&"!K:K"),50)-SUMIFS(INDIRECT(T$5&"!N:N"),INDIRECT(T$5&"!L:L"),$E39,INDIRECT(T$5&"!K:K"),40) -> 0 | U39: {=INDEX($I39:$T39,$U$2)} -> 17874.01 | X39: =U39+V39-W39 -> 17874.01 | Z39: {=IFERROR(U39/OFFSET($H39,,MATCH($G$2,$H$5:$U$5,0)-2,,),"-")} -> 0.55605276 | AA39: {=U39-OFFSET($H39,,MATCH($G$2,$H$5:$U$5,0)-2,,)} -> -14270.44 | AD39: {=IFERROR(U39/OFFSET($AT39,,MATCH($G$2,$AT$5:$BE$5,0)-1,,),"-")} -> 0.3811238 | AE39: {=U39-OFFSET($AT39,,MATCH($G$2,$AT$5:$BE$5,0)-1,,)} -> -29024.163 | AI39: =H39/PrvMonthProductionRRT -> 41.739344 | AL39: =SUM(I39:T39) -> 17874.01 | AM39: {=INDEX($BG$8:$BQ$83,ROW()-7,MATCH($G$3,$BG$5:$BQ$5,0))} -> #N/A | AN39: =AL39-AM39 -> #N/A | AO39: =IFERROR(AL39/AM39,"") | AR39: =BQ39-AL39 -> 765542.34 | AT39: 46898.173 | AU39: 33065.43 | AV39: 103268.99 | AW39: 63030.752 | AX39: 80236.073 | AY39: 58941.567 | AZ39: 51472.473 | BA39: 149906.84 | BB39: 56705.41 | BC39: 59325.211 | BD39: 25263.146 | BE39: 55302.29 | BG39: =SUM(AT39:AU39) -> 79963.603 | BH39: =SUM(AT39:AV39) -> 183232.59 | BI39: =SUM(AT39:AW39) -> 246263.34 | BJ39: =SUM(AT39:AX39) -> 326499.41 | BK39: =SUM(AT39:AY39) -> 385440.98 | BL39: =SUM(AT39:AZ39) -> 436913.45 | BM39: =SUM(AT39:BA39) -> 586820.29 | BN39: =SUM(AT39:BB39) -> 643525.7 | BO39: =SUM(AT39:BC39) -> 702850.91 | BP39: =SUM(AT39:BD39) -> 728114.06 | BQ39: =SUM(AT39:BE39) -> 783416.35
A40: Other | B40: Other | C40: Other | D40: CC | E40: 667111 | F40: 62730300 | G40: Stationery & printing | H40: 2301.88 | I40: =SUMIFS(INDIRECT(I$5&"!N:N"),INDIRECT(I$5&"!L:L"),$E40,INDIRECT(I$5&"!K:K"),50)-SUMIFS(INDIRECT(I$5&"!N:N"),INDIRECT(I$5&"!L:L"),$E40,INDIRECT(I$5&"!K:K"),40) -> 1640.67 | J40: =SUMIFS(INDIRECT(J$5&"!N:N"),INDIRECT(J$5&"!L:L"),$E40,INDIRECT(J$5&"!K:K"),50)-SUMIFS(INDIRECT(J$5&"!N:N"),INDIRECT(J$5&"!L:L"),$E40,INDIRECT(J$5&"!K:K"),40) -> 0 | K40: =SUMIFS(INDIRECT(K$5&"!N:N"),INDIRECT(K$5&"!L:L"),$E40,INDIRECT(K$5&"!K:K"),50)-SUMIFS(INDIRECT(K$5&"!N:N"),INDIRECT(K$5&"!L:L"),$E40,INDIRECT(K$5&"!K:K"),40) -> 0 | L40: =SUMIFS(INDIRECT(L$5&"!N:N"),INDIRECT(L$5&"!L:L"),$E40,INDIRECT(L$5&"!K:K"),50)-SUMIFS(INDIRECT(L$5&"!N:N"),INDIRECT(L$5&"!L:L"),$E40,INDIRECT(L$5&"!K:K"),40) -> 0 | M40: =SUMIFS(INDIRECT(M$5&"!N:N"),INDIRECT(M$5&"!L:L"),$E40,INDIRECT(M$5&"!K:K"),50)-SUMIFS(INDIRECT(M$5&"!N:N"),INDIRECT(M$5&"!L:L"),$E40,INDIRECT(M$5&"!K:K"),40) -> 0 | N40: =SUMIFS(INDIRECT(N$5&"!N:N"),INDIRECT(N$5&"!L:L"),$E40,INDIRECT(N$5&"!K:K"),50)-SUMIFS(INDIRECT(N$5&"!N:N"),INDIRECT(N$5&"!L:L"),$E40,INDIRECT(N$5&"!K:K"),40) -> 0 | O40: =SUMIFS(INDIRECT(O$5&"!N:N"),INDIRECT(O$5&"!L:L"),$E40,INDIRECT(O$5&"!K:K"),50)-SUMIFS(INDIRECT(O$5&"!N:N"),INDIRECT(O$5&"!L:L"),$E40,INDIRECT(O$5&"!K:K"),40) -> 0 | P40: =SUMIFS(INDIRECT(P$5&"!N:N"),INDIRECT(P$5&"!L:L"),$E40,INDIRECT(P$5&"!K:K"),50)-SUMIFS(INDIRECT(P$5&"!N:N"),INDIRECT(P$5&"!L:L"),$E40,INDIRECT(P$5&"!K:K"),40) -> 0 | ... T40: =SUMIFS(INDIRECT(T$5&"!N:N"),INDIRECT(T$5&"!L:L"),$E40,INDIRECT(T$5&"!K:K"),50)-SUMIFS(INDIRECT(T$5&"!N:N"),INDIRECT(T$5&"!L:L"),$E40,INDIRECT(T$5&"!K:K"),40) -> 0 | U40: {=INDEX($I40:$T40,$U$2)} -> 1640.67 | X40: =U40+V40-W40 -> 1640.67 | Z40: {=IFERROR(U40/OFFSET($H40,,MATCH($G$2,$H$5:$U$5,0)-2,,),"-")} -> 0.71275219 | AA40: {=U40-OFFSET($H40,,MATCH($G$2,$H$5:$U$5,0)-2,,)} -> -661.21 | AD40: {=IFERROR(U40/OFFSET($AT40,,MATCH($G$2,$AT$5:$BE$5,0)-1,,),"-")} -> 0.6081401 | AE40: {=U40-OFFSET($AT40,,MATCH($G$2,$AT$5:$BE$5,0)-1,,)} -> -1057.1788 | AI40: =H40/PrvMonthProductionRRT -> 2.9889751 | AL40: =SUM(I40:T40) -> 1640.67 | AM40: {=INDEX($BG$8:$BQ$83,ROW()-7,MATCH($G$3,$BG$5:$BQ$5,0))} -> #N/A | AN40: =AL40-AM40 -> #N/A | AO40: =IFERROR(AL40/AM40,"") | AR40: =BQ40-AL40 -> 35516.625 | AT40: 2697.8488 | AU40: 3343.0363 | AV40: 3952.727 | AW40: 2905.0039 | AX40: 3008.0446 | AY40: 2718.0347 | AZ40: 2935.06 | BA40: 2957.1354 | BB40: 3356.8984 | BC40: 2792.7216 | BD40: 2747.8053 | BE40: 3742.9791 | BG40: =SUM(AT40:AU40) -> 6040.885 | BH40: =SUM(AT40:AV40) -> 9993.612 | BI40: =SUM(AT40:AW40) -> 12898.616 | BJ40: =SUM(AT40:AX40) -> 15906.66 | BK40: =SUM(AT40:AY40) -> 18624.695 | BL40: =SUM(AT40:AZ40) -> 21559.755 | BM40: =SUM(AT40:BA40) -> 24516.891 | BN40: =SUM(AT40:BB40) -> 27873.789 | BO40: =SUM(AT40:BC40) -> 30666.511 | BP40: =SUM(AT40:BD40) -> 33414.316 | BQ40: =SUM(AT40:BE40) -> 37157.295
A41: Other | B41: Mech.Service & Maint | C41: Other | D41: CC | E41: 651110 | F41: 62730400 | G41: Spare part | H41: 236981.27 | I41: =SUMIFS(INDIRECT(I$5&"!N:N"),INDIRECT(I$5&"!L:L"),$E41,INDIRECT(I$5&"!K:K"),50)-SUMIFS(INDIRECT(I$5&"!N:N"),INDIRECT(I$5&"!L:L"),$E41,INDIRECT(I$5&"!K:K"),40) -> 171638.7 | J41: =SUMIFS(INDIRECT(J$5&"!N:N"),INDIRECT(J$5&"!L:L"),$E41,INDIRECT(J$5&"!K:K"),50)-SUMIFS(INDIRECT(J$5&"!N:N"),INDIRECT(J$5&"!L:L"),$E41,INDIRECT(J$5&"!K:K"),40) -> 0 | K41: =SUMIFS(INDIRECT(K$5&"!N:N"),INDIRECT(K$5&"!L:L"),$E41,INDIRECT(K$5&"!K:K"),50)-SUMIFS(INDIRECT(K$5&"!N:N"),INDIRECT(K$5&"!L:L"),$E41,INDIRECT(K$5&"!K:K"),40) -> 0 | L41: =SUMIFS(INDIRECT(L$5&"!N:N"),INDIRECT(L$5&"!L:L"),$E41,INDIRECT(L$5&"!K:K"),50)-SUMIFS(INDIRECT(L$5&"!N:N"),INDIRECT(L$5&"!L:L"),$E41,INDIRECT(L$5&"!K:K"),40) -> 0 | M41: =SUMIFS(INDIRECT(M$5&"!N:N"),INDIRECT(M$5&"!L:L"),$E41,INDIRECT(M$5&"!K:K"),50)-SUMIFS(INDIRECT(M$5&"!N:N"),INDIRECT(M$5&"!L:L"),$E41,INDIRECT(M$5&"!K:K"),40) -> 0 | N41: =SUMIFS(INDIRECT(N$5&"!N:N"),INDIRECT(N$5&"!L:L"),$E41,INDIRECT(N$5&"!K:K"),50)-SUMIFS(INDIRECT(N$5&"!N:N"),INDIRECT(N$5&"!L:L"),$E41,INDIRECT(N$5&"!K:K"),40) -> 0 | O41: =SUMIFS(INDIRECT(O$5&"!N:N"),INDIRECT(O$5&"!L:L"),$E41,INDIRECT(O$5&"!K:K"),50)-SUMIFS(INDIRECT(O$5&"!N:N"),INDIRECT(O$5&"!L:L"),$E41,INDIRECT(O$5&"!K:K"),40) -> 0 | P41: =SUMIFS(INDIRECT(P$5&"!N:N"),INDIRECT(P$5&"!L:L"),$E41,INDIRECT(P$5&"!K:K"),50)-SUMIFS(INDIRECT(P$5&"!N:N"),INDIRECT(P$5&"!L:L"),$E41,INDIRECT(P$5&"!K:K"),40) -> 0 | ... T41: =SUMIFS(INDIRECT(T$5&"!N:N"),INDIRECT(T$5&"!L:L"),$E41,INDIRECT(T$5&"!K:K"),50)-SUMIFS(INDIRECT(T$5&"!N:N"),INDIRECT(T$5&"!L:L"),$E41,INDIRECT(T$5&"!K:K"),40) -> 0 | U41: {=INDEX($I41:$T41,$U$2)} -> 171638.7 | X41: =U41+V41-W41 -> 171638.7 | Z41: {=IFERROR(U41/OFFSET($H41,,MATCH($G$2,$H$5:$U$5,0)-2,,),"-")} -> 0.72427116 | AA41: {=U41-OFFSET($H41,,MATCH($G$2,$H$5:$U$5,0)-2,,)} -> -65342.57 | AD41: {=IFERROR(U41/OFFSET($AT41,,MATCH($G$2,$AT$5:$BE$5,0)-1,,),"-")} -> 0.76779842 | AE41: {=U41-OFFSET($AT41,,MATCH($G$2,$AT$5:$BE$5,0)-1,,)} -> -51907.866 | AI41: =H41/PrvMonthProductionRRT -> 307.71853 | AL41: =SUM(I41:T41) -> 171638.7 | AM41: {=INDEX($BG$8:$BQ$83,ROW()-7,MATCH($G$3,$BG$5:$BQ$5,0))} -> #N/A | AN41: =AL41-AM41 -> #N/A | AO41: =IFERROR(AL41/AM41,"") | AR41: =BQ41-AL41 -> 2904269.9 | AT41: 223546.57 | AU41: 214985.08 | AV41: 223376.4 | AW41: 318187.85 | AX41: 314633.16 | AY41: 274090.81 | AZ41: 284492.42 | BA41: 278350.78 | BB41: 259777.98 | BC41: 222169.07 | BD41: 272297.52 | BE41: 190001 | BG41: =SUM(AT41:AU41) -> 438531.65 | BH41: =SUM(AT41:AV41) -> 661908.05 | BI41: =SUM(AT41:AW41) -> 980095.9 | BJ41: =SUM(AT41:AX41) -> 1294729.1 | BK41: =SUM(AT41:AY41) -> 1568819.9 | BL41: =SUM(AT41:AZ41) -> 1853312.3 | BM41: =SUM(AT41:BA41) -> 2131663.1 | BN41: =SUM(AT41:BB41) -> 2391441 | BO41: =SUM(AT41:BC41) -> 2613610.1 | BP41: =SUM(AT41:BD41) -> 2885907.6 | BQ41: =SUM(AT41:BE41) -> 3075908.6
A42: Labor | B42: Labor | C42: Labor_Indirect | D42: CC | E42: 624131 | F42: 62730501 | G42: Uniform & safety supplies_Local | H42: 36338.13 | I42: =SUMIFS(INDIRECT(I$5&"!N:N"),INDIRECT(I$5&"!L:L"),$E42,INDIRECT(I$5&"!K:K"),50)-SUMIFS(INDIRECT(I$5&"!N:N"),INDIRECT(I$5&"!L:L"),$E42,INDIRECT(I$5&"!K:K"),40) -> 5921.97 | J42: =SUMIFS(INDIRECT(J$5&"!N:N"),INDIRECT(J$5&"!L:L"),$E42,INDIRECT(J$5&"!K:K"),50)-SUMIFS(INDIRECT(J$5&"!N:N"),INDIRECT(J$5&"!L:L"),$E42,INDIRECT(J$5&"!K:K"),40) -> 0 | K42: =SUMIFS(INDIRECT(K$5&"!N:N"),INDIRECT(K$5&"!L:L"),$E42,INDIRECT(K$5&"!K:K"),50)-SUMIFS(INDIRECT(K$5&"!N:N"),INDIRECT(K$5&"!L:L"),$E42,INDIRECT(K$5&"!K:K"),40) -> 0 | L42: =SUMIFS(INDIRECT(L$5&"!N:N"),INDIRECT(L$5&"!L:L"),$E42,INDIRECT(L$5&"!K:K"),50)-SUMIFS(INDIRECT(L$5&"!N:N"),INDIRECT(L$5&"!L:L"),$E42,INDIRECT(L$5&"!K:K"),40) -> 0 | M42: =SUMIFS(INDIRECT(M$5&"!N:N"),INDIRECT(M$5&"!L:L"),$E42,INDIRECT(M$5&"!K:K"),50)-SUMIFS(INDIRECT(M$5&"!N:N"),INDIRECT(M$5&"!L:L"),$E42,INDIRECT(M$5&"!K:K"),40) -> 0 | N42: =SUMIFS(INDIRECT(N$5&"!N:N"),INDIRECT(N$5&"!L:L"),$E42,INDIRECT(N$5&"!K:K"),50)-SUMIFS(INDIRECT(N$5&"!N:N"),INDIRECT(N$5&"!L:L"),$E42,INDIRECT(N$5&"!K:K"),40) -> 0 | O42: =SUMIFS(INDIRECT(O$5&"!N:N"),INDIRECT(O$5&"!L:L"),$E42,INDIRECT(O$5&"!K:K"),50)-SUMIFS(INDIRECT(O$5&"!N:N"),INDIRECT(O$5&"!L:L"),$E42,INDIRECT(O$5&"!K:K"),40) -> 0 | P42: =SUMIFS(INDIRECT(P$5&"!N:N"),INDIRECT(P$5&"!L:L"),$E42,INDIRECT(P$5&"!K:K"),50)-SUMIFS(INDIRECT(P$5&"!N:N"),INDIRECT(P$5&"!L:L"),$E42,INDIRECT(P$5&"!K:K"),40) -> 0 | ... T42: =SUMIFS(INDIRECT(T$5&"!N:N"),INDIRECT(T$5&"!L:L"),$E42,INDIRECT(T$5&"!K:K"),50)-SUMIFS(INDIRECT(T$5&"!N:N"),INDIRECT(T$5&"!L:L"),$E42,INDIRECT(T$5&"!K:K"),40) -> 0 | U42: {=INDEX($I42:$T42,$U$2)} -> 5921.97 | X42: =U42+V42-W42 -> 5921.97 | Z42: {=IFERROR(U42/OFFSET($H42,,MATCH($G$2,$H$5:$U$5,0)-2,,),"-")} -> 0.16296849 | AA42: {=U42-OFFSET($H42,,MATCH($G$2,$H$5:$U$5,0)-2,,)} -> -30416.16 | AD42: {=IFERROR(U42/OFFSET($AT42,,MATCH($G$2,$AT$5:$BE$5,0)-1,,),"-")} -> 0.57324354 | AE42: {=U42-OFFSET($AT42,,MATCH($G$2,$AT$5:$BE$5,0)-1,,)} -> -4408.6654 | AI42: =H42/PrvMonthProductionRRT -> 47.184808 | AL42: =SUM(I42:T42) -> 5921.97 | AM42: {=INDEX($BG$8:$BQ$83,ROW()-7,MATCH($G$3,$BG$5:$BQ$5,0))} -> #N/A | AN42: =AL42-AM42 -> #N/A | AO42: =IFERROR(AL42/AM42,"") | AR42: =BQ42-AL42 -> 143300.41 | AT42: 10330.635 | AU42: 9185.6211 | AV42: 10140.463 | AW42: 16309.563 | AX42: 10412.417 | AY42: 9276.7541 | AZ42: 10995.735 | BA42: 13211.699 | BB42: 10492.246 | BC42: 23811.229 | BD42: 13322.955 | BE42: 11733.06 | BG42: =SUM(AT42:AU42) -> 19516.257 | BH42: =SUM(AT42:AV42) -> 29656.72 | BI42: =SUM(AT42:AW42) -> 45966.282 | BJ42: =SUM(AT42:AX42) -> 56378.7 | BK42: =SUM(AT42:AY42) -> 65655.454 | BL42: =SUM(AT42:AZ42) -> 76651.189 | BM42: =SUM(AT42:BA42) -> 89862.888 | BN42: =SUM(AT42:BB42) -> 100355.13 | BO42: =SUM(AT42:BC42) -> 124166.36 | BP42: =SUM(AT42:BD42) -> 137489.32 | BQ42: =SUM(AT42:BE42) -> 149222.38
A43: Labor | B43: Labor | C43: Labor_Indirect | D43: CC | E43: 662101 | F43: 62730502 | G43: Uniform & safety supplies_Expat | H43: 55.29 | I43: =SUMIFS(INDIRECT(I$5&"!N:N"),INDIRECT(I$5&"!L:L"),$E43,INDIRECT(I$5&"!K:K"),50)-SUMIFS(INDIRECT(I$5&"!N:N"),INDIRECT(I$5&"!L:L"),$E43,INDIRECT(I$5&"!K:K"),40) -> 0 | J43: =SUMIFS(INDIRECT(J$5&"!N:N"),INDIRECT(J$5&"!L:L"),$E43,INDIRECT(J$5&"!K:K"),50)-SUMIFS(INDIRECT(J$5&"!N:N"),INDIRECT(J$5&"!L:L"),$E43,INDIRECT(J$5&"!K:K"),40) -> 0 | K43: =SUMIFS(INDIRECT(K$5&"!N:N"),INDIRECT(K$5&"!L:L"),$E43,INDIRECT(K$5&"!K:K"),50)-SUMIFS(INDIRECT(K$5&"!N:N"),INDIRECT(K$5&"!L:L"),$E43,INDIRECT(K$5&"!K:K"),40) -> 0 | L43: =SUMIFS(INDIRECT(L$5&"!N:N"),INDIRECT(L$5&"!L:L"),$E43,INDIRECT(L$5&"!K:K"),50)-SUMIFS(INDIRECT(L$5&"!N:N"),INDIRECT(L$5&"!L:L"),$E43,INDIRECT(L$5&"!K:K"),40) -> 0 | M43: =SUMIFS(INDIRECT(M$5&"!N:N"),INDIRECT(M$5&"!L:L"),$E43,INDIRECT(M$5&"!K:K"),50)-SUMIFS(INDIRECT(M$5&"!N:N"),INDIRECT(M$5&"!L:L"),$E43,INDIRECT(M$5&"!K:K"),40) -> 0 | N43: =SUMIFS(INDIRECT(N$5&"!N:N"),INDIRECT(N$5&"!L:L"),$E43,INDIRECT(N$5&"!K:K"),50)-SUMIFS(INDIRECT(N$5&"!N:N"),INDIRECT(N$5&"!L:L"),$E43,INDIRECT(N$5&"!K:K"),40) -> 0 | O43: =SUMIFS(INDIRECT(O$5&"!N:N"),INDIRECT(O$5&"!L:L"),$E43,INDIRECT(O$5&"!K:K"),50)-SUMIFS(INDIRECT(O$5&"!N:N"),INDIRECT(O$5&"!L:L"),$E43,INDIRECT(O$5&"!K:K"),40) -> 0 | P43: =SUMIFS(INDIRECT(P$5&"!N:N"),INDIRECT(P$5&"!L:L"),$E43,INDIRECT(P$5&"!K:K"),50)-SUMIFS(INDIRECT(P$5&"!N:N"),INDIRECT(P$5&"!L:L"),$E43,INDIRECT(P$5&"!K:K"),40) -> 0 | ... T43: =SUMIFS(INDIRECT(T$5&"!N:N"),INDIRECT(T$5&"!L:L"),$E43,INDIRECT(T$5&"!K:K"),50)-SUMIFS(INDIRECT(T$5&"!N:N"),INDIRECT(T$5&"!L:L"),$E43,INDIRECT(T$5&"!K:K"),40) -> 0 | U43: {=INDEX($I43:$T43,$U$2)} -> 0 | X43: =U43+V43-W43 -> 0 | Z43: {=IFERROR(U43/OFFSET($H43,,MATCH($G$2,$H$5:$U$5,0)-2,,),"-")} -> 0 | AA43: {=U43-OFFSET($H43,,MATCH($G$2,$H$5:$U$5,0)-2,,)} -> -55.29 | AD43: {=IFERROR(U43/OFFSET($AT43,,MATCH($G$2,$AT$5:$BE$5,0)-1,,),"-")} -> - | AE43: {=U43-OFFSET($AT43,,MATCH($G$2,$AT$5:$BE$5,0)-1,,)} -> 0 | AI43: =H43/PrvMonthProductionRRT -> 0.071793679 | AL43: =SUM(I43:T43) -> 0 | AM43: {=INDEX($BG$8:$BQ$83,ROW()-7,MATCH($G$3,$BG$5:$BQ$5,0))} -> #N/A | AN43: =AL43-AM43 -> #N/A | AO43: =IFERROR(AL43/AM43,"") | AR43: =BQ43-AL43 -> 140 | AT43: 0 | AU43: 0 | AV43: 100 | AW43: 0 | AX43: 0 | AY43: 20 | AZ43: 0 | BA43: 0 | BB43: 0 | BC43: 20 | BD43: 0 | BE43: 0 | BG43: =SUM(AT43:AU43) -> 0 | BH43: =SUM(AT43:AV43) -> 100 | BI43: =SUM(AT43:AW43) -> 100 | BJ43: =SUM(AT43:AX43) -> 100 | BK43: =SUM(AT43:AY43) -> 120 | BL43: =SUM(AT43:AZ43) -> 120 | BM43: =SUM(AT43:BA43) -> 120 | BN43: =SUM(AT43:BB43) -> 120 | BO43: =SUM(AT43:BC43) -> 140 | BP43: =SUM(AT43:BD43) -> 140 | BQ43: =SUM(AT43:BE43) -> 140
